Workbook
Name _Hlk61886961: CAMPOS!$D$54
Name _TIPO: TblTIPOS_RETRIB[Nombre]
Name AGR_CL_EMP: TblAGR_CL_EMP[AGRUP. CLAS. PROF. ]
Name AGR_VAL_PTO: TblAGR_VAL_PTO[AGRUP. VALOR. PTO]
Name DATOS: DATOS_[]
Name rngAnualizable: DATOS!$AE$5:$CG$5
Name rngNombre: DATOS!$AG$6:$CG$6
Name rngNormalizable: DATOS!$AE$4:$CG$4
Name RngTipo: DATOS!$AE$3:$CG$3
Name TblRngEdad: CONTRATOS!$M$5:$N$14

Sheet Inicio
B6: Razón Social: | C6: TANATORIOS DE CORDOBA, SA/Convenio Colectivo de Sector de POMPAS FUNEBRES (14000425011981) de Córdoba
B8: NIF: | C8: A14087548
B10: PERIODO DE REFERENCIA | D10: fecha inicio | E10: 45292 | F10: fecha fin | G10: 45657
B16: TABLAS DEL REGISTRO RETRIBUTIVO
B22: TABLAS ADICIONALES PARA EMPRESAS QUE REALICEN AUDITORÍA RETRIBUTIVA (TRABAJOS DE IGUAL VALOR)

Sheet CAMPOS
D3: CAMPO | E3: Tipo | F3: Reg. | G3: Descripción | H3: Formato | I3: Valores permitidos
F4: Ret.
D5: id | E5: PERSONA | F5: x | G5: Identificador único para cada persona trabajadora. | H5: Número entero
D6: Sexo | E6: PERSONA | F6: x | G6: Sexo de la persona trabajadora. | H6: Texto | I6: Hombre / Mujer
D7: Fecha Nacimiento | E7: PERSONA | G7: Fecha de nacimiento de la persona trabajadora. | H7: Fecha | I7: dd-mm-aa
D8: Nivel de Estudios | E8: PERSONA | G8: Nivel académico actual de la persona trabajadora. | H8: Texto
D9: Situación Familiar | E9: PERSONA | G9: Situación familiar conforme a MODELO 145 AEAT. | H9: Número entero | I9: conforme a MODELO 145 AEAT
D10: Hijos/as | E10: PERSONA | G10: Número de hijos/as de la persona trabajadora, conforme a MODELO 145 AEAT. | H10: Número entero
D11: Fecha de Contratación | E11: SITUACION CONTRACTUAL | F11: x | G11: Fecha de contratación. Se emplea exclusivamente en el caso de contrataciones con fecha posterior al inicio del periodo de referencia. Si es anterior, puede dejarse en blanco. 1/1/1900 = 0. | H11: Fecha | I11: dd-mm-aa
D12: Fecha fin contrato | E12: SITUACION CONTRACTUAL | F12: x | G12: Fecha de fin del contrato. Se emplea exclusivamente en el caso de contrataciones finalizadas antes del fin del periodo de referencia. Si es posterior, puede dejarse en blanco. 1/1/1900 = 0. | H12: Fecha | I12: dd-mm-aa
D13: Fecha de Antigüedad | E13: SITUACION CONTRACTUAL | G13: Fecha que aplica a efectos de cálculo de antigüedad (puede o no coincidir con la fecha de contratación). | H13: Fecha | I13: dd-mm-aa
D14: Fecha Inicio Sit. Contract. | E14: SITUACION CONTRACTUAL | F14: x | G14: Fecha de inicio de la Situación contractual. Se emplea exclusivamente en el caso de inicio de Situación contractual con fecha posterior al inicio del periodo de referencia. Si es anterior, puede dejarse en blanco. 1/1/1900 = 0. | H14: Fecha | I14: dd-mm-aa
D15: Fecha Fin Sit. Contract. | E15: SITUACION CONTRACTUAL | F15: x | G15: Fecha de fin de la Situación contractual. Se emplea exclusivamente en el caso de fin de Situación contractual con fecha anterior al fin del periodo de referencia. Si es posterior, puede dejarse en blanco. 1/1/1900 = 0. | H15: Fecha | I15: dd-mm-aa
D16: % de jornada | E16: SITUACION CONTRACTUAL | F16: x | G16: % de jornada realizada por la persona en el periodo de referencia y Situación contractual, considerando 100% como jornada completa, y sin considerar las reducciones de jornada. Si el % ha variado a lo largo del periodo de referencia, deberá asegurarse que para el periodo indicado (inicio y fin de contrato que se indique), el % de jornada sea constante, y que los importes de retribución son igualmente consistentes con ese %. | H16: Porcentaje | I16: %
D17: % jornada reducida | E17: SITUACION CONTRACTUAL | F17: x | G17: Medido en relación a la jornada por contrato en la Situación contractual. Ejemplo: si una persona con contrato a tiempo completo reduce 1/3 su jornada, el % a indicar será el 66,67%. Si una persona con contrato a tiempo parcial del 50% se reduce la jornada en 1/3, el % a indicar será también del 66,67%. Dejar en blanco si no hay reducción de jornada. | H17: Porcentaje | I17: %
D18: motivo reducción | E18: SITUACION CONTRACTUAL | G18: Motivo de Reducción de Jornada (dejar en blanco si no hay reducción de jornada) en la Situación contractual. | H18: Texto | I18: ver tabla "Motivo reducción de jornada"
D19: Clave de Contrato | E19: SITUACION CONTRACTUAL | G19: Clave del contrato actual de la persona trabajadora en la Situación contractual, de acuerdo a los códigos de la Seguridad Social. | H19: Número entero | I19: ver tabla "Clave de Contrato"
D20: Area-empresa | E20: PUESTO ACTUAL | G20: Área de la empresa en la que trabaja la persona en la Situación contractual. Si resulta útil, puede emplearse este campo y el siguiente para reflejar cualquier otra organización de la empresa (centro de trabajo, división, dirección territorial, etc.). | H20: Texto | I20: los de la empresa
D21: Dpto-empresa | E21: PUESTO ACTUAL | G21: Departamento actual de la persona trabajadora en la Situación contractual. | H21: Texto | I21: los de la empresa
D22: Puesto-empresa | E22: PUESTO ACTUAL | F22: x | G22: Puesto actual de la persona trabajadora en la Situación Contractual. Para una mejor visualización de los datos, se recomienda utilizar una nomenclatura con denominaciones breves. | H22: Texto | I22: los de la empresa
D23: Horario (continuo/ partido) | E23: PUESTO ACTUAL | G23: Indica el tipo de horario que realiza en la Situación Contractual. | H23: Texto | I23: continuo/partido
D24: Trabajo a turnos | E24: PUESTO ACTUAL | G24: Indica si realiza o no trabajo a turnos en la Situación Contractual. | H24: Texto | I24: Sí/No
D25: Escala-empresa | E25: PUESTO ACTUAL | F25: X | G25: Escala actual de la persona trabajadora en la Situación Contractual, conforme a la escala de mando vigente en la empresa. | H25: Texto | I25: los de la empresa
D26: AGRUP. CLAS. PROF. | E26: PUESTO ACTUAL | F26: x | G26: Agrupación en la que queda agrupada la persona en su Situación Contractual según la clasificación profesional de la empresa de acuerdo con el Convenio de aplicación. Se nombrarán necesariamente como GRUPO 01, GRUPO 02, etc., hasta un máximo de 30. Se recomienda que este orden esté relacionado con la jerarquía dentro de las empresas. Esta agrupación es la que se emplea en las TABLAS DEL REGISTRO RETRIBUTIVO | H26: Texto | I26: GRUPO 01, GRUPO 02, … hasta GRUPO 30 (máximo)
D27: AGRUP. VALOR. PTO. | E27: PUESTO ACTUAL | F27: (x) | G27: Agrupación en la que queda agrupada la persona en su Situación Contractual según la valoración su puesto de trabajo (solamente para empresas con auditoría retributiva). Se nombrarán necesariamente como ESCALA 01, ESCALA 02, etc., hasta un máximo de 30. Se recomienda que este orden esté relacionado el valor de los puestos agrupados en esa ESCALA. Esta agrupación es la que se emplea en las TABLAS ADICIONALES PARA EMPRESAS QUE REALICEN AUDITORÍA RERIBUTIVA (TRABAJOS DE IGUAL VALOR) | H27: Texto | I27: ESCALA 01, ESCALA 02…, hasta ESCALA 30 (máximo)
D28: Convenio/Área | E28: CONTRATO-CONVENIO | F28: x | G28: Convenio de aplicación de cada contrato. No hace falta incluir el nº completo del convenio, basta una nomenclatura suficiente para identificarlo. En convenios con varias Áreas, indicar conjuntamente el Área para cada caso. | H28: Texto | I28: los del convenio y contrato
D29: Categoría profesional | E29: CONTRATO-CONVENIO | F29: (x) | G29: Categoría profesional que corresponde a la persona en su Situación Contractual, conforme al Convenio. (Puede ser que el Convenio de referencia no utilice Categorías, sino Grupos, ver abajo). | H29: Texto | I29: los del convenio y contrato
D30: Grupo profesional | E30: CONTRATO-CONVENIO | F30: x | G30: Grupo profesional que corresponde a la persona en su Situación Contractual, conforme al Convenio. | H30: Texto | I30: los del convenio y contrato
D31: Nivel | E31: CONTRATO-CONVENIO | F31: X | G31: Nivel (retributivo) que corresponde a la persona en su Situación Contractual, conforme al Convenio. | H31: Texto | I31: los del convenio y contrato
D32: Grupo de Cotización Seg.Social. | E32: SEG-SOCIAL | G32: Grupo de cotización de la Seguridad Social. | H32: Número entero | I32: ver aquí
D33: S.BASE | E33: RETRIBUCION | F33: x | G33: Salario base de la persona (sumatorio de importes correspondiente al periodo de referencia y Situación Contractual). Se deben añadir las pagas extraordinarias percibidas. | H33: Moneda
D34: Conc.Sal.01 | E34: RETRIBUCION | F34: x | G34: Concepto Salarial 01. A determinar por la organización (sumatorio de importes correspondiente al periodo de referencia y Situación Contractual). | H34: Moneda
D35: Conc.Sal.02 | E35: RETRIBUCION | F35: x | G35: Concepto Salarial 02. A determinar por la organización (sumatorio de importes correspondiente al periodo de referencia y Situación Contractual) | H35: Moneda
D36: Conc.Sal.03 | E36: RETRIBUCION | F36: x | G36: Concepto Salarial 03. A determinar por la organización (sumatorio de importes correspondiente al periodo de referencia y Situación Contractual). | H36: Moneda
D37: Conc.Sal.04 | E37: RETRIBUCION | F37: x | G37: Concepto Salarial 04. A determinar por la organización (sumatorio de importes correspondiente al periodo de referencia y Situación Contractual). | H37: Moneda
D38: Conc.Sal.05 | E38: RETRIBUCION | F38: x | G38: Concepto Salarial 05. A determinar por la organización (sumatorio de importes correspondiente al periodo de referencia y Situación Contractual).. | H38: Moneda
D39: … | E39: … | F39: … | G39: …
D40: Conc.Sal.30 | E40: RETRIBUCION | F40: x | G40: Concepto Salarial 30. A determinar por la organización (sumatorio de importes correspondiente al periodo de referencia y Situación Contractual). | H40: Moneda
D41: C.Extra.01 | E41: RETRIBUCION | F41: x | G41: Concepto Extrasalarial 01. A determinar por la organización (sumatorio de importes correspondiente al periodo de referencia y Situación Contractual). | H41: Moneda
D42: … | E42: … | F42: … | G42: … | H42: Moneda
D43: C.Extra.05 | E43: RETRIBUCION | F43: x | G43: Concepto Extrasalarial 05. A determinar por la organización (sumatorio de importes correspondiente al periodo de referencia y Situación Contractual). | H43: Moneda
D44: F.ini.cal | E44: CAMPO CALCULADO | G44: Fecha de inicio considerada a efectos de cálculo de la anualización de importes para su equiparación. | H44: Fecha | I44: dd-mm-aa
D45: F.fin.cal | E45: CAMPO CALCULADO | G45: Fecha de fin considerada a efectos de cálculo de la anualización de importes para su equiparación. | H45: Fecha | I45: dd-mm-aa
D46: % normaliz | E46: CAMPO CALCULADO | G46: % de jornada efectiva, calculada como producto del % de jornada y el % de jornada reducida reseñados. Se usa para la normalización de las retribuciones para su equiparación. | H46: Porcentaje | I46: %
D47: % anualiz | E47: CAMPO CALCULADO | G47: % del Periodo de Referencia en que ha estado activa la Situación Contractual, calculada como diferencia entre la F.fin.cal menos la F.ini.cal. Se usa para la anualización de las retribuciones para su equiparación. | H47: Porcentaje | I47: %
D48: Check Periodo Ref. | E48: CAMPO CALCULADO | G48: Campo que chequea si la Situación Contractual de la ficha está activa durante el periodo de referencia | H48: Texto | I48: Dentro / Fuera
D49: Check Equiparado | E49: CAMPO CALCULADO | G49: Campo que chequea si la Situación Contractual es considerada a los efectos de cálculo de importes equiparados. NOTA: para los importes equiparados se emplea una sola Situación Contractual, la última del periodo de referencia. | H49: Texto | I49: Sí / NO
D50: Check Nº SC Norm | E50: CAMPO CALCULADO | G50: Campo que chequea si los importes de la Situación Contractual son objeto solamente de Normalización. | H50: Texto | I50: Sí / NO
D51: Check Nº SC Anualiz | E51: CAMPO CALCULADO | G51: Campo que chequea si los importes de la Situación Contractual son objeto solamente de Anualización. | H51: Texto | I51: Sí / NO
D52: Check Nº SC Norm y Anualiz | E52: CAMPO CALCULADO | G52: Campo que chequea si los importes de la Situación Contractual son objeto solamente de Normalización y también de Anualización. | H52: Texto | I52: Sí / NO
D53: Check Equiparación | E53: CAMPO CALCULADO | G53: Campo que chequea si los importes de esa Situación Contractual son objeto o no de equiparación. | H53: Texto | I53: Sí / NO
D54: SALARIO BASE EQ | E54: CAMPO CALCULADO | G54: Salario Base equiparado, esto es, ajustado al 100% de jornada (Normalizado), y ajustado al 100% del periodo de referencia (Anualizado). | H54: Moneda
D55: Tot COMPL.SAL EQ | E55: CAMPO CALCULADO | G55: Sumatorio de Complementos Salariales equiparados, esto es, ajustados al 100% de jornada (Normalizado), y ajustados al 100% del periodo de referencia (Anualizado), si es que procede conforme se indique en la Tabla de CONCEPTROS RETRIBUTIVOS (columnas "Normalizable" y "Anualizable"). | H55: Moneda
D56: TOTAL SALARIO EQ | E56: CAMPO CALCULADO | G56: Suma de SALARIO BASE Eq + Tot COMPL.SAL Eq | H56: Moneda
D57: Tot Extrasalarial EQ | E57: CAMPO CALCULADO | G57: Sumatorio de Complementos Extrasalariales equiparados, esto es, ajustados al 100% de jornada (Normalizado), y ajustados al 100% del periodo de referencia (Anualizado), si es que procede conforme se indique en la Tabla de CONCEPTROS RETRIBUTIVOS (columnas "Normalizable" y "Anualizable"). | H57: Moneda
D58: TOTAL Retrib EQ | E58: CAMPO CALCULADO | G58: Suma de TOTAL SALARIO Eq + Tot Extrasalarial Eq | H58: Moneda
D59: SALARIO BASE Ef | E59: CAMPO CALCULADO | G59: Salario Base efectivo, conforme reportado. | H59: Moneda
D60: Tot COMPL.SAL Ef | E60: CAMPO CALCULADO | G60: Sumatorio de Complementos Salariales efectivos, conforme reportados. | H60: Moneda
D61: TOTAL SALARIO Ef | E61: CAMPO CALCULADO | G61: Suma de Salario Base efectivo + Total complementos salariales efectivos | H61: Moneda
D62: Tot Extrasalarial Ef | E62: CAMPO CALCULADO | G62: Sumatorio de Complementos Extrasalariales efectivos, conforme reportados. | H62: Moneda
D63: TOTAL Retrib Ef | E63: CAMPO CALCULADO | G63: Suma de TOTAL SALARIO Ef + Tot Extrasalarial Ef | H63: Moneda

Sheet CONC.RETR
B2: TABLA DE CONCEPTOS RETRIBUTIVOS
E4: Form. Retrib. | G4: Tipo de Retribución
E6: Retrib | G6: Nombre
E7: Dinero | G7: Salario Base
E8: En especie | G8: Comp. Salarial
G9: Extrasalarial
B11: Valor | C11: Nombre Corto | D11: Descripción | E11: Retrib | F11: Tipo | G11: Normalizable | H11: Anualizable | J11: AGRUP. CLAS. PROF. | L11: AGRUP. VALOR. PTO
B12: S.BASE | C12: S.BASE | D12: SALARIO BASE | E12: Dinero | F12: Salario Base | G12: Sí | H12: Sí | J12: GRUPO 01 | L12: ESCALA 01
B13: Conc.Sal.01 | C13: HORAS EXTRAS | D13: HORAS EXTRAS ORDINARIAS | E13: Dinero | F13: Comp. Salarial | G13: Sí | H13: Sí | J13: GRUPO 02 | L13: ESCALA 02
B14: Conc.Sal.02 | C14: SEGURO CONVENIO | D14: SEGURO CONVENIO | E14: Dinero | F14: Comp. Salarial | G14: Sí | H14: Sí | J14: GRUPO 03 | L14: ESCALA 03
B15: Conc.Sal.03 | C15: PLUS UNIFICADO | D15: PLUS UNIFICADO | E15: Dinero | F15: Comp. Salarial | G15: Sí | H15: Sí | J15: GRUPO 04 | L15: ESCALA 04
B16: Conc.Sal.04 | C16: GARANTIA AD PERS | D16: GARANTIA AD PERSONAM | E16: Dinero | F16: Comp. Salarial | G16: Sí | H16: Sí | J16: GRUPO 05 | L16: ESCALA 05
B17: Conc.Sal.05 | C17: COMISIONES | D17: COMISIONES | E17: Dinero | F17: Comp. Salarial | G17: Sí | H17: Sí | J17: GRUPO 06 | L17: ESCALA 06
B18: Conc.Sal.06 | C18: DOMINGOS Y FESTIVOS | D18: DOMINGOS Y FESTIVOS | E18: Dinero | F18: Comp. Salarial | G18: Sí | H18: Sí | J18: GRUPO 07 | L18: ESCALA 07
B19: Conc.Sal.07 | C19: LOCOMOCION NO | D19: LOCOMOCION NO | E19: Dinero | F19: Comp. Salarial | G19: Sí | H19: Sí | J19: GRUPO 08 | L19: ESCALA 08
B20: Conc.Sal.08 | C20: PLUS EXTRA VAC | D20: PLUS EXTRA VACACIONES | E20: Dinero | F20: Comp. Salarial | G20: Sí | H20: Sí | J20: GRUPO 09 | L20: ESCALA 09
B21: Conc.Sal.09 | C21: PLUS DE TRANS | D21: PLUS DE TRANSPORTE | E21: Dinero | F21: Comp. Salarial | G21: Sí | H21: Sí | J21: GRUPO 10 | L21: ESCALA 10
B22: Conc.Sal.10 | C22: PLUS ACTIVIDAD | D22: PLUS ACTIVIDAD | E22: Dinero | F22: Comp. Salarial | G22: Sí | H22: Sí | J22: GRUPO 11 | L22: ESCALA 11
... B33: Conc.Sal.21 | C33: LIQUID PAGAS EXTRA | D33: LIQUIDACION DE PAGAS EXTRAORDINARIAS | E33: Dinero | F33: Comp. Salarial | G33: Sí | H33: Sí | J33: GRUPO 22 | L33: ESCALA 22
B34: Conc.Sal.22 | J34: GRUPO 23 | L34: ESCALA 23
B35: Conc.Sal.23 | J35: GRUPO 24 | L35: ESCALA 24
B36: Conc.Sal.24 | J36: GRUPO 25 | L36: ESCALA 25
B37: Conc.Sal.25 | J37: GRUPO 26 | L37: ESCALA 26
B38: Conc.Sal.26 | J38: GRUPO 27 | L38: ESCALA 27
B39: Conc.Sal.27 | J39: GRUPO 28 | L39: ESCALA 28
B40: Conc.Sal.28 | J40: GRUPO 29 | L40: ESCALA 29
B41: Conc.Sal.29 | J41: GRUPO 30 | L41: ESCALA 30
B42: Conc.Sal.30
B43: Conc.Sal.31
B44: Conc.Sal.32
B45: Conc.Sal.33
B46: Conc.Sal.34
B47: Conc.Sal.35
B48: Conc.Sal.36
B49: Conc.Sal.37
B50: Conc.Sal.38
B51: Conc.Sal.39
B52: Conc.Sal.40
B53: Conc.Sal.41
... B67: C.Extra.11

Sheet DATOS
C2: PERIODO DE REFERENCIA
C3: fecha inicio | D3: =+Inicio!E10 -> 45292 | AB3: 5 | AC3: Tipo | AD3: =IFERROR(IF(VLOOKUP(AD$8,TblComplem[],$AB3,FALSE)=0,"",VLOOKUP(AD$8,TblComplem[],$AB3,FALSE)),"") -> Salario Base | AE3: =IFERROR(IF(VLOOKUP(AE$8,TblComplem[],$AB3,FALSE)=0,"",VLOOKUP(AE$8,TblComplem[],$AB3,FALSE)),"") -> Comp. Salarial | AF3: =IFERROR(IF(VLOOKUP(AF$8,TblComplem[],$AB3,FALSE)=0,"",VLOOKUP(AF$8,TblComplem[],$AB3,FALSE)),"") -> Comp. Salarial | AG3: =IFERROR(IF(VLOOKUP(AG$8,TblComplem[],$AB3,FALSE)=0,"",VLOOKUP(AG$8,TblComplem[],$AB3,FALSE)),"") -> Comp. Salarial | AH3: =IFERROR(IF(VLOOKUP(AH$8,TblComplem[],$AB3,FALSE)=0,"",VLOOKUP(AH$8,TblComplem[],$AB3,FALSE)),"") -> Comp. Salarial | AI3: =IFERROR(IF(VLOOKUP(AI$8,TblComplem[],$AB3,FALSE)=0,"",VLOOKUP(AI$8,TblComplem[],$AB3,FALSE)),"") -> Comp. Salarial | AJ3: =IFERROR(IF(VLOOKUP(AJ$8,TblComplem[],$AB3,FALSE)=0,"",VLOOKUP(AJ$8,TblComplem[],$AB3,FALSE)),"") -> Comp. Salarial | AK3: =IFERROR(IF(VLOOKUP(AK$8,TblComplem[],$AB3,FALSE)=0,"",VLOOKUP(AK$8,TblComplem[],$AB3,FALSE)),"") -> Comp. Salarial | ... BJ3: =IFERROR(IF(VLOOKUP(BJ$8,TblComplem[],$AB3,FALSE)=0,"",VLOOKUP(BJ$8,TblComplem[],$AB3,FALSE)),"") | BP3: =IFERROR(IF(VLOOKUP(BP$8,TblComplem[],$AB3,FALSE)=0,"",VLOOKUP(BP$8,TblComplem[],$AB3,FALSE)),"") | BQ3: =IFERROR(IF(VLOOKUP(BQ$8,TblComplem[],$AB3,FALSE)=0,"",VLOOKUP(BQ$8,TblComplem[],$AB3,FALSE)),"") | BR3: =IFERROR(IF(VLOOKUP(BR$8,TblComplem[],$AB3,FALSE)=0,"",VLOOKUP(BR$8,TblComplem[],$AB3,FALSE)),"") | BS3: =IFERROR(IF(VLOOKUP(BS$8,TblComplem[],$AB3,FALSE)=0,"",VLOOKUP(BS$8,TblComplem[],$AB3,FALSE)),"") | BW3: =IFERROR(IF(VLOOKUP(BW$8,TblComplem[],$AB3,FALSE)=0,"",VLOOKUP(BW$8,TblComplem[],$AB3,FALSE)),"") | CB3: =IFERROR(IF(VLOOKUP(CB$8,TblComplem[],$AB3,FALSE)=0,"",VLOOKUP(CB$8,TblComplem[],$AB3,FALSE)),"") | CC3: =IFERROR(IF(VLOOKUP(CC$8,TblComplem[],$AB3,FALSE)=0,"",VLOOKUP(CC$8,TblComplem[],$AB3,FALSE)),"") | CD3: =IFERROR(IF(VLOOKUP(CD$8,TblComplem[],$AB3,FALSE)=0,"",VLOOKUP(CD$8,TblComplem[],$AB3,FALSE)),"") | CG3: =IFERROR(IF(VLOOKUP(CG$8,TblComplem[],$AB3,FALSE)=0,"",VLOOKUP(CG$8,TblComplem[],$AB3,FALSE)),"") | CJ3: Nº SC Norm | CK3: cuando % norm difer 100% y % anualiz es 100%
C4: fecha fin | D4: =+Inicio!G10 -> 45657 | AB4: 6 | AC4: Normalizable | AD4: =IFERROR(IF(VLOOKUP(AD$8,TblComplem[],$AB4,FALSE)=0,"",VLOOKUP(AD$8,TblComplem[],$AB4,FALSE)),"") -> Sí | AE4: =IFERROR(IF(VLOOKUP(AE$8,TblComplem[],$AB4,FALSE)=0,"",VLOOKUP(AE$8,TblComplem[],$AB4,FALSE)),"") -> Sí | AF4: =IFERROR(IF(VLOOKUP(AF$8,TblComplem[],$AB4,FALSE)=0,"",VLOOKUP(AF$8,TblComplem[],$AB4,FALSE)),"") -> Sí | AG4: =IFERROR(IF(VLOOKUP(AG$8,TblComplem[],$AB4,FALSE)=0,"",VLOOKUP(AG$8,TblComplem[],$AB4,FALSE)),"") -> Sí | AH4: =IFERROR(IF(VLOOKUP(AH$8,TblComplem[],$AB4,FALSE)=0,"",VLOOKUP(AH$8,TblComplem[],$AB4,FALSE)),"") -> Sí | AI4: =IFERROR(IF(VLOOKUP(AI$8,TblComplem[],$AB4,FALSE)=0,"",VLOOKUP(AI$8,TblComplem[],$AB4,FALSE)),"") -> Sí | AJ4: =IFERROR(IF(VLOOKUP(AJ$8,TblComplem[],$AB4,FALSE)=0,"",VLOOKUP(AJ$8,TblComplem[],$AB4,FALSE)),"") -> Sí | AK4: =IFERROR(IF(VLOOKUP(AK$8,TblComplem[],$AB4,FALSE)=0,"",VLOOKUP(AK$8,TblComplem[],$AB4,FALSE)),"") -> Sí | ... BJ4: =IFERROR(IF(VLOOKUP(BJ$8,TblComplem[],$AB4,FALSE)=0,"",VLOOKUP(BJ$8,TblComplem[],$AB4,FALSE)),"") | BP4: =IFERROR(IF(VLOOKUP(BP$8,TblComplem[],$AB4,FALSE)=0,"",VLOOKUP(BP$8,TblComplem[],$AB4,FALSE)),"") | BQ4: =IFERROR(IF(VLOOKUP(BQ$8,TblComplem[],$AB4,FALSE)=0,"",VLOOKUP(BQ$8,TblComplem[],$AB4,FALSE)),"") | BR4: =IFERROR(IF(VLOOKUP(BR$8,TblComplem[],$AB4,FALSE)=0,"",VLOOKUP(BR$8,TblComplem[],$AB4,FALSE)),"") | BS4: =IFERROR(IF(VLOOKUP(BS$8,TblComplem[],$AB4,FALSE)=0,"",VLOOKUP(BS$8,TblComplem[],$AB4,FALSE)),"") | BW4: =IFERROR(IF(VLOOKUP(BW$8,TblComplem[],$AB4,FALSE)=0,"",VLOOKUP(BW$8,TblComplem[],$AB4,FALSE)),"") | CB4: =IFERROR(IF(VLOOKUP(CB$8,TblComplem[],$AB4,FALSE)=0,"",VLOOKUP(CB$8,TblComplem[],$AB4,FALSE)),"") | CC4: =IFERROR(IF(VLOOKUP(CC$8,TblComplem[],$AB4,FALSE)=0,"",VLOOKUP(CC$8,TblComplem[],$AB4,FALSE)),"") | CD4: =IFERROR(IF(VLOOKUP(CD$8,TblComplem[],$AB4,FALSE)=0,"",VLOOKUP(CD$8,TblComplem[],$AB4,FALSE)),"") | CG4: =IFERROR(IF(VLOOKUP(CG$8,TblComplem[],$AB4,FALSE)=0,"",VLOOKUP(CG$8,TblComplem[],$AB4,FALSE)),"") | CJ4: Nº SC Anualiz
C5: días | D5: =D4-D3+1 -> 366 | AB5: 7 | AC5: Anualizable | AD5: =IFERROR(IF(VLOOKUP(AD$8,TblComplem[],$AB5,FALSE)=0,"",VLOOKUP(AD$8,TblComplem[],$AB5,FALSE)),"") -> Sí | AE5: =IFERROR(IF(VLOOKUP(AE$8,TblComplem[],$AB5,FALSE)=0,"",VLOOKUP(AE$8,TblComplem[],$AB5,FALSE)),"") -> Sí | AF5: =IFERROR(IF(VLOOKUP(AF$8,TblComplem[],$AB5,FALSE)=0,"",VLOOKUP(AF$8,TblComplem[],$AB5,FALSE)),"") -> Sí | AG5: =IFERROR(IF(VLOOKUP(AG$8,TblComplem[],$AB5,FALSE)=0,"",VLOOKUP(AG$8,TblComplem[],$AB5,FALSE)),"") -> Sí | AH5: =IFERROR(IF(VLOOKUP(AH$8,TblComplem[],$AB5,FALSE)=0,"",VLOOKUP(AH$8,TblComplem[],$AB5,FALSE)),"") -> Sí | AI5: =IFERROR(IF(VLOOKUP(AI$8,TblComplem[],$AB5,FALSE)=0,"",VLOOKUP(AI$8,TblComplem[],$AB5,FALSE)),"") -> Sí | AJ5: =IFERROR(IF(VLOOKUP(AJ$8,TblComplem[],$AB5,FALSE)=0,"",VLOOKUP(AJ$8,TblComplem[],$AB5,FALSE)),"") -> Sí | AK5: =IFERROR(IF(VLOOKUP(AK$8,TblComplem[],$AB5,FALSE)=0,"",VLOOKUP(AK$8,TblComplem[],$AB5,FALSE)),"") -> Sí | ... BJ5: =IFERROR(IF(VLOOKUP(BJ$8,TblComplem[],$AB5,FALSE)=0,"",VLOOKUP(BJ$8,TblComplem[],$AB5,FALSE)),"") | BP5: =IFERROR(IF(VLOOKUP(BP$8,TblComplem[],$AB5,FALSE)=0,"",VLOOKUP(BP$8,TblComplem[],$AB5,FALSE)),"") | BQ5: =IFERROR(IF(VLOOKUP(BQ$8,TblComplem[],$AB5,FALSE)=0,"",VLOOKUP(BQ$8,TblComplem[],$AB5,FALSE)),"") | BR5: =IFERROR(IF(VLOOKUP(BR$8,TblComplem[],$AB5,FALSE)=0,"",VLOOKUP(BR$8,TblComplem[],$AB5,FALSE)),"") | BS5: =IFERROR(IF(VLOOKUP(BS$8,TblComplem[],$AB5,FALSE)=0,"",VLOOKUP(BS$8,TblComplem[],$AB5,FALSE)),"") | BW5: =IFERROR(IF(VLOOKUP(BW$8,TblComplem[],$AB5,FALSE)=0,"",VLOOKUP(BW$8,TblComplem[],$AB5,FALSE)),"") | CB5: =IFERROR(IF(VLOOKUP(CB$8,TblComplem[],$AB5,FALSE)=0,"",VLOOKUP(CB$8,TblComplem[],$AB5,FALSE)),"") | CC5: =IFERROR(IF(VLOOKUP(CC$8,TblComplem[],$AB5,FALSE)=0,"",VLOOKUP(CC$8,TblComplem[],$AB5,FALSE)),"") | CD5: =IFERROR(IF(VLOOKUP(CD$8,TblComplem[],$AB5,FALSE)=0,"",VLOOKUP(CD$8,TblComplem[],$AB5,FALSE)),"") | CG5: =IFERROR(IF(VLOOKUP(CG$8,TblComplem[],$AB5,FALSE)=0,"",VLOOKUP(CG$8,TblComplem[],$AB5,FALSE)),"") | CJ5: Nº SC Norm y Anualiz
AB6: 2 | AC6: Nombre Corto | AD6: =IFERROR(IF(VLOOKUP(AD$8,TblComplem[],$AB6,FALSE)=0,"",VLOOKUP(AD$8,TblComplem[],$AB6,FALSE)),"") -> S.BASE | AE6: =IFERROR(IF(VLOOKUP(AE$8,TblComplem[],$AB6,FALSE)=0,"",VLOOKUP(AE$8,TblComplem[],$AB6,FALSE)),"") -> HORAS EXTRAS | AF6: =IFERROR(IF(VLOOKUP(AF$8,TblComplem[],$AB6,FALSE)=0,"",VLOOKUP(AF$8,TblComplem[],$AB6,FALSE)),"") -> SEGURO CONVENIO | AG6: =IFERROR(IF(VLOOKUP(AG$8,TblComplem[],$AB6,FALSE)=0,"",VLOOKUP(AG$8,TblComplem[],$AB6,FALSE)),"") -> PLUS UNIFICADO | AH6: =IFERROR(IF(VLOOKUP(AH$8,TblComplem[],$AB6,FALSE)=0,"",VLOOKUP(AH$8,TblComplem[],$AB6,FALSE)),"") -> GARANTIA AD PERS | AI6: =IFERROR(IF(VLOOKUP(AI$8,TblComplem[],$AB6,FALSE)=0,"",VLOOKUP(AI$8,TblComplem[],$AB6,FALSE)),"") -> COMISIONES | AJ6: =IFERROR(IF(VLOOKUP(AJ$8,TblComplem[],$AB6,FALSE)=0,"",VLOOKUP(AJ$8,TblComplem[],$AB6,FALSE)),"") -> DOMINGOS Y FESTIVOS | AK6: =IFERROR(IF(VLOOKUP(AK$8,TblComplem[],$AB6,FALSE)=0,"",VLOOKUP(AK$8,TblComplem[],$AB6,FALSE)),"") -> LOCOMOCION NO | ... BJ6: =IFERROR(IF(VLOOKUP(BJ$8,TblComplem[],$AB6,FALSE)=0,"",VLOOKUP(BJ$8,TblComplem[],$AB6,FALSE)),"") | BP6: =IFERROR(IF(VLOOKUP(BP$8,TblComplem[],$AB6,FALSE)=0,"",VLOOKUP(BP$8,TblComplem[],$AB6,FALSE)),"") | BQ6: =IFERROR(IF(VLOOKUP(BQ$8,TblComplem[],$AB6,FALSE)=0,"",VLOOKUP(BQ$8,TblComplem[],$AB6,FALSE)),"") | BR6: =IFERROR(IF(VLOOKUP(BR$8,TblComplem[],$AB6,FALSE)=0,"",VLOOKUP(BR$8,TblComplem[],$AB6,FALSE)),"") | BS6: =IFERROR(IF(VLOOKUP(BS$8,TblComplem[],$AB6,FALSE)=0,"",VLOOKUP(BS$8,TblComplem[],$AB6,FALSE)),"") | BW6: =IFERROR(IF(VLOOKUP(BW$8,TblComplem[],$AB6,FALSE)=0,"",VLOOKUP(BW$8,TblComplem[],$AB6,FALSE)),"") | CB6: =IFERROR(IF(VLOOKUP(CB$8,TblComplem[],$AB6,FALSE)=0,"",VLOOKUP(CB$8,TblComplem[],$AB6,FALSE)),"") | CC6: =IFERROR(IF(VLOOKUP(CC$8,TblComplem[],$AB6,FALSE)=0,"",VLOOKUP(CC$8,TblComplem[],$AB6,FALSE)),"") | CD6: =IFERROR(IF(VLOOKUP(CD$8,TblComplem[],$AB6,FALSE)=0,"",VLOOKUP(CD$8,TblComplem[],$AB6,FALSE)),"") | CG6: =IFERROR(IF(VLOOKUP(CG$8,TblComplem[],$AB6,FALSE)=0,"",VLOOKUP(CG$8,TblComplem[],$AB6,FALSE)),"")
CS7: Comp. Salarial | CU7: Extrasalarial
A8: id | B8: id/cod | C8: Sexo | D8: Fecha Nacimiento | E8: Nivel de Estudios | F8: Situación Familiar | G8: Hijos/as | H8: Fecha de Contratación | I8: Fecha Fin Contrato | J8: Fecha de Antigüedad | K8: Fecha Inicio Sit. Contract. | L8: Fecha Fin Sit. Contract. | M8: % de jornada | N8: % jornada reducida | O8: motivo reducción | P8: Clave de Contrato | Q8: Area-empresa | R8: Dpto-empresa | S8: Puesto-empresa | T8: Horario (continuo/partido) | U8: Trabajo a turnos | V8: Escala-empresa | W8: AGRUP. CLAS. PROF. | X8: AGRUP. VALOR. PTO. | Y8: Convenio/Área | Z8: Categoría profesional | AA8: Grupo profesional | AB8: Nivel | AC8: Grupo de Cotización Seg.Social. | AD8: S.BASE | AE8: Conc.Sal.01 | AF8: Conc.Sal.02 | AG8: Conc.Sal.03 | AH8: Conc.Sal.04 | AI8: Conc.Sal.05 | AJ8: Conc.Sal.06 | AK8: Conc.Sal.07 | AL8: Conc.Sal.08 | AM8: Conc.Sal.09 | AN8: Conc.Sal.10 | AO8: Conc.Sal.11 | AP8: Conc.Sal.12 | AQ8: Conc.Sal.13 | AR8: Conc.Sal.14 | AS8: Conc.Sal.15 | AT8: Conc.Sal.16 | AU8: Conc.Sal.17 | AV8: Conc.Sal.18 | AW8: Conc.Sal.19 | AX8: Conc.Sal.20 | AY8: Conc.Sal.21 | AZ8: Conc.Sal.22 | BA8: Conc.Sal.23 | BB8: Conc.Sal.24 | BC8: Conc.Sal.25 | BD8: Conc.Sal.26 | BE8: Conc.Sal.27 | BF8: Conc.Sal.28 | BG8: Conc.Sal.29 | BH8: Conc.Sal.30 | BI8: Conc.Sal.31 | BJ8: Conc.Sal.32 | BK8: Conc.Sal.33 | BL8: Conc.Sal.34 | BM8: Conc.Sal.35 | BN8: Conc.Sal.36 | BO8: Conc.Sal.37 | BP8: Conc.Sal.38 | BQ8: Conc.Sal.39 | BR8: Conc.Sal.40 | BS8: Conc.Sal.41 | BT8: Conc.Sal.42 | BU8: Conc.Sal.43 | BV8: Conc.Sal.44 | BW8: C.Extra.01 | BX8: C.Extra.02 | BY8: C.Extra.03 | BZ8: C.Extra.04 | CA8: C.Extra.05 | CB8: C.Extra.06 | CC8: C.Extra.07 | CD8: C.Extra.08 | CE8: C.Extra.09 | CF8: C.Extra.10 | CG8: C.Extra.11 | CH8: F.ini.cal | CI8: F.fin.cal | CJ8: % normaliz | CK8: % anualiz | CL8: Check Periodo Ref. | CM8: Check Equiparado | CN8: Check Nº SC Norm | CO8: Check Nº SC Anualiz | CP8: Check Nº SC Norm y Anualiz | CQ8: Check Equiparación | CR8: SALARIO BASE Eq | CS8: Tot COMPL.SAL Eq | CT8: TOTAL SALARIO Eq | CU8: Tot Extrasalarial Eq | CV8: TOTAL Retrib Eq | CW8: SALARIO BASE Ef | CX8: Tot COMPL.SAL Ef | CY8: TOTAL SALARIO Ef | CZ8: Tot Extrasalarial Ef | DA8: TOTAL Retrib Ef | DB8: DIAS TRABAJ. EN EL AÑO | DC8: REPET. | DD8: Edad | DE8: Antigüedad | DF8: Jornada | DG8: Contrato | DH8: Intervalo Edad | DI8: Intervalo Antigüedad
A9: RAFAEL MORENO SERRANO | B9: 1 | C9: HOMBRE | D9: 24001 | E9: FPI | H9: 31479 | J9: 31479 | M9: 1 | Q9: CONDUCTORES | R9: CONDUCTORES | S9: CONDUCTOR | T9: CONTINUO | U9: SI | Y9: 14000425011981 | AA9: PERSONAL OPERARIO GENERAL | AC9: 8 | CH9: =+MAX($D$3,DATOS_[[#This Row],[Fecha Inicio Sit. Contract.]]) -> 45292 | CI9: =+MIN($D$4,DATOS_[[#This Row],[Fecha Fin Sit. Contract.]]) -> 45657 | CJ9: =+DATOS_[[#This Row],[% de jornada]]*IF(DATOS_[[#This Row],[% jornada reducida]]="",1,DATOS_[[#This Row],[% jornada reducida]]) -> 1 | CK9: =+(DATOS_[[#This Row],[F.fin.cal]]-DATOS_[[#This Row],[F.ini.cal]]+1)/($D$4-$D$3+1) -> 1 | CL9: =IF(OR(AND(DATOS_[[#This Row],[Fecha Fin Contrato]]<$D$3,DATOS_[[#This Row],[Fecha Fin Contrato]]<>""),DATOS_[[#This Row],[Fecha de Contratación]]>$D$4),"Fuera","Dentro") -> Dentro | CM9: {=IF(MAX(IF(DATOS_[id/cod]=DATOS_[[#This Row],[id/cod]],DATOS_[F.fin.cal]))=DATOS_[[#This Row],[F.fin.cal]],"Sí","NO")} -> Sí | CN9: =IF(AND(DATOS_[[#This Row],[% normaliz]]<>1,DATOS_[[#This Row],[% anualiz]]=1),"Sí","NO") -> NO | CO9: =IF(AND(DATOS_[[#This Row],[% normaliz]]=1,DATOS_[[#This Row],[% anualiz]]<>1),"Sí","NO") -> NO | CP9: =IF(AND(DATOS_[[#This Row],[% normaliz]]<>1,DATOS_[[#This Row],[% anualiz]]<>1),"Sí","NO") -> NO | CQ9: =+IF(DATOS_[[#This Row],[% normaliz]]*DATOS_[[#This Row],[% anualiz]]=1,"NO","Sí") -> NO | CR9: =(DATOS_[[#This Row],[S.BASE]]*(1/DATOS_[[#This Row],[% normaliz]])*(1/DATOS_[[#This Row],[% anualiz]]))*IF(DATOS_[[#This Row],[Check Equiparado]]="Sí",1,0) -> 0 | CS9: =(SUMPRODUCT((RngTipo=$CS$7)*(rngAnualizable="Sí")*(rngNormalizable="Sí")*(DATOS_[[#This Row],[Conc.Sal.01]:[C.Extra.11]]))*(1/DATOS_[[#This Row],[% anualiz]])*(1/DATOS_[[#This Row],[% normaliz]]) +SUMPRODUCT((RngTipo=$CS$7)*(rngAnualizable="Sí")*(rngNormalizable="No")*(DATOS_[[#This Row],[Conc.Sal.01]:[C.Extra.11]]))*(1/DATOS_[[#This Row],[% anualiz]]) +SUMPRODUCT((RngTipo=$CS$7)*(rngAnualizable="No")*(rngNormalizable="Sí")*(DATOS_[[#This Row],[Conc.Sal.01]:[C.Extra.11]]))*(1/DATOS_[[#This Row],[% normaliz]]) +SUMPRODUCT((RngTipo=$CS$7)*(rngAnualizable="No")*(rngNormalizable="No")*(DATOS_[[#This Row],[Conc.Sal.01]:[C.Extra.11]]))) *IF(DATOS_[[#This Row],[Check Equiparado]]="Sí",1,0) -> 0 | CT9: =+DATOS_[[#This Row],[SALARIO BASE Eq]]+DATOS_[[#This Row],[Tot COMPL.SAL Eq]] -> 0 | CU9: {=(SUMPRODUCT((RngTipo=$CU$7)*(rngAnualizable="Sí")*(rngNormalizable="Sí")*(DATOS_[[#This Row],[Conc.Sal.01]:[C.Extra.11]]))*(1/DATOS_[[#This Row],[% anualiz]])*(1/DATOS_[[#This Row],[% normaliz]]) +SUMPRODUCT((RngTipo=$CU$7)*(rngAnualizable="Sí")*(rngNormalizable="No")*(DATOS_[[#This Row],[Conc.Sal.01]:[C.Extra.11]]))*(1/DATOS_[[#This Row],[% anualiz]]) +SUMPRODUCT((RngTipo=$CU$7)*(rngAnualizable="No")*(rngNormalizable="Sí")*(DATOS_[[#This Row],[Conc.Sal.01]:[C.Extra.11]]))*(1/DATOS_[[#This Row],[% normaliz]]) +SUMPRODUCT((RngTipo=$CU$7)*(rngAnualizable="No")*(rngNormalizable="No")*(DATOS_[[#This Row],[Conc.Sal.01]:[C.Extra.11]]))) *IF(DATOS_[[#This Row],[Check Equiparado]]="Sí",1,0)} -> 0 | CV9: =+DATOS_[[#This Row],[TOTAL SALARIO Eq]]+DATOS_[[#This Row],[Tot Extrasalarial Eq]] -> 0 | CW9: =DATOS_[[#This Row],[S.BASE]] -> 0 | CX9: =+SUM(DATOS_[[#This Row],[Conc.Sal.01]:[Conc.Sal.30]]) -> 0 | CY9: =+DATOS_[[#This Row],[SALARIO BASE Ef]]+DATOS_[[#This Row],[Tot COMPL.SAL Ef]] -> 0 | CZ9: =+SUM(DATOS_[[#This Row],[C.Extra.01]:[C.Extra.11]]) -> 0 | DA9: =+DATOS_[[#This Row],[TOTAL SALARIO Ef]]+DATOS_[[#This Row],[Tot Extrasalarial Ef]] -> 0 | DB9: =MIN(IF(DATOS_[[#This Row],[Fecha Fin Contrato]]="",$D$4,DATOS_[[#This Row],[Fecha Fin Contrato]]),$D$4)-MAX(DATOS_[[#This Row],[Fecha de Contratación]],$D$3)+1 -> 366 | DC9: =IF(COUNTIFS(DATOS_[id/cod],DATOS_[[#This Row],[id/cod]])>1,DATOS_[[#This Row],[id/cod]],"") | DD9: =(Inicio!$G$10-DATOS_[[#This Row],[Fecha Nacimiento]])/365.25 -> 59.290897 | DE9: =(Inicio!$G$10-DATOS_[[#This Row],[Fecha de Antigüedad]])/365.25 -> 38.817248 | DF9: =+VLOOKUP(DATOS_[[#This Row],[Clave de Contrato]],TblTiposContrato13[],3,FALSE) -> #N/A | DG9: =+VLOOKUP(DATOS_[[#This Row],[Clave de Contrato]],TblTiposContrato13[],4,FALSE) -> #N/A | DH9: =VLOOKUP(DATOS_[[#This Row],[Edad]],CONTRATOS!TblRngEdad,2,TRUE) -> 55 a 60 | DI9: =VLOOKUP(DATOS_[[#This Row],[Antigüedad]],TblRngAntg14[],2,TRUE) -> más de 15
A10: JOSE HINOJOSA CUENCA | B10: 2 | C10: HOMBRE | D10: 22330 | E10: PRIMARIOS | H10: 33635 | J10: 33635 | M10: 1 | Q10: CONDUCTORES | R10: CONDUCTORES | S10: ENCARGADOS DE CONDUCTORES | T10: CONTINUO | U10: SI | Y10: 14000425011981 | AA10: PERSONAL OPERARIO GENERAL | AC10: 8 | CH10: =+MAX($D$3,DATOS_[[#This Row],[Fecha Inicio Sit. Contract.]]) -> 45292 | CI10: =+MIN($D$4,DATOS_[[#This Row],[Fecha Fin Sit. Contract.]]) -> 45657 | CJ10: =+DATOS_[[#This Row],[% de jornada]]*IF(DATOS_[[#This Row],[% jornada reducida]]="",1,DATOS_[[#This Row],[% jornada reducida]]) -> 1 | CK10: =+(DATOS_[[#This Row],[F.fin.cal]]-DATOS_[[#This Row],[F.ini.cal]]+1)/($D$4-$D$3+1) -> 1 | CL10: =IF(OR(AND(DATOS_[[#This Row],[Fecha Fin Contrato]]<$D$3,DATOS_[[#This Row],[Fecha Fin Contrato]]<>""),DATOS_[[#This Row],[Fecha de Contratación]]>$D$4),"Fuera","Dentro") -> Dentro | CM10: {=IF(MAX(IF(DATOS_[id/cod]=DATOS_[[#This Row],[id/cod]],DATOS_[F.fin.cal]))=DATOS_[[#This Row],[F.fin.cal]],"Sí","NO")} -> Sí | CN10: =IF(AND(DATOS_[[#This Row],[% normaliz]]<>1,DATOS_[[#This Row],[% anualiz]]=1),"Sí","NO") -> NO | CO10: =IF(AND(DATOS_[[#This Row],[% normaliz]]=1,DATOS_[[#This Row],[% anualiz]]<>1),"Sí","NO") -> NO | CP10: =IF(AND(DATOS_[[#This Row],[% normaliz]]<>1,DATOS_[[#This Row],[% anualiz]]<>1),"Sí","NO") -> NO | CQ10: =+IF(DATOS_[[#This Row],[% normaliz]]*DATOS_[[#This Row],[% anualiz]]=1,"NO","Sí") -> NO | CR10: =(DATOS_[[#This Row],[S.BASE]]*(1/DATOS_[[#This Row],[% normaliz]])*(1/DATOS_[[#This Row],[% anualiz]]))*IF(DATOS_[[#This Row],[Check Equiparado]]="Sí",1,0) -> 0 | CS10: =(SUMPRODUCT((RngTipo=$CS$7)*(rngAnualizable="Sí")*(rngNormalizable="Sí")*(DATOS_[[#This Row],[Conc.Sal.01]:[C.Extra.11]]))*(1/DATOS_[[#This Row],[% anualiz]])*(1/DATOS_[[#This Row],[% normaliz]]) +SUMPRODUCT((RngTipo=$CS$7)*(rngAnualizable="Sí")*(rngNormalizable="No")*(DATOS_[[#This Row],[Conc.Sal.01]:[C.Extra.11]]))*(1/DATOS_[[#This Row],[% anualiz]]) +SUMPRODUCT((RngTipo=$CS$7)*(rngAnualizable="No")*(rngNormalizable="Sí")*(DATOS_[[#This Row],[Conc.Sal.01]:[C.Extra.11]]))*(1/DATOS_[[#This Row],[% normaliz]]) +SUMPRODUCT((RngTipo=$CS$7)*(rngAnualizable="No")*(rngNormalizable="No")*(DATOS_[[#This Row],[Conc.Sal.01]:[C.Extra.11]]))) *IF(DATOS_[[#This Row],[Check Equiparado]]="Sí",1,0) -> 0 | CT10: =+DATOS_[[#This Row],[SALARIO BASE Eq]]+DATOS_[[#This Row],[Tot COMPL.SAL Eq]] -> 0 | CU10: {=(SUMPRODUCT((RngTipo=$CU$7)*(rngAnualizable="Sí")*(rngNormalizable="Sí")*(DATOS_[[#This Row],[Conc.Sal.01]:[C.Extra.11]]))*(1/DATOS_[[#This Row],[% anualiz]])*(1/DATOS_[[#This Row],[% normaliz]]) +SUMPRODUCT((RngTipo=$CU$7)*(rngAnualizable="Sí")*(rngNormalizable="No")*(DATOS_[[#This Row],[Conc.Sal.01]:[C.Extra.11]]))*(1/DATOS_[[#This Row],[% anualiz]]) +SUMPRODUCT((RngTipo=$CU$7)*(rngAnualizable="No")*(rngNormalizable="Sí")*(DATOS_[[#This Row],[Conc.Sal.01]:[C.Extra.11]]))*(1/DATOS_[[#This Row],[% normaliz]]) +SUMPRODUCT((RngTipo=$CU$7)*(rngAnualizable="No")*(rngNormalizable="No")*(DATOS_[[#This Row],[Conc.Sal.01]:[C.Extra.11]]))) *IF(DATOS_[[#This Row],[Check Equiparado]]="Sí",1,0)} -> 0 | CV10: =+DATOS_[[#This Row],[TOTAL SALARIO Eq]]+DATOS_[[#This Row],[Tot Extrasalarial Eq]] -> 0 | CW10: =DATOS_[[#This Row],[S.BASE]] -> 0 | CX10: =+SUM(DATOS_[[#This Row],[Conc.Sal.01]:[Conc.Sal.30]]) -> 0 | CY10: =+DATOS_[[#This Row],[SALARIO BASE Ef]]+DATOS_[[#This Row],[Tot COMPL.SAL Ef]] -> 0 | CZ10: =+SUM(DATOS_[[#This Row],[C.Extra.01]:[C.Extra.11]]) -> 0 | DA10: =+DATOS_[[#This Row],[TOTAL SALARIO Ef]]+DATOS_[[#This Row],[Tot Extrasalarial Ef]] -> 0 | DB10: =MIN(IF(DATOS_[[#This Row],[Fecha Fin Contrato]]="",$D$4,DATOS_[[#This Row],[Fecha Fin Contrato]]),$D$4)-MAX(DATOS_[[#This Row],[Fecha de Contratación]],$D$3)+1 -> 366 | DC10: =IF(COUNTIFS(DATOS_[id/cod],DATOS_[[#This Row],[id/cod]])>1,DATOS_[[#This Row],[id/cod]],"") | DD10: =(Inicio!$G$10-DATOS_[[#This Row],[Fecha Nacimiento]])/365.25 -> 63.865845 | DE10: =(Inicio!$G$10-DATOS_[[#This Row],[Fecha de Antigüedad]])/365.25 -> 32.914442 | DF10: =+VLOOKUP(DATOS_[[#This Row],[Clave de Contrato]],TblTiposContrato13[],3,FALSE) -> #N/A | DG10: =+VLOOKUP(DATOS_[[#This Row],[Clave de Contrato]],TblTiposContrato13[],4,FALSE) -> #N/A | DH10: =VLOOKUP(DATOS_[[#This Row],[Edad]],CONTRATOS!TblRngEdad,2,TRUE) -> 60 en adelante | DI10: =VLOOKUP(DATOS_[[#This Row],[Antigüedad]],TblRngAntg14[],2,TRUE) -> más de 15
A11: MANUEL CARMONA CHICO | B11: 3 | C11: HOMBRE | D11: 26224 | E11: E.G.B. | H11: 33635 | J11: 33635 | M11: 1 | Q11: CONDUCTORES | R11: CONDUCTORES | S11: OPERARIO CREMATORIO | T11: CONTINUO | U11: SI | Y11: 14000425011981 | AA11: PERSONAL OPERARIO GENERAL | AC11: 8 | CH11: =+MAX($D$3,DATOS_[[#This Row],[Fecha Inicio Sit. Contract.]]) -> 45292 | CI11: =+MIN($D$4,DATOS_[[#This Row],[Fecha Fin Sit. Contract.]]) -> 45657 | CJ11: =+DATOS_[[#This Row],[% de jornada]]*IF(DATOS_[[#This Row],[% jornada reducida]]="",1,DATOS_[[#This Row],[% jornada reducida]]) -> 1 | CK11: =+(DATOS_[[#This Row],[F.fin.cal]]-DATOS_[[#This Row],[F.ini.cal]]+1)/($D$4-$D$3+1) -> 1 | CL11: =IF(OR(AND(DATOS_[[#This Row],[Fecha Fin Contrato]]<$D$3,DATOS_[[#This Row],[Fecha Fin Contrato]]<>""),DATOS_[[#This Row],[Fecha de Contratación]]>$D$4),"Fuera","Dentro") -> Dentro | CM11: {=IF(MAX(IF(DATOS_[id/cod]=DATOS_[[#This Row],[id/cod]],DATOS_[F.fin.cal]))=DATOS_[[#This Row],[F.fin.cal]],"Sí","NO")} -> Sí | CN11: =IF(AND(DATOS_[[#This Row],[% normaliz]]<>1,DATOS_[[#This Row],[% anualiz]]=1),"Sí","NO") -> NO | CO11: =IF(AND(DATOS_[[#This Row],[% normaliz]]=1,DATOS_[[#This Row],[% anualiz]]<>1),"Sí","NO") -> NO | CP11: =IF(AND(DATOS_[[#This Row],[% normaliz]]<>1,DATOS_[[#This Row],[% anualiz]]<>1),"Sí","NO") -> NO | CQ11: =+IF(DATOS_[[#This Row],[% normaliz]]*DATOS_[[#This Row],[% anualiz]]=1,"NO","Sí") -> NO | CR11: =(DATOS_[[#This Row],[S.BASE]]*(1/DATOS_[[#This Row],[% normaliz]])*(1/DATOS_[[#This Row],[% anualiz]]))*IF(DATOS_[[#This Row],[Check Equiparado]]="Sí",1,0) -> 0 | CS11: =(SUMPRODUCT((RngTipo=$CS$7)*(rngAnualizable="Sí")*(rngNormalizable="Sí")*(DATOS_[[#This Row],[Conc.Sal.01]:[C.Extra.11]]))*(1/DATOS_[[#This Row],[% anualiz]])*(1/DATOS_[[#This Row],[% normaliz]]) +SUMPRODUCT((RngTipo=$CS$7)*(rngAnualizable="Sí")*(rngNormalizable="No")*(DATOS_[[#This Row],[Conc.Sal.01]:[C.Extra.11]]))*(1/DATOS_[[#This Row],[% anualiz]]) +SUMPRODUCT((RngTipo=$CS$7)*(rngAnualizable="No")*(rngNormalizable="Sí")*(DATOS_[[#This Row],[Conc.Sal.01]:[C.Extra.11]]))*(1/DATOS_[[#This Row],[% normaliz]]) +SUMPRODUCT((RngTipo=$CS$7)*(rngAnualizable="No")*(rngNormalizable="No")*(DATOS_[[#This Row],[Conc.Sal.01]:[C.Extra.11]]))) *IF(DATOS_[[#This Row],[Check Equiparado]]="Sí",1,0) -> 0 | CT11: =+DATOS_[[#This Row],[SALARIO BASE Eq]]+DATOS_[[#This Row],[Tot COMPL.SAL Eq]] -> 0 | CU11: {=(SUMPRODUCT((RngTipo=$CU$7)*(rngAnualizable="Sí")*(rngNormalizable="Sí")*(DATOS_[[#This Row],[Conc.Sal.01]:[C.Extra.11]]))*(1/DATOS_[[#This Row],[% anualiz]])*(1/DATOS_[[#This Row],[% normaliz]]) +SUMPRODUCT((RngTipo=$CU$7)*(rngAnualizable="Sí")*(rngNormalizable="No")*(DATOS_[[#This Row],[Conc.Sal.01]:[C.Extra.11]]))*(1/DATOS_[[#This Row],[% anualiz]]) +SUMPRODUCT((RngTipo=$CU$7)*(rngAnualizable="No")*(rngNormalizable="Sí")*(DATOS_[[#This Row],[Conc.Sal.01]:[C.Extra.11]]))*(1/DATOS_[[#This Row],[% normaliz]]) +SUMPRODUCT((RngTipo=$CU$7)*(rngAnualizable="No")*(rngNormalizable="No")*(DATOS_[[#This Row],[Conc.Sal.01]:[C.Extra.11]]))) *IF(DATOS_[[#This Row],[Check Equiparado]]="Sí",1,0)} -> 0 | CV11: =+DATOS_[[#This Row],[TOTAL SALARIO Eq]]+DATOS_[[#This Row],[Tot Extrasalarial Eq]] -> 0 | CW11: =DATOS_[[#This Row],[S.BASE]] -> 0 | CX11: =+SUM(DATOS_[[#This Row],[Conc.Sal.01]:[Conc.Sal.30]]) -> 0 | CY11: =+DATOS_[[#This Row],[SALARIO BASE Ef]]+DATOS_[[#This Row],[Tot COMPL.SAL Ef]] -> 0 | CZ11: =+SUM(DATOS_[[#This Row],[C.Extra.01]:[C.Extra.11]]) -> 0 | DA11: =+DATOS_[[#This Row],[TOTAL SALARIO Ef]]+DATOS_[[#This Row],[Tot Extrasalarial Ef]] -> 0 | DB11: =MIN(IF(DATOS_[[#This Row],[Fecha Fin Contrato]]="",$D$4,DATOS_[[#This Row],[Fecha Fin Contrato]]),$D$4)-MAX(DATOS_[[#This Row],[Fecha de Contratación]],$D$3)+1 -> 366 | DC11: =IF(COUNTIFS(DATOS_[id/cod],DATOS_[[#This Row],[id/cod]])>1,DATOS_[[#This Row],[id/cod]],"") | DD11: =(Inicio!$G$10-DATOS_[[#This Row],[Fecha Nacimiento]])/365.25 -> 53.204654 | DE11: =(Inicio!$G$10-DATOS_[[#This Row],[Fecha de Antigüedad]])/365.25 -> 32.914442 | DF11: =+VLOOKUP(DATOS_[[#This Row],[Clave de Contrato]],TblTiposContrato13[],3,FALSE) -> #N/A | DG11: =+VLOOKUP(DATOS_[[#This Row],[Clave de Contrato]],TblTiposContrato13[],4,FALSE) -> #N/A | DH11: =VLOOKUP(DATOS_[[#This Row],[Edad]],CONTRATOS!TblRngEdad,2,TRUE) -> 50 a 55 | DI11: =VLOOKUP(DATOS_[[#This Row],[Antigüedad]],TblRngAntg14[],2,TRUE) -> más de 15
A12: EDUARDO CALVENTE BORREGO | B12: 4 | C12: HOMBRE | D12: 24589 | E12: FPII | H12: 33780 | J12: 33780 | M12: 1 | P12: 100 | Q12: MANTENIMIENTO | R12: MANTENIMIENTO | S12: ENCARGADO DE MANTENIMIENTO | T12: CONTINUO | U12: SI | W12: GRUPO 02 | Y12: 14000425011981 | Z12: Oficial administrativo/a 1era | AA12: PERSONAL OPERARIO GENERAL | AC12: 8 | AD12: 13448.76 | AE12: 2989.88 | AF12: 37.44 | AG12: 902.4 | AH12: 1215 | AI12: 426.96 | AJ12: 843.12 | AK12: 1363.56 | AL12: 3600 | AM12: 0 | AN12: 0 | AO12: 0 | AP12: 65 | CH12: =+MAX($D$3,DATOS_[[#This Row],[Fecha Inicio Sit. Contract.]]) -> 45292 | CI12: =+MIN($D$4,DATOS_[[#This Row],[Fecha Fin Sit. Contract.]]) -> 45657 | CJ12: =+DATOS_[[#This Row],[% de jornada]]*IF(DATOS_[[#This Row],[% jornada reducida]]="",1,DATOS_[[#This Row],[% jornada reducida]]) -> 1 | CK12: =+(DATOS_[[#This Row],[F.fin.cal]]-DATOS_[[#This Row],[F.ini.cal]]+1)/($D$4-$D$3+1) -> 1 | CL12: =IF(OR(AND(DATOS_[[#This Row],[Fecha Fin Contrato]]<$D$3,DATOS_[[#This Row],[Fecha Fin Contrato]]<>""),DATOS_[[#This Row],[Fecha de Contratación]]>$D$4),"Fuera","Dentro") -> Dentro | CM12: {=IF(MAX(IF(DATOS_[id/cod]=DATOS_[[#This Row],[id/cod]],DATOS_[F.fin.cal]))=DATOS_[[#This Row],[F.fin.cal]],"Sí","NO")} -> Sí | CN12: =IF(AND(DATOS_[[#This Row],[% normaliz]]<>1,DATOS_[[#This Row],[% anualiz]]=1),"Sí","NO") -> NO | CO12: =IF(AND(DATOS_[[#This Row],[% normaliz]]=1,DATOS_[[#This Row],[% anualiz]]<>1),"Sí","NO") -> NO | CP12: =IF(AND(DATOS_[[#This Row],[% normaliz]]<>1,DATOS_[[#This Row],[% anualiz]]<>1),"Sí","NO") -> NO | CQ12: =+IF(DATOS_[[#This Row],[% normaliz]]*DATOS_[[#This Row],[% anualiz]]=1,"NO","Sí") -> NO | CR12: =(DATOS_[[#This Row],[S.BASE]]*(1/DATOS_[[#This Row],[% normaliz]])*(1/DATOS_[[#This Row],[% anualiz]]))*IF(DATOS_[[#This Row],[Check Equiparado]]="Sí",1,0) -> 13448.76 | CS12: =(SUMPRODUCT((RngTipo=$CS$7)*(rngAnualizable="Sí")*(rngNormalizable="Sí")*(DATOS_[[#This Row],[Conc.Sal.01]:[C.Extra.11]]))*(1/DATOS_[[#This Row],[% anualiz]])*(1/DATOS_[[#This Row],[% normaliz]]) +SUMPRODUCT((RngTipo=$CS$7)*(rngAnualizable="Sí")*(rngNormalizable="No")*(DATOS_[[#This Row],[Conc.Sal.01]:[C.Extra.11]]))*(1/DATOS_[[#This Row],[% anualiz]]) +SUMPRODUCT((RngTipo=$CS$7)*(rngAnualizable="No")*(rngNormalizable="Sí")*(DATOS_[[#This Row],[Conc.Sal.01]:[C.Extra.11]]))*(1/DATOS_[[#This Row],[% normaliz]]) +SUMPRODUCT((RngTipo=$CS$7)*(rngAnualizable="No")*(rngNormalizable="No")*(DATOS_[[#This Row],[Conc.Sal.01]:[C.Extra.11]]))) *IF(DATOS_[[#This Row],[Check Equiparado]]="Sí",1,0) -> 11443.36 | CT12: =+DATOS_[[#This Row],[SALARIO BASE Eq]]+DATOS_[[#This Row],[Tot COMPL.SAL Eq]] -> 24892.12 | CU12: {=(SUMPRODUCT((RngTipo=$CU$7)*(rngAnualizable="Sí")*(rngNormalizable="Sí")*(DATOS_[[#This Row],[Conc.Sal.01]:[C.Extra.11]]))*(1/DATOS_[[#This Row],[% anualiz]])*(1/DATOS_[[#This Row],[% normaliz]]) +SUMPRODUCT((RngTipo=$CU$7)*(rngAnualizable="Sí")*(rngNormalizable="No")*(DATOS_[[#This Row],[Conc.Sal.01]:[C.Extra.11]]))*(1/DATOS_[[#This Row],[% anualiz]]) +SUMPRODUCT((RngTipo=$CU$7)*(rngAnualizable="No")*(rngNormalizable="Sí")*(DATOS_[[#This Row],[Conc.Sal.01]:[C.Extra.11]]))*(1/DATOS_[[#This Row],[% normaliz]]) +SUMPRODUCT((RngTipo=$CU$7)*(rngAnualizable="No")*(rngNormalizable="No")*(DATOS_[[#This Row],[Conc.Sal.01]:[C.Extra.11]]))) *IF(DATOS_[[#This Row],[Check Equiparado]]="Sí",1,0)} -> 0 | CV12: =+DATOS_[[#This Row],[TOTAL SALARIO Eq]]+DATOS_[[#This Row],[Tot Extrasalarial Eq]] -> 24892.12 | CW12: =DATOS_[[#This Row],[S.BASE]] -> 13448.76 | CX12: =+SUM(DATOS_[[#This Row],[Conc.Sal.01]:[Conc.Sal.30]]) -> 11443.36 | CY12: =+DATOS_[[#This Row],[SALARIO BASE Ef]]+DATOS_[[#This Row],[Tot COMPL.SAL Ef]] -> 24892.12 | CZ12: =+SUM(DATOS_[[#This Row],[C.Extra.01]:[C.Extra.11]]) -> 0 | DA12: =+DATOS_[[#This Row],[TOTAL SALARIO Ef]]+DATOS_[[#This Row],[Tot Extrasalarial Ef]] -> 24892.12 | DB12: =MIN(IF(DATOS_[[#This Row],[Fecha Fin Contrato]]="",$D$4,DATOS_[[#This Row],[Fecha Fin Contrato]]),$D$4)-MAX(DATOS_[[#This Row],[Fecha de Contratación]],$D$3)+1 -> 366 | DC12: =IF(COUNTIFS(DATOS_[id/cod],DATOS_[[#This Row],[id/cod]])>1,DATOS_[[#This Row],[id/cod]],"") | DD12: =(Inicio!$G$10-DATOS_[[#This Row],[Fecha Nacimiento]])/365.25 -> 57.68104 | DE12: =(Inicio!$G$10-DATOS_[[#This Row],[Fecha de Antigüedad]])/365.25 -> 32.517454 | DF12: =+VLOOKUP(DATOS_[[#This Row],[Clave de Contrato]],TblTiposContrato13[],3,FALSE) -> Completa | DG12: =+VLOOKUP(DATOS_[[#This Row],[Clave de Contrato]],TblTiposContrato13[],4,FALSE) -> Indefinido | DH12: =VLOOKUP(DATOS_[[#This Row],[Edad]],CONTRATOS!TblRngEdad,2,TRUE) -> 55 a 60 | DI12: =VLOOKUP(DATOS_[[#This Row],[Antigüedad]],TblRngAntg14[],2,TRUE) -> más de 15
A13: Mª NIEVES ESTRADA VALS | B13: 5 | C13: MUJER | D13: 25000 | E13: FPI | H13: 34092 | J13: 34092 | M13: 1 | P13: 100 | Q13: ADMINISTRACIÓN | R13: ADMINISTRACIÓN | S13: CONTABILIDAD | T13: CONTINUO | U13: SI | W13: GRUPO 02 | Y13: 14000425011981 | Z13: Oficial administrativo/a 1era | AA13: PERSONAL ADMINISTRATIVO | AC13: 5 | AD13: 13448.76 | AE13: 4924 | AF13: 37.44 | AG13: 902.4 | AH13: 3720 | AI13: 426.96 | AJ13: 843.12 | AK13: 1374.12 | AL13: 0 | AM13: 0 | AN13: 0 | AO13: 0 | AP13: 65 | AQ13: 4517.81 | CH13: =+MAX($D$3,DATOS_[[#This Row],[Fecha Inicio Sit. Contract.]]) -> 45292 | CI13: =+MIN($D$4,DATOS_[[#This Row],[Fecha Fin Sit. Contract.]]) -> 45657 | CJ13: =+DATOS_[[#This Row],[% de jornada]]*IF(DATOS_[[#This Row],[% jornada reducida]]="",1,DATOS_[[#This Row],[% jornada reducida]]) -> 1 | CK13: =+(DATOS_[[#This Row],[F.fin.cal]]-DATOS_[[#This Row],[F.ini.cal]]+1)/($D$4-$D$3+1) -> 1 | CL13: =IF(OR(AND(DATOS_[[#This Row],[Fecha Fin Contrato]]<$D$3,DATOS_[[#This Row],[Fecha Fin Contrato]]<>""),DATOS_[[#This Row],[Fecha de Contratación]]>$D$4),"Fuera","Dentro") -> Dentro | CM13: {=IF(MAX(IF(DATOS_[id/cod]=DATOS_[[#This Row],[id/cod]],DATOS_[F.fin.cal]))=DATOS_[[#This Row],[F.fin.cal]],"Sí","NO")} -> Sí | CN13: =IF(AND(DATOS_[[#This Row],[% normaliz]]<>1,DATOS_[[#This Row],[% anualiz]]=1),"Sí","NO") -> NO | CO13: =IF(AND(DATOS_[[#This Row],[% normaliz]]=1,DATOS_[[#This Row],[% anualiz]]<>1),"Sí","NO") -> NO | CP13: =IF(AND(DATOS_[[#This Row],[% normaliz]]<>1,DATOS_[[#This Row],[% anualiz]]<>1),"Sí","NO") -> NO | CQ13: =+IF(DATOS_[[#This Row],[% normaliz]]*DATOS_[[#This Row],[% anualiz]]=1,"NO","Sí") -> NO | CR13: =(DATOS_[[#This Row],[S.BASE]]*(1/DATOS_[[#This Row],[% normaliz]])*(1/DATOS_[[#This Row],[% anualiz]]))*IF(DATOS_[[#This Row],[Check Equiparado]]="Sí",1,0) -> 13448.76 | CS13: =(SUMPRODUCT((RngTipo=$CS$7)*(rngAnualizable="Sí")*(rngNormalizable="Sí")*(DATOS_[[#This Row],[Conc.Sal.01]:[C.Extra.11]]))*(1/DATOS_[[#This Row],[% anualiz]])*(1/DATOS_[[#This Row],[% normaliz]]) +SUMPRODUCT((RngTipo=$CS$7)*(rngAnualizable="Sí")*(rngNormalizable="No")*(DATOS_[[#This Row],[Conc.Sal.01]:[C.Extra.11]]))*(1/DATOS_[[#This Row],[% anualiz]]) +SUMPRODUCT((RngTipo=$CS$7)*(rngAnualizable="No")*(rngNormalizable="Sí")*(DATOS_[[#This Row],[Conc.Sal.01]:[C.Extra.11]]))*(1/DATOS_[[#This Row],[% normaliz]]) +SUMPRODUCT((RngTipo=$CS$7)*(rngAnualizable="No")*(rngNormalizable="No")*(DATOS_[[#This Row],[Conc.Sal.01]:[C.Extra.11]]))) *IF(DATOS_[[#This Row],[Check Equiparado]]="Sí",1,0) -> 16810.85 | CT13: =+DATOS_[[#This Row],[SALARIO BASE Eq]]+DATOS_[[#This Row],[Tot COMPL.SAL Eq]] -> 30259.61 | CU13: {=(SUMPRODUCT((RngTipo=$CU$7)*(rngAnualizable="Sí")*(rngNormalizable="Sí")*(DATOS_[[#This Row],[Conc.Sal.01]:[C.Extra.11]]))*(1/DATOS_[[#This Row],[% anualiz]])*(1/DATOS_[[#This Row],[% normaliz]]) +SUMPRODUCT((RngTipo=$CU$7)*(rngAnualizable="Sí")*(rngNormalizable="No")*(DATOS_[[#This Row],[Conc.Sal.01]:[C.Extra.11]]))*(1/DATOS_[[#This Row],[% anualiz]]) +SUMPRODUCT((RngTipo=$CU$7)*(rngAnualizable="No")*(rngNormalizable="Sí")*(DATOS_[[#This Row],[Conc.Sal.01]:[C.Extra.11]]))*(1/DATOS_[[#This Row],[% normaliz]]) +SUMPRODUCT((RngTipo=$CU$7)*(rngAnualizable="No")*(rngNormalizable="No")*(DATOS_[[#This Row],[Conc.Sal.01]:[C.Extra.11]]))) *IF(DATOS_[[#This Row],[Check Equiparado]]="Sí",1,0)} -> 0 | CV13: =+DATOS_[[#This Row],[TOTAL SALARIO Eq]]+DATOS_[[#This Row],[Tot Extrasalarial Eq]] -> 30259.61 | CW13: =DATOS_[[#This Row],[S.BASE]] -> 13448.76 | CX13: =+SUM(DATOS_[[#This Row],[Conc.Sal.01]:[Conc.Sal.30]]) -> 16810.85 | CY13: =+DATOS_[[#This Row],[SALARIO BASE Ef]]+DATOS_[[#This Row],[Tot COMPL.SAL Ef]] -> 30259.61 | CZ13: =+SUM(DATOS_[[#This Row],[C.Extra.01]:[C.Extra.11]]) -> 0 | DA13: =+DATOS_[[#This Row],[TOTAL SALARIO Ef]]+DATOS_[[#This Row],[Tot Extrasalarial Ef]] -> 30259.61 | DB13: =MIN(IF(DATOS_[[#This Row],[Fecha Fin Contrato]]="",$D$4,DATOS_[[#This Row],[Fecha Fin Contrato]]),$D$4)-MAX(DATOS_[[#This Row],[Fecha de Contratación]],$D$3)+1 -> 366 | DC13: =IF(COUNTIFS(DATOS_[id/cod],DATOS_[[#This Row],[id/cod]])>1,DATOS_[[#This Row],[id/cod]],"") | DD13: =(Inicio!$G$10-DATOS_[[#This Row],[Fecha Nacimiento]])/365.25 -> 56.555784 | DE13: =(Inicio!$G$10-DATOS_[[#This Row],[Fecha de Antigüedad]])/365.25 -> 31.663244 | DF13: =+VLOOKUP(DATOS_[[#This Row],[Clave de Contrato]],TblTiposContrato13[],3,FALSE) -> Completa | DG13: =+VLOOKUP(DATOS_[[#This Row],[Clave de Contrato]],TblTiposContrato13[],4,FALSE) -> Indefinido | DH13: =VLOOKUP(DATOS_[[#This Row],[Edad]],CONTRATOS!TblRngEdad,2,TRUE) -> 55 a 60 | DI13: =VLOOKUP(DATOS_[[#This Row],[Antigüedad]],TblRngAntg14[],2,TRUE) -> más de 15
A14: PILAR AVILA PORRAS | B14: 6 | C14: MUJER | D14: 24133 | E14: BACHILLER | H14: 34444 | J14: 34444 | M14: 1 | P14: 100 | Q14: ADMINISTRACIÓN | R14: ADMINISTRACIÓN | S14: FACTURACION | T14: CONTINUO | U14: SI | W14: GRUPO 02 | Y14: 14000425011981 | Z14: Oficial administrativo/a 1era | AA14: PERSONAL ADMINISTRATIVO | AC14: 5 | AD14: 13448.76 | AE14: 3564 | AF14: 37.44 | AG14: 902.4 | AH14: 1168.32 | AI14: 310.68 | AJ14: 843.12 | AK14: 1358.88 | AL14: 0 | AM14: 0 | AN14: 0 | AO14: 200 | AP14: 65 | CH14: =+MAX($D$3,DATOS_[[#This Row],[Fecha Inicio Sit. Contract.]]) -> 45292 | CI14: =+MIN($D$4,DATOS_[[#This Row],[Fecha Fin Sit. Contract.]]) -> 45657 | CJ14: =+DATOS_[[#This Row],[% de jornada]]*IF(DATOS_[[#This Row],[% jornada reducida]]="",1,DATOS_[[#This Row],[% jornada reducida]]) -> 1 | CK14: =+(DATOS_[[#This Row],[F.fin.cal]]-DATOS_[[#This Row],[F.ini.cal]]+1)/($D$4-$D$3+1) -> 1 | CL14: =IF(OR(AND(DATOS_[[#This Row],[Fecha Fin Contrato]]<$D$3,DATOS_[[#This Row],[Fecha Fin Contrato]]<>""),DATOS_[[#This Row],[Fecha de Contratación]]>$D$4),"Fuera","Dentro") -> Dentro | CM14: {=IF(MAX(IF(DATOS_[id/cod]=DATOS_[[#This Row],[id/cod]],DATOS_[F.fin.cal]))=DATOS_[[#This Row],[F.fin.cal]],"Sí","NO")} -> Sí | CN14: =IF(AND(DATOS_[[#This Row],[% normaliz]]<>1,DATOS_[[#This Row],[% anualiz]]=1),"Sí","NO") -> NO | CO14: =IF(AND(DATOS_[[#This Row],[% normaliz]]=1,DATOS_[[#This Row],[% anualiz]]<>1),"Sí","NO") -> NO | CP14: =IF(AND(DATOS_[[#This Row],[% normaliz]]<>1,DATOS_[[#This Row],[% anualiz]]<>1),"Sí","NO") -> NO | CQ14: =+IF(DATOS_[[#This Row],[% normaliz]]*DATOS_[[#This Row],[% anualiz]]=1,"NO","Sí") -> NO | CR14: =(DATOS_[[#This Row],[S.BASE]]*(1/DATOS_[[#This Row],[% normaliz]])*(1/DATOS_[[#This Row],[% anualiz]]))*IF(DATOS_[[#This Row],[Check Equiparado]]="Sí",1,0) -> 13448.76 | CS14: =(SUMPRODUCT((RngTipo=$CS$7)*(rngAnualizable="Sí")*(rngNormalizable="Sí")*(DATOS_[[#This Row],[Conc.Sal.01]:[C.Extra.11]]))*(1/DATOS_[[#This Row],[% anualiz]])*(1/DATOS_[[#This Row],[% normaliz]]) +SUMPRODUCT((RngTipo=$CS$7)*(rngAnualizable="Sí")*(rngNormalizable="No")*(DATOS_[[#This Row],[Conc.Sal.01]:[C.Extra.11]]))*(1/DATOS_[[#This Row],[% anualiz]]) +SUMPRODUCT((RngTipo=$CS$7)*(rngAnualizable="No")*(rngNormalizable="Sí")*(DATOS_[[#This Row],[Conc.Sal.01]:[C.Extra.11]]))*(1/DATOS_[[#This Row],[% normaliz]]) +SUMPRODUCT((RngTipo=$CS$7)*(rngAnualizable="No")*(rngNormalizable="No")*(DATOS_[[#This Row],[Conc.Sal.01]:[C.Extra.11]]))) *IF(DATOS_[[#This Row],[Check Equiparado]]="Sí",1,0) -> 8449.84 | CT14: =+DATOS_[[#This Row],[SALARIO BASE Eq]]+DATOS_[[#This Row],[Tot COMPL.SAL Eq]] -> 21898.6 | CU14: {=(SUMPRODUCT((RngTipo=$CU$7)*(rngAnualizable="Sí")*(rngNormalizable="Sí")*(DATOS_[[#This Row],[Conc.Sal.01]:[C.Extra.11]]))*(1/DATOS_[[#This Row],[% anualiz]])*(1/DATOS_[[#This Row],[% normaliz]]) +SUMPRODUCT((RngTipo=$CU$7)*(rngAnualizable="Sí")*(rngNormalizable="No")*(DATOS_[[#This Row],[Conc.Sal.01]:[C.Extra.11]]))*(1/DATOS_[[#This Row],[% anualiz]]) +SUMPRODUCT((RngTipo=$CU$7)*(rngAnualizable="No")*(rngNormalizable="Sí")*(DATOS_[[#This Row],[Conc.Sal.01]:[C.Extra.11]]))*(1/DATOS_[[#This Row],[% normaliz]]) +SUMPRODUCT((RngTipo=$CU$7)*(rngAnualizable="No")*(rngNormalizable="No")*(DATOS_[[#This Row],[Conc.Sal.01]:[C.Extra.11]]))) *IF(DATOS_[[#This Row],[Check Equiparado]]="Sí",1,0)} -> 0 | CV14: =+DATOS_[[#This Row],[TOTAL SALARIO Eq]]+DATOS_[[#This Row],[Tot Extrasalarial Eq]] -> 21898.6 | CW14: =DATOS_[[#This Row],[S.BASE]] -> 13448.76 | CX14: =+SUM(DATOS_[[#This Row],[Conc.Sal.01]:[Conc.Sal.30]]) -> 8449.84 | CY14: =+DATOS_[[#This Row],[SALARIO BASE Ef]]+DATOS_[[#This Row],[Tot COMPL.SAL Ef]] -> 21898.6 | CZ14: =+SUM(DATOS_[[#This Row],[C.Extra.01]:[C.Extra.11]]) -> 0 | DA14: =+DATOS_[[#This Row],[TOTAL SALARIO Ef]]+DATOS_[[#This Row],[Tot Extrasalarial Ef]] -> 21898.6 | DB14: =MIN(IF(DATOS_[[#This Row],[Fecha Fin Contrato]]="",$D$4,DATOS_[[#This Row],[Fecha Fin Contrato]]),$D$4)-MAX(DATOS_[[#This Row],[Fecha de Contratación]],$D$3)+1 -> 366 | DC14: =IF(COUNTIFS(DATOS_[id/cod],DATOS_[[#This Row],[id/cod]])>1,DATOS_[[#This Row],[id/cod]],"") | DD14: =(Inicio!$G$10-DATOS_[[#This Row],[Fecha Nacimiento]])/365.25 -> 58.9295 | DE14: =(Inicio!$G$10-DATOS_[[#This Row],[Fecha de Antigüedad]])/365.25 -> 30.699521 | DF14: =+VLOOKUP(DATOS_[[#This Row],[Clave de Contrato]],TblTiposContrato13[],3,FALSE) -> Completa | DG14: =+VLOOKUP(DATOS_[[#This Row],[Clave de Contrato]],TblTiposContrato13[],4,FALSE) -> Indefinido | DH14: =VLOOKUP(DATOS_[[#This Row],[Edad]],CONTRATOS!TblRngEdad,2,TRUE) -> 55 a 60 | DI14: =VLOOKUP(DATOS_[[#This Row],[Antigüedad]],TblRngAntg14[],2,TRUE) -> más de 15
A15: JOSE RAFAEL ROMAN CRUZ | B15: 7 | C15: HOMBRE | D15: 23863 | E15: GRADUADO SOCIAL | H15: 34835 | J15: 34835 | M15: 1 | Q15: ADMINISTRACIÓN | R15: TRAMITES | S15: TRAMITACIONES Y DILIGENCIA | T15: CONTINUO | U15: NO | Y15: 14000425011981 | AA15: PERSONAL ADMINISTRATIVO | AC15: 5 | CH15: =+MAX($D$3,DATOS_[[#This Row],[Fecha Inicio Sit. Contract.]]) -> 45292 | CI15: =+MIN($D$4,DATOS_[[#This Row],[Fecha Fin Sit. Contract.]]) -> 45657 | CJ15: =+DATOS_[[#This Row],[% de jornada]]*IF(DATOS_[[#This Row],[% jornada reducida]]="",1,DATOS_[[#This Row],[% jornada reducida]]) -> 1 | CK15: =+(DATOS_[[#This Row],[F.fin.cal]]-DATOS_[[#This Row],[F.ini.cal]]+1)/($D$4-$D$3+1) -> 1 | CL15: =IF(OR(AND(DATOS_[[#This Row],[Fecha Fin Contrato]]<$D$3,DATOS_[[#This Row],[Fecha Fin Contrato]]<>""),DATOS_[[#This Row],[Fecha de Contratación]]>$D$4),"Fuera","Dentro") -> Dentro | CM15: {=IF(MAX(IF(DATOS_[id/cod]=DATOS_[[#This Row],[id/cod]],DATOS_[F.fin.cal]))=DATOS_[[#This Row],[F.fin.cal]],"Sí","NO")} -> Sí | CN15: =IF(AND(DATOS_[[#This Row],[% normaliz]]<>1,DATOS_[[#This Row],[% anualiz]]=1),"Sí","NO") -> NO | CO15: =IF(AND(DATOS_[[#This Row],[% normaliz]]=1,DATOS_[[#This Row],[% anualiz]]<>1),"Sí","NO") -> NO | CP15: =IF(AND(DATOS_[[#This Row],[% normaliz]]<>1,DATOS_[[#This Row],[% anualiz]]<>1),"Sí","NO") -> NO | CQ15: =+IF(DATOS_[[#This Row],[% normaliz]]*DATOS_[[#This Row],[% anualiz]]=1,"NO","Sí") -> NO | CR15: =(DATOS_[[#This Row],[S.BASE]]*(1/DATOS_[[#This Row],[% normaliz]])*(1/DATOS_[[#This Row],[% anualiz]]))*IF(DATOS_[[#This Row],[Check Equiparado]]="Sí",1,0) -> 0 | CS15: =(SUMPRODUCT((RngTipo=$CS$7)*(rngAnualizable="Sí")*(rngNormalizable="Sí")*(DATOS_[[#This Row],[Conc.Sal.01]:[C.Extra.11]]))*(1/DATOS_[[#This Row],[% anualiz]])*(1/DATOS_[[#This Row],[% normaliz]]) +SUMPRODUCT((RngTipo=$CS$7)*(rngAnualizable="Sí")*(rngNormalizable="No")*(DATOS_[[#This Row],[Conc.Sal.01]:[C.Extra.11]]))*(1/DATOS_[[#This Row],[% anualiz]]) +SUMPRODUCT((RngTipo=$CS$7)*(rngAnualizable="No")*(rngNormalizable="Sí")*(DATOS_[[#This Row],[Conc.Sal.01]:[C.Extra.11]]))*(1/DATOS_[[#This Row],[% normaliz]]) +SUMPRODUCT((RngTipo=$CS$7)*(rngAnualizable="No")*(rngNormalizable="No")*(DATOS_[[#This Row],[Conc.Sal.01]:[C.Extra.11]]))) *IF(DATOS_[[#This Row],[Check Equiparado]]="Sí",1,0) -> 0 | CT15: =+DATOS_[[#This Row],[SALARIO BASE Eq]]+DATOS_[[#This Row],[Tot COMPL.SAL Eq]] -> 0 | CU15: {=(SUMPRODUCT((RngTipo=$CU$7)*(rngAnualizable="Sí")*(rngNormalizable="Sí")*(DATOS_[[#This Row],[Conc.Sal.01]:[C.Extra.11]]))*(1/DATOS_[[#This Row],[% anualiz]])*(1/DATOS_[[#This Row],[% normaliz]]) +SUMPRODUCT((RngTipo=$CU$7)*(rngAnualizable="Sí")*(rngNormalizable="No")*(DATOS_[[#This Row],[Conc.Sal.01]:[C.Extra.11]]))*(1/DATOS_[[#This Row],[% anualiz]]) +SUMPRODUCT((RngTipo=$CU$7)*(rngAnualizable="No")*(rngNormalizable="Sí")*(DATOS_[[#This Row],[Conc.Sal.01]:[C.Extra.11]]))*(1/DATOS_[[#This Row],[% normaliz]]) +SUMPRODUCT((RngTipo=$CU$7)*(rngAnualizable="No")*(rngNormalizable="No")*(DATOS_[[#This Row],[Conc.Sal.01]:[C.Extra.11]]))) *IF(DATOS_[[#This Row],[Check Equiparado]]="Sí",1,0)} -> 0 | CV15: =+DATOS_[[#This Row],[TOTAL SALARIO Eq]]+DATOS_[[#This Row],[Tot Extrasalarial Eq]] -> 0 | CW15: =DATOS_[[#This Row],[S.BASE]] -> 0 | CX15: =+SUM(DATOS_[[#This Row],[Conc.Sal.01]:[Conc.Sal.30]]) -> 0 | CY15: =+DATOS_[[#This Row],[SALARIO BASE Ef]]+DATOS_[[#This Row],[Tot COMPL.SAL Ef]] -> 0 | CZ15: =+SUM(DATOS_[[#This Row],[C.Extra.01]:[C.Extra.11]]) -> 0 | DA15: =+DATOS_[[#This Row],[TOTAL SALARIO Ef]]+DATOS_[[#This Row],[Tot Extrasalarial Ef]] -> 0 | DB15: =MIN(IF(DATOS_[[#This Row],[Fecha Fin Contrato]]="",$D$4,DATOS_[[#This Row],[Fecha Fin Contrato]]),$D$4)-MAX(DATOS_[[#This Row],[Fecha de Contratación]],$D$3)+1 -> 366 | DC15: =IF(COUNTIFS(DATOS_[id/cod],DATOS_[[#This Row],[id/cod]])>1,DATOS_[[#This Row],[id/cod]],"") | DD15: =(Inicio!$G$10-DATOS_[[#This Row],[Fecha Nacimiento]])/365.25 -> 59.66872 | DE15: =(Inicio!$G$10-DATOS_[[#This Row],[Fecha de Antigüedad]])/365.25 -> 29.629021 | DF15: =+VLOOKUP(DATOS_[[#This Row],[Clave de Contrato]],TblTiposContrato13[],3,FALSE) -> #N/A | DG15: =+VLOOKUP(DATOS_[[#This Row],[Clave de Contrato]],TblTiposContrato13[],4,FALSE) -> #N/A | DH15: =VLOOKUP(DATOS_[[#This Row],[Edad]],CONTRATOS!TblRngEdad,2,TRUE) -> 55 a 60 | DI15: =VLOOKUP(DATOS_[[#This Row],[Antigüedad]],TblRngAntg14[],2,TRUE) -> más de 15
A16: Mª GEMMA GIL MOLINA | B16: 8 | C16: MUJER | D16: 26394 | E16: DIPLOMADA | H16: 35138 | J16: 35138 | M16: 1 | P16: 100 | Q16: ADMINISTRACIÓN | R16: RR.HH, | S16: PERSONAL Y CALIDAD | T16: CONTINUO | U16: NO | W16: GRUPO 02 | Y16: 14000425011981 | Z16: Oficial administrativo/a 1era | AA16: PERSONAL ADMINISTRATIVO | AC16: 5 | AD16: 13448.76 | AE16: 7380 | AF16: 37.44 | AG16: 902.4 | AH16: 713.4 | AI16: 431.76 | AJ16: 843.12 | AK16: 1318.32 | AL16: 0 | AM16: 1224 | AN16: 1224 | AO16: 0 | AP16: 65 | AQ16: 3766.18 | CH16: =+MAX($D$3,DATOS_[[#This Row],[Fecha Inicio Sit. Contract.]]) -> 45292 | CI16: =+MIN($D$4,DATOS_[[#This Row],[Fecha Fin Sit. Contract.]]) -> 45657 | CJ16: =+DATOS_[[#This Row],[% de jornada]]*IF(DATOS_[[#This Row],[% jornada reducida]]="",1,DATOS_[[#This Row],[% jornada reducida]]) -> 1 | CK16: =+(DATOS_[[#This Row],[F.fin.cal]]-DATOS_[[#This Row],[F.ini.cal]]+1)/($D$4-$D$3+1) -> 1 | CL16: =IF(OR(AND(DATOS_[[#This Row],[Fecha Fin Contrato]]<$D$3,DATOS_[[#This Row],[Fecha Fin Contrato]]<>""),DATOS_[[#This Row],[Fecha de Contratación]]>$D$4),"Fuera","Dentro") -> Dentro | CM16: {=IF(MAX(IF(DATOS_[id/cod]=DATOS_[[#This Row],[id/cod]],DATOS_[F.fin.cal]))=DATOS_[[#This Row],[F.fin.cal]],"Sí","NO")} -> Sí | CN16: =IF(AND(DATOS_[[#This Row],[% normaliz]]<>1,DATOS_[[#This Row],[% anualiz]]=1),"Sí","NO") -> NO | CO16: =IF(AND(DATOS_[[#This Row],[% normaliz]]=1,DATOS_[[#This Row],[% anualiz]]<>1),"Sí","NO") -> NO | CP16: =IF(AND(DATOS_[[#This Row],[% normaliz]]<>1,DATOS_[[#This Row],[% anualiz]]<>1),"Sí","NO") -> NO | CQ16: =+IF(DATOS_[[#This Row],[% normaliz]]*DATOS_[[#This Row],[% anualiz]]=1,"NO","Sí") -> NO | CR16: =(DATOS_[[#This Row],[S.BASE]]*(1/DATOS_[[#This Row],[% normaliz]])*(1/DATOS_[[#This Row],[% anualiz]]))*IF(DATOS_[[#This Row],[Check Equiparado]]="Sí",1,0) -> 13448.76 | CS16: =(SUMPRODUCT((RngTipo=$CS$7)*(rngAnualizable="Sí")*(rngNormalizable="Sí")*(DATOS_[[#This Row],[Conc.Sal.01]:[C.Extra.11]]))*(1/DATOS_[[#This Row],[% anualiz]])*(1/DATOS_[[#This Row],[% normaliz]]) +SUMPRODUCT((RngTipo=$CS$7)*(rngAnualizable="Sí")*(rngNormalizable="No")*(DATOS_[[#This Row],[Conc.Sal.01]:[C.Extra.11]]))*(1/DATOS_[[#This Row],[% anualiz]]) +SUMPRODUCT((RngTipo=$CS$7)*(rngAnualizable="No")*(rngNormalizable="Sí")*(DATOS_[[#This Row],[Conc.Sal.01]:[C.Extra.11]]))*(1/DATOS_[[#This Row],[% normaliz]]) +SUMPRODUCT((RngTipo=$CS$7)*(rngAnualizable="No")*(rngNormalizable="No")*(DATOS_[[#This Row],[Conc.Sal.01]:[C.Extra.11]]))) *IF(DATOS_[[#This Row],[Check Equiparado]]="Sí",1,0) -> 17905.62 | CT16: =+DATOS_[[#This Row],[SALARIO BASE Eq]]+DATOS_[[#This Row],[Tot COMPL.SAL Eq]] -> 31354.38 | CU16: {=(SUMPRODUCT((RngTipo=$CU$7)*(rngAnualizable="Sí")*(rngNormalizable="Sí")*(DATOS_[[#This Row],[Conc.Sal.01]:[C.Extra.11]]))*(1/DATOS_[[#This Row],[% anualiz]])*(1/DATOS_[[#This Row],[% normaliz]]) +SUMPRODUCT((RngTipo=$CU$7)*(rngAnualizable="Sí")*(rngNormalizable="No")*(DATOS_[[#This Row],[Conc.Sal.01]:[C.Extra.11]]))*(1/DATOS_[[#This Row],[% anualiz]]) +SUMPRODUCT((RngTipo=$CU$7)*(rngAnualizable="No")*(rngNormalizable="Sí")*(DATOS_[[#This Row],[Conc.Sal.01]:[C.Extra.11]]))*(1/DATOS_[[#This Row],[% normaliz]]) +SUMPRODUCT((RngTipo=$CU$7)*(rngAnualizable="No")*(rngNormalizable="No")*(DATOS_[[#This Row],[Conc.Sal.01]:[C.Extra.11]]))) *IF(DATOS_[[#This Row],[Check Equiparado]]="Sí",1,0)} -> 0 | CV16: =+DATOS_[[#This Row],[TOTAL SALARIO Eq]]+DATOS_[[#This Row],[Tot Extrasalarial Eq]] -> 31354.38 | CW16: =DATOS_[[#This Row],[S.BASE]] -> 13448.76 | CX16: =+SUM(DATOS_[[#This Row],[Conc.Sal.01]:[Conc.Sal.30]]) -> 17905.62 | CY16: =+DATOS_[[#This Row],[SALARIO BASE Ef]]+DATOS_[[#This Row],[Tot COMPL.SAL Ef]] -> 31354.38 | CZ16: =+SUM(DATOS_[[#This Row],[C.Extra.01]:[C.Extra.11]]) -> 0 | DA16: =+DATOS_[[#This Row],[TOTAL SALARIO Ef]]+DATOS_[[#This Row],[Tot Extrasalarial Ef]] -> 31354.38 | DB16: =MIN(IF(DATOS_[[#This Row],[Fecha Fin Contrato]]="",$D$4,DATOS_[[#This Row],[Fecha Fin Contrato]]),$D$4)-MAX(DATOS_[[#This Row],[Fecha de Contratación]],$D$3)+1 -> 366 | DC16: =IF(COUNTIFS(DATOS_[id/cod],DATOS_[[#This Row],[id/cod]])>1,DATOS_[[#This Row],[id/cod]],"") | DD16: =(Inicio!$G$10-DATOS_[[#This Row],[Fecha Nacimiento]])/365.25 -> 52.73922 | DE16: =(Inicio!$G$10-DATOS_[[#This Row],[Fecha de Antigüedad]])/365.25 -> 28.799452 | DF16: =+VLOOKUP(DATOS_[[#This Row],[Clave de Contrato]],TblTiposContrato13[],3,FALSE) -> Completa | DG16: =+VLOOKUP(DATOS_[[#This Row],[Clave de Contrato]],TblTiposContrato13[],4,FALSE) -> Indefinido | DH16: =VLOOKUP(DATOS_[[#This Row],[Edad]],CONTRATOS!TblRngEdad,2,TRUE) -> 50 a 55 | DI16: =VLOOKUP(DATOS_[[#This Row],[Antigüedad]],TblRngAntg14[],2,TRUE) -> más de 15
A17: MANUEL VIDA SANCHEZ | B17: 9 | C17: HOMBRE | D17: 24529 | E17: GRADUADO ESCOLAR | H17: 35196 | J17: 35196 | M17: 1 | Q17: CONDUCTORES | R17: CONDUCTORES | S17: OPERARIO CREMATORIO | T17: CONTINUO | U17: SI | Y17: 14000425011981 | AA17: PERSONAL OPERARIO GENERAL | AC17: 8 | CH17: =+MAX($D$3,DATOS_[[#This Row],[Fecha Inicio Sit. Contract.]]) -> 45292 | CI17: =+MIN($D$4,DATOS_[[#This Row],[Fecha Fin Sit. Contract.]]) -> 45657 | CJ17: =+DATOS_[[#This Row],[% de jornada]]*IF(DATOS_[[#This Row],[% jornada reducida]]="",1,DATOS_[[#This Row],[% jornada reducida]]) -> 1 | CK17: =+(DATOS_[[#This Row],[F.fin.cal]]-DATOS_[[#This Row],[F.ini.cal]]+1)/($D$4-$D$3+1) -> 1 | CL17: =IF(OR(AND(DATOS_[[#This Row],[Fecha Fin Contrato]]<$D$3,DATOS_[[#This Row],[Fecha Fin Contrato]]<>""),DATOS_[[#This Row],[Fecha de Contratación]]>$D$4),"Fuera","Dentro") -> Dentro | CM17: {=IF(MAX(IF(DATOS_[id/cod]=DATOS_[[#This Row],[id/cod]],DATOS_[F.fin.cal]))=DATOS_[[#This Row],[F.fin.cal]],"Sí","NO")} -> Sí | CN17: =IF(AND(DATOS_[[#This Row],[% normaliz]]<>1,DATOS_[[#This Row],[% anualiz]]=1),"Sí","NO") -> NO | CO17: =IF(AND(DATOS_[[#This Row],[% normaliz]]=1,DATOS_[[#This Row],[% anualiz]]<>1),"Sí","NO") -> NO | CP17: =IF(AND(DATOS_[[#This Row],[% normaliz]]<>1,DATOS_[[#This Row],[% anualiz]]<>1),"Sí","NO") -> NO | CQ17: =+IF(DATOS_[[#This Row],[% normaliz]]*DATOS_[[#This Row],[% anualiz]]=1,"NO","Sí") -> NO | CR17: =(DATOS_[[#This Row],[S.BASE]]*(1/DATOS_[[#This Row],[% normaliz]])*(1/DATOS_[[#This Row],[% anualiz]]))*IF(DATOS_[[#This Row],[Check Equiparado]]="Sí",1,0) -> 0 | CS17: =(SUMPRODUCT((RngTipo=$CS$7)*(rngAnualizable="Sí")*(rngNormalizable="Sí")*(DATOS_[[#This Row],[Conc.Sal.01]:[C.Extra.11]]))*(1/DATOS_[[#This Row],[% anualiz]])*(1/DATOS_[[#This Row],[% normaliz]]) +SUMPRODUCT((RngTipo=$CS$7)*(rngAnualizable="Sí")*(rngNormalizable="No")*(DATOS_[[#This Row],[Conc.Sal.01]:[C.Extra.11]]))*(1/DATOS_[[#This Row],[% anualiz]]) +SUMPRODUCT((RngTipo=$CS$7)*(rngAnualizable="No")*(rngNormalizable="Sí")*(DATOS_[[#This Row],[Conc.Sal.01]:[C.Extra.11]]))*(1/DATOS_[[#This Row],[% normaliz]]) +SUMPRODUCT((RngTipo=$CS$7)*(rngAnualizable="No")*(rngNormalizable="No")*(DATOS_[[#This Row],[Conc.Sal.01]:[C.Extra.11]]))) *IF(DATOS_[[#This Row],[Check Equiparado]]="Sí",1,0) -> 0 | CT17: =+DATOS_[[#This Row],[SALARIO BASE Eq]]+DATOS_[[#This Row],[Tot COMPL.SAL Eq]] -> 0 | CU17: {=(SUMPRODUCT((RngTipo=$CU$7)*(rngAnualizable="Sí")*(rngNormalizable="Sí")*(DATOS_[[#This Row],[Conc.Sal.01]:[C.Extra.11]]))*(1/DATOS_[[#This Row],[% anualiz]])*(1/DATOS_[[#This Row],[% normaliz]]) +SUMPRODUCT((RngTipo=$CU$7)*(rngAnualizable="Sí")*(rngNormalizable="No")*(DATOS_[[#This Row],[Conc.Sal.01]:[C.Extra.11]]))*(1/DATOS_[[#This Row],[% anualiz]]) +SUMPRODUCT((RngTipo=$CU$7)*(rngAnualizable="No")*(rngNormalizable="Sí")*(DATOS_[[#This Row],[Conc.Sal.01]:[C.Extra.11]]))*(1/DATOS_[[#This Row],[% normaliz]]) +SUMPRODUCT((RngTipo=$CU$7)*(rngAnualizable="No")*(rngNormalizable="No")*(DATOS_[[#This Row],[Conc.Sal.01]:[C.Extra.11]]))) *IF(DATOS_[[#This Row],[Check Equiparado]]="Sí",1,0)} -> 0 | CV17: =+DATOS_[[#This Row],[TOTAL SALARIO Eq]]+DATOS_[[#This Row],[Tot Extrasalarial Eq]] -> 0 | CW17: =DATOS_[[#This Row],[S.BASE]] -> 0 | CX17: =+SUM(DATOS_[[#This Row],[Conc.Sal.01]:[Conc.Sal.30]]) -> 0 | CY17: =+DATOS_[[#This Row],[SALARIO BASE Ef]]+DATOS_[[#This Row],[Tot COMPL.SAL Ef]] -> 0 | CZ17: =+SUM(DATOS_[[#This Row],[C.Extra.01]:[C.Extra.11]]) -> 0 | DA17: =+DATOS_[[#This Row],[TOTAL SALARIO Ef]]+DATOS_[[#This Row],[Tot Extrasalarial Ef]] -> 0 | DB17: =MIN(IF(DATOS_[[#This Row],[Fecha Fin Contrato]]="",$D$4,DATOS_[[#This Row],[Fecha Fin Contrato]]),$D$4)-MAX(DATOS_[[#This Row],[Fecha de Contratación]],$D$3)+1 -> 366 | DC17: =IF(COUNTIFS(DATOS_[id/cod],DATOS_[[#This Row],[id/cod]])>1,DATOS_[[#This Row],[id/cod]],"") | DD17: =(Inicio!$G$10-DATOS_[[#This Row],[Fecha Nacimiento]])/365.25 -> 57.845311 | DE17: =(Inicio!$G$10-DATOS_[[#This Row],[Fecha de Antigüedad]])/365.25 -> 28.640657 | DF17: =+VLOOKUP(DATOS_[[#This Row],[Clave de Contrato]],TblTiposContrato13[],3,FALSE) -> #N/A | DG17: =+VLOOKUP(DATOS_[[#This Row],[Clave de Contrato]],TblTiposContrato13[],4,FALSE) -> #N/A | DH17: =VLOOKUP(DATOS_[[#This Row],[Edad]],CONTRATOS!TblRngEdad,2,TRUE) -> 55 a 60 | DI17: =VLOOKUP(DATOS_[[#This Row],[Antigüedad]],TblRngAntg14[],2,TRUE) -> más de 15
A18: ANGEL HEREDIA AGUILERA | B18: 10 | C18: HOMBRE | D18: 25774 | E18: BACHILLER | H18: 35432 | J18: 35432 | M18: 1 | Q18: ASESORES | R18: ASESORES | S18: ASESOR | T18: CONTINUO | U18: SI | Y18: 14000425011981 | AA18: PERSONAL ADMINISTRATIVO | AC18: 8 | CH18: =+MAX($D$3,DATOS_[[#This Row],[Fecha Inicio Sit. Contract.]]) -> 45292 | CI18: =+MIN($D$4,DATOS_[[#This Row],[Fecha Fin Sit. Contract.]]) -> 45657 | CJ18: =+DATOS_[[#This Row],[% de jornada]]*IF(DATOS_[[#This Row],[% jornada reducida]]="",1,DATOS_[[#This Row],[% jornada reducida]]) -> 1 | CK18: =+(DATOS_[[#This Row],[F.fin.cal]]-DATOS_[[#This Row],[F.ini.cal]]+1)/($D$4-$D$3+1) -> 1 | CL18: =IF(OR(AND(DATOS_[[#This Row],[Fecha Fin Contrato]]<$D$3,DATOS_[[#This Row],[Fecha Fin Contrato]]<>""),DATOS_[[#This Row],[Fecha de Contratación]]>$D$4),"Fuera","Dentro") -> Dentro | CM18: {=IF(MAX(IF(DATOS_[id/cod]=DATOS_[[#This Row],[id/cod]],DATOS_[F.fin.cal]))=DATOS_[[#This Row],[F.fin.cal]],"Sí","NO")} -> Sí | CN18: =IF(AND(DATOS_[[#This Row],[% normaliz]]<>1,DATOS_[[#This Row],[% anualiz]]=1),"Sí","NO") -> NO | CO18: =IF(AND(DATOS_[[#This Row],[% normaliz]]=1,DATOS_[[#This Row],[% anualiz]]<>1),"Sí","NO") -> NO | CP18: =IF(AND(DATOS_[[#This Row],[% normaliz]]<>1,DATOS_[[#This Row],[% anualiz]]<>1),"Sí","NO") -> NO | CQ18: =+IF(DATOS_[[#This Row],[% normaliz]]*DATOS_[[#This Row],[% anualiz]]=1,"NO","Sí") -> NO | CR18: =(DATOS_[[#This Row],[S.BASE]]*(1/DATOS_[[#This Row],[% normaliz]])*(1/DATOS_[[#This Row],[% anualiz]]))*IF(DATOS_[[#This Row],[Check Equiparado]]="Sí",1,0) -> 0 | CS18: =(SUMPRODUCT((RngTipo=$CS$7)*(rngAnualizable="Sí")*(rngNormalizable="Sí")*(DATOS_[[#This Row],[Conc.Sal.01]:[C.Extra.11]]))*(1/DATOS_[[#This Row],[% anualiz]])*(1/DATOS_[[#This Row],[% normaliz]]) +SUMPRODUCT((RngTipo=$CS$7)*(rngAnualizable="Sí")*(rngNormalizable="No")*(DATOS_[[#This Row],[Conc.Sal.01]:[C.Extra.11]]))*(1/DATOS_[[#This Row],[% anualiz]]) +SUMPRODUCT((RngTipo=$CS$7)*(rngAnualizable="No")*(rngNormalizable="Sí")*(DATOS_[[#This Row],[Conc.Sal.01]:[C.Extra.11]]))*(1/DATOS_[[#This Row],[% normaliz]]) +SUMPRODUCT((RngTipo=$CS$7)*(rngAnualizable="No")*(rngNormalizable="No")*(DATOS_[[#This Row],[Conc.Sal.01]:[C.Extra.11]]))) *IF(DATOS_[[#This Row],[Check Equiparado]]="Sí",1,0) -> 0 | CT18: =+DATOS_[[#This Row],[SALARIO BASE Eq]]+DATOS_[[#This Row],[Tot COMPL.SAL Eq]] -> 0 | CU18: {=(SUMPRODUCT((RngTipo=$CU$7)*(rngAnualizable="Sí")*(rngNormalizable="Sí")*(DATOS_[[#This Row],[Conc.Sal.01]:[C.Extra.11]]))*(1/DATOS_[[#This Row],[% anualiz]])*(1/DATOS_[[#This Row],[% normaliz]]) +SUMPRODUCT((RngTipo=$CU$7)*(rngAnualizable="Sí")*(rngNormalizable="No")*(DATOS_[[#This Row],[Conc.Sal.01]:[C.Extra.11]]))*(1/DATOS_[[#This Row],[% anualiz]]) +SUMPRODUCT((RngTipo=$CU$7)*(rngAnualizable="No")*(rngNormalizable="Sí")*(DATOS_[[#This Row],[Conc.Sal.01]:[C.Extra.11]]))*(1/DATOS_[[#This Row],[% normaliz]]) +SUMPRODUCT((RngTipo=$CU$7)*(rngAnualizable="No")*(rngNormalizable="No")*(DATOS_[[#This Row],[Conc.Sal.01]:[C.Extra.11]]))) *IF(DATOS_[[#This Row],[Check Equiparado]]="Sí",1,0)} -> 0 | CV18: =+DATOS_[[#This Row],[TOTAL SALARIO Eq]]+DATOS_[[#This Row],[Tot Extrasalarial Eq]] -> 0 | CW18: =DATOS_[[#This Row],[S.BASE]] -> 0 | CX18: =+SUM(DATOS_[[#This Row],[Conc.Sal.01]:[Conc.Sal.30]]) -> 0 | CY18: =+DATOS_[[#This Row],[SALARIO BASE Ef]]+DATOS_[[#This Row],[Tot COMPL.SAL Ef]] -> 0 | CZ18: =+SUM(DATOS_[[#This Row],[C.Extra.01]:[C.Extra.11]]) -> 0 | DA18: =+DATOS_[[#This Row],[TOTAL SALARIO Ef]]+DATOS_[[#This Row],[Tot Extrasalarial Ef]] -> 0 | DB18: =MIN(IF(DATOS_[[#This Row],[Fecha Fin Contrato]]="",$D$4,DATOS_[[#This Row],[Fecha Fin Contrato]]),$D$4)-MAX(DATOS_[[#This Row],[Fecha de Contratación]],$D$3)+1 -> 366 | DC18: =IF(COUNTIFS(DATOS_[id/cod],DATOS_[[#This Row],[id/cod]])>1,DATOS_[[#This Row],[id/cod]],"") | DD18: =(Inicio!$G$10-DATOS_[[#This Row],[Fecha Nacimiento]])/365.25 -> 54.436687 | DE18: =(Inicio!$G$10-DATOS_[[#This Row],[Fecha de Antigüedad]])/365.25 -> 27.994524 | DF18: =+VLOOKUP(DATOS_[[#This Row],[Clave de Contrato]],TblTiposContrato13[],3,FALSE) -> #N/A | DG18: =+VLOOKUP(DATOS_[[#This Row],[Clave de Contrato]],TblTiposContrato13[],4,FALSE) -> #N/A | DH18: =VLOOKUP(DATOS_[[#This Row],[Edad]],CONTRATOS!TblRngEdad,2,TRUE) -> 50 a 55 | DI18: =VLOOKUP(DATOS_[[#This Row],[Antigüedad]],TblRngAntg14[],2,TRUE) -> más de 15
A19: Mª DOLORES BRAVO MOLINA | B19: 11 | C19: MUJER | D19: 21815 | E19: CERTIFICADO ESCOLARIDAD | H19: 36391 | J19: 36391 | M19: 0.75 | P19: 200 | Q19: LIMPIEZA | R19: LIMPIEZA | S19: LIMPIADORA (ENCARGADA) | T19: PARTIDO | U19: SI | W19: GRUPO 05 | Y19: 14000425011981 | Z19: limpiador/a | AA19: PERSONAL SUBALTERNO | AC19: 10 | AD19: 5367.89 | AE19: 17.97 | AF19: 500.43 | AG19: 348.79 | AH19: 715.04 | AI19: 0 | AJ19: 412.19 | AK19: 523.78 | AL19: 98.5 | AM19: 95.04 | AN19: 1902.8 | AO19: 680.43 | AP19: 0 | AQ19: 0 | AR19: 0 | AS19: 0 | AT19: 2225.93 | AU19: 389.64 | AV19: 1095.92 | AW19: 4117.44 | AX19: 0 | AY19: 0 | CH19: =+MAX($D$3,DATOS_[[#This Row],[Fecha Inicio Sit. Contract.]]) -> 45292 | CI19: =+MIN($D$4,DATOS_[[#This Row],[Fecha Fin Sit. Contract.]]) -> 45657 | CJ19: =+DATOS_[[#This Row],[% de jornada]]*IF(DATOS_[[#This Row],[% jornada reducida]]="",1,DATOS_[[#This Row],[% jornada reducida]]) -> 0.75 | CK19: =+(DATOS_[[#This Row],[F.fin.cal]]-DATOS_[[#This Row],[F.ini.cal]]+1)/($D$4-$D$3+1) -> 1 | CL19: =IF(OR(AND(DATOS_[[#This Row],[Fecha Fin Contrato]]<$D$3,DATOS_[[#This Row],[Fecha Fin Contrato]]<>""),DATOS_[[#This Row],[Fecha de Contratación]]>$D$4),"Fuera","Dentro") -> Dentro | CM19: {=IF(MAX(IF(DATOS_[id/cod]=DATOS_[[#This Row],[id/cod]],DATOS_[F.fin.cal]))=DATOS_[[#This Row],[F.fin.cal]],"Sí","NO")} -> Sí | CN19: =IF(AND(DATOS_[[#This Row],[% normaliz]]<>1,DATOS_[[#This Row],[% anualiz]]=1),"Sí","NO") -> Sí | CO19: =IF(AND(DATOS_[[#This Row],[% normaliz]]=1,DATOS_[[#This Row],[% anualiz]]<>1),"Sí","NO") -> NO | CP19: =IF(AND(DATOS_[[#This Row],[% normaliz]]<>1,DATOS_[[#This Row],[% anualiz]]<>1),"Sí","NO") -> NO | CQ19: =+IF(DATOS_[[#This Row],[% normaliz]]*DATOS_[[#This Row],[% anualiz]]=1,"NO","Sí") -> Sí | CR19: =(DATOS_[[#This Row],[S.BASE]]*(1/DATOS_[[#This Row],[% normaliz]])*(1/DATOS_[[#This Row],[% anualiz]]))*IF(DATOS_[[#This Row],[Check Equiparado]]="Sí",1,0) -> 7157.1867 | CS19: =(SUMPRODUCT((RngTipo=$CS$7)*(rngAnualizable="Sí")*(rngNormalizable="Sí")*(DATOS_[[#This Row],[Conc.Sal.01]:[C.Extra.11]]))*(1/DATOS_[[#This Row],[% anualiz]])*(1/DATOS_[[#This Row],[% normaliz]]) +SUMPRODUCT((RngTipo=$CS$7)*(rngAnualizable="Sí")*(rngNormalizable="No")*(DATOS_[[#This Row],[Conc.Sal.01]:[C.Extra.11]]))*(1/DATOS_[[#This Row],[% anualiz]]) +SUMPRODUCT((RngTipo=$CS$7)*(rngAnualizable="No")*(rngNormalizable="Sí")*(DATOS_[[#This Row],[Conc.Sal.01]:[C.Extra.11]]))*(1/DATOS_[[#This Row],[% normaliz]]) +SUMPRODUCT((RngTipo=$CS$7)*(rngAnualizable="No")*(rngNormalizable="No")*(DATOS_[[#This Row],[Conc.Sal.01]:[C.Extra.11]]))) *IF(DATOS_[[#This Row],[Check Equiparado]]="Sí",1,0) -> 13069.4 | CT19: =+DATOS_[[#This Row],[SALARIO BASE Eq]]+DATOS_[[#This Row],[Tot COMPL.SAL Eq]] -> 20226.587 | CU19: {=(SUMPRODUCT((RngTipo=$CU$7)*(rngAnualizable="Sí")*(rngNormalizable="Sí")*(DATOS_[[#This Row],[Conc.Sal.01]:[C.Extra.11]]))*(1/DATOS_[[#This Row],[% anualiz]])*(1/DATOS_[[#This Row],[% normaliz]]) +SUMPRODUCT((RngTipo=$CU$7)*(rngAnualizable="Sí")*(rngNormalizable="No")*(DATOS_[[#This Row],[Conc.Sal.01]:[C.Extra.11]]))*(1/DATOS_[[#This Row],[% anualiz]]) +SUMPRODUCT((RngTipo=$CU$7)*(rngAnualizable="No")*(rngNormalizable="Sí")*(DATOS_[[#This Row],[Conc.Sal.01]:[C.Extra.11]]))*(1/DATOS_[[#This Row],[% normaliz]]) +SUMPRODUCT((RngTipo=$CU$7)*(rngAnualizable="No")*(rngNormalizable="No")*(DATOS_[[#This Row],[Conc.Sal.01]:[C.Extra.11]]))) *IF(DATOS_[[#This Row],[Check Equiparado]]="Sí",1,0)} -> 4429.1333 | CV19: =+DATOS_[[#This Row],[TOTAL SALARIO Eq]]+DATOS_[[#This Row],[Tot Extrasalarial Eq]] -> 24655.72 | CW19: =DATOS_[[#This Row],[S.BASE]] -> 5367.89 | CX19: =+SUM(DATOS_[[#This Row],[Conc.Sal.01]:[Conc.Sal.30]]) -> 13123.9 | CY19: =+DATOS_[[#This Row],[SALARIO BASE Ef]]+DATOS_[[#This Row],[Tot COMPL.SAL Ef]] -> 18491.79 | CZ19: =+SUM(DATOS_[[#This Row],[C.Extra.01]:[C.Extra.11]]) -> 0 | DA19: =+DATOS_[[#This Row],[TOTAL SALARIO Ef]]+DATOS_[[#This Row],[Tot Extrasalarial Ef]] -> 18491.79 | DB19: =MIN(IF(DATOS_[[#This Row],[Fecha Fin Contrato]]="",$D$4,DATOS_[[#This Row],[Fecha Fin Contrato]]),$D$4)-MAX(DATOS_[[#This Row],[Fecha de Contratación]],$D$3)+1 -> 366 | DC19: =IF(COUNTIFS(DATOS_[id/cod],DATOS_[[#This Row],[id/cod]])>1,DATOS_[[#This Row],[id/cod]],"") | DD19: =(Inicio!$G$10-DATOS_[[#This Row],[Fecha Nacimiento]])/365.25 -> 65.275838 | DE19: =(Inicio!$G$10-DATOS_[[#This Row],[Fecha de Antigüedad]])/365.25 -> 25.368925 | DF19: =+VLOOKUP(DATOS_[[#This Row],[Clave de Contrato]],TblTiposContrato13[],3,FALSE) -> Parcial | DG19: =+VLOOKUP(DATOS_[[#This Row],[Clave de Contrato]],TblTiposContrato13[],4,FALSE) -> Indefinido | DH19: =VLOOKUP(DATOS_[[#This Row],[Edad]],CONTRATOS!TblRngEdad,2,TRUE) -> 60 en adelante | DI19: =VLOOKUP(DATOS_[[#This Row],[Antigüedad]],TblRngAntg14[],2,TRUE) -> más de 15
A20: MERCEDES RAYA VAZQUEZ | B20: 12 | C20: MUJER | D20: 25872 | E20: GRADUADO ESCOLAR | H20: 36571 | J20: 36571 | M20: 0.75 | P20: 100 | Q20: LIMPIEZA | R20: LIMPIEZA | S20: LIMPIADORA | T20: PARTIDO | U20: SI | W20: GRUPO 05 | Y20: 14000425011981 | Z20: limpiador/a | AA20: PERSONAL SUBALTERNO | AC20: 10 | AD20: 8377.56 | AE20: 37.44 | AF20: 854.16 | AG20: 543.96 | AH20: 1158.57 | AI20: 95.22 | AJ20: 843.12 | AK20: 820.68 | AL20: 0 | AM20: 0 | AN20: 0 | AO20: 0 | AP20: 300 | AQ20: 0 | AR20: 374 | AS20: 0 | AT20: 2443.1 | AU20: 0 | AV20: 0 | AW20: 0 | AX20: 0 | AY20: 65 | CH20: =+MAX($D$3,DATOS_[[#This Row],[Fecha Inicio Sit. Contract.]]) -> 45292 | CI20: =+MIN($D$4,DATOS_[[#This Row],[Fecha Fin Sit. Contract.]]) -> 45657 | CJ20: =+DATOS_[[#This Row],[% de jornada]]*IF(DATOS_[[#This Row],[% jornada reducida]]="",1,DATOS_[[#This Row],[% jornada reducida]]) -> 0.75 | CK20: =+(DATOS_[[#This Row],[F.fin.cal]]-DATOS_[[#This Row],[F.ini.cal]]+1)/($D$4-$D$3+1) -> 1 | CL20: =IF(OR(AND(DATOS_[[#This Row],[Fecha Fin Contrato]]<$D$3,DATOS_[[#This Row],[Fecha Fin Contrato]]<>""),DATOS_[[#This Row],[Fecha de Contratación]]>$D$4),"Fuera","Dentro") -> Dentro | CM20: {=IF(MAX(IF(DATOS_[id/cod]=DATOS_[[#This Row],[id/cod]],DATOS_[F.fin.cal]))=DATOS_[[#This Row],[F.fin.cal]],"Sí","NO")} -> Sí | CN20: =IF(AND(DATOS_[[#This Row],[% normaliz]]<>1,DATOS_[[#This Row],[% anualiz]]=1),"Sí","NO") -> Sí | CO20: =IF(AND(DATOS_[[#This Row],[% normaliz]]=1,DATOS_[[#This Row],[% anualiz]]<>1),"Sí","NO") -> NO | CP20: =IF(AND(DATOS_[[#This Row],[% normaliz]]<>1,DATOS_[[#This Row],[% anualiz]]<>1),"Sí","NO") -> NO | CQ20: =+IF(DATOS_[[#This Row],[% normaliz]]*DATOS_[[#This Row],[% anualiz]]=1,"NO","Sí") -> Sí | CR20: =(DATOS_[[#This Row],[S.BASE]]*(1/DATOS_[[#This Row],[% normaliz]])*(1/DATOS_[[#This Row],[% anualiz]]))*IF(DATOS_[[#This Row],[Check Equiparado]]="Sí",1,0) -> 11170.08 | CS20: =(SUMPRODUCT((RngTipo=$CS$7)*(rngAnualizable="Sí")*(rngNormalizable="Sí")*(DATOS_[[#This Row],[Conc.Sal.01]:[C.Extra.11]]))*(1/DATOS_[[#This Row],[% anualiz]])*(1/DATOS_[[#This Row],[% normaliz]]) +SUMPRODUCT((RngTipo=$CS$7)*(rngAnualizable="Sí")*(rngNormalizable="No")*(DATOS_[[#This Row],[Conc.Sal.01]:[C.Extra.11]]))*(1/DATOS_[[#This Row],[% anualiz]]) +SUMPRODUCT((RngTipo=$CS$7)*(rngAnualizable="No")*(rngNormalizable="Sí")*(DATOS_[[#This Row],[Conc.Sal.01]:[C.Extra.11]]))*(1/DATOS_[[#This Row],[% normaliz]]) +SUMPRODUCT((RngTipo=$CS$7)*(rngAnualizable="No")*(rngNormalizable="No")*(DATOS_[[#This Row],[Conc.Sal.01]:[C.Extra.11]]))) *IF(DATOS_[[#This Row],[Check Equiparado]]="Sí",1,0) -> 6789.5333 | CT20: =+DATOS_[[#This Row],[SALARIO BASE Eq]]+DATOS_[[#This Row],[Tot COMPL.SAL Eq]] -> 17959.613 | CU20: {=(SUMPRODUCT((RngTipo=$CU$7)*(rngAnualizable="Sí")*(rngNormalizable="Sí")*(DATOS_[[#This Row],[Conc.Sal.01]:[C.Extra.11]]))*(1/DATOS_[[#This Row],[% anualiz]])*(1/DATOS_[[#This Row],[% normaliz]]) +SUMPRODUCT((RngTipo=$CU$7)*(rngAnualizable="Sí")*(rngNormalizable="No")*(DATOS_[[#This Row],[Conc.Sal.01]:[C.Extra.11]]))*(1/DATOS_[[#This Row],[% anualiz]]) +SUMPRODUCT((RngTipo=$CU$7)*(rngAnualizable="No")*(rngNormalizable="Sí")*(DATOS_[[#This Row],[Conc.Sal.01]:[C.Extra.11]]))*(1/DATOS_[[#This Row],[% normaliz]]) +SUMPRODUCT((RngTipo=$CU$7)*(rngAnualizable="No")*(rngNormalizable="No")*(DATOS_[[#This Row],[Conc.Sal.01]:[C.Extra.11]]))) *IF(DATOS_[[#This Row],[Check Equiparado]]="Sí",1,0)} -> 3257.4667 | CV20: =+DATOS_[[#This Row],[TOTAL SALARIO Eq]]+DATOS_[[#This Row],[Tot Extrasalarial Eq]] -> 21217.08 | CW20: =DATOS_[[#This Row],[S.BASE]] -> 8377.56 | CX20: =+SUM(DATOS_[[#This Row],[Conc.Sal.01]:[Conc.Sal.30]]) -> 7535.25 | CY20: =+DATOS_[[#This Row],[SALARIO BASE Ef]]+DATOS_[[#This Row],[Tot COMPL.SAL Ef]] -> 15912.81 | CZ20: =+SUM(DATOS_[[#This Row],[C.Extra.01]:[C.Extra.11]]) -> 0 | DA20: =+DATOS_[[#This Row],[TOTAL SALARIO Ef]]+DATOS_[[#This Row],[Tot Extrasalarial Ef]] -> 15912.81 | DB20: =MIN(IF(DATOS_[[#This Row],[Fecha Fin Contrato]]="",$D$4,DATOS_[[#This Row],[Fecha Fin Contrato]]),$D$4)-MAX(DATOS_[[#This Row],[Fecha de Contratación]],$D$3)+1 -> 366 | DC20: =IF(COUNTIFS(DATOS_[id/cod],DATOS_[[#This Row],[id/cod]])>1,DATOS_[[#This Row],[id/cod]],"") | DD20: =(Inicio!$G$10-DATOS_[[#This Row],[Fecha Nacimiento]])/365.25 -> 54.168378 | DE20: =(Inicio!$G$10-DATOS_[[#This Row],[Fecha de Antigüedad]])/365.25 -> 24.876112 | DF20: =+VLOOKUP(DATOS_[[#This Row],[Clave de Contrato]],TblTiposContrato13[],3,FALSE) -> Completa | DG20: =+VLOOKUP(DATOS_[[#This Row],[Clave de Contrato]],TblTiposContrato13[],4,FALSE) -> Indefinido | DH20: =VLOOKUP(DATOS_[[#This Row],[Edad]],CONTRATOS!TblRngEdad,2,TRUE) -> 50 a 55 | DI20: =VLOOKUP(DATOS_[[#This Row],[Antigüedad]],TblRngAntg14[],2,TRUE) -> más de 15
A21: JOSE ENRIQUE HIDALGO SEOANE | B21: 13 | C21: HOMBRE | D21: 27239 | E21: FPII | H21: 36571 | J21: 36571 | M21: 1 | Q21: CONDUCTORES | R21: CONDUCTORES | S21: ASESOR | T21: CONTINUO | U21: SI | Y21: 14000425011981 | AA21: PERSONAL OPERARIO GENERAL | AC21: 8 | CH21: =+MAX($D$3,DATOS_[[#This Row],[Fecha Inicio Sit. Contract.]]) -> 45292 | CI21: =+MIN($D$4,DATOS_[[#This Row],[Fecha Fin Sit. Contract.]]) -> 45657 | CJ21: =+DATOS_[[#This Row],[% de jornada]]*IF(DATOS_[[#This Row],[% jornada reducida]]="",1,DATOS_[[#This Row],[% jornada reducida]]) -> 1 | CK21: =+(DATOS_[[#This Row],[F.fin.cal]]-DATOS_[[#This Row],[F.ini.cal]]+1)/($D$4-$D$3+1) -> 1 | CL21: =IF(OR(AND(DATOS_[[#This Row],[Fecha Fin Contrato]]<$D$3,DATOS_[[#This Row],[Fecha Fin Contrato]]<>""),DATOS_[[#This Row],[Fecha de Contratación]]>$D$4),"Fuera","Dentro") -> Dentro | CM21: {=IF(MAX(IF(DATOS_[id/cod]=DATOS_[[#This Row],[id/cod]],DATOS_[F.fin.cal]))=DATOS_[[#This Row],[F.fin.cal]],"Sí","NO")} -> Sí | CN21: =IF(AND(DATOS_[[#This Row],[% normaliz]]<>1,DATOS_[[#This Row],[% anualiz]]=1),"Sí","NO") -> NO | CO21: =IF(AND(DATOS_[[#This Row],[% normaliz]]=1,DATOS_[[#This Row],[% anualiz]]<>1),"Sí","NO") -> NO | CP21: =IF(AND(DATOS_[[#This Row],[% normaliz]]<>1,DATOS_[[#This Row],[% anualiz]]<>1),"Sí","NO") -> NO | CQ21: =+IF(DATOS_[[#This Row],[% normaliz]]*DATOS_[[#This Row],[% anualiz]]=1,"NO","Sí") -> NO | CR21: =(DATOS_[[#This Row],[S.BASE]]*(1/DATOS_[[#This Row],[% normaliz]])*(1/DATOS_[[#This Row],[% anualiz]]))*IF(DATOS_[[#This Row],[Check Equiparado]]="Sí",1,0) -> 0 | CS21: =(SUMPRODUCT((RngTipo=$CS$7)*(rngAnualizable="Sí")*(rngNormalizable="Sí")*(DATOS_[[#This Row],[Conc.Sal.01]:[C.Extra.11]]))*(1/DATOS_[[#This Row],[% anualiz]])*(1/DATOS_[[#This Row],[% normaliz]]) +SUMPRODUCT((RngTipo=$CS$7)*(rngAnualizable="Sí")*(rngNormalizable="No")*(DATOS_[[#This Row],[Conc.Sal.01]:[C.Extra.11]]))*(1/DATOS_[[#This Row],[% anualiz]]) +SUMPRODUCT((RngTipo=$CS$7)*(rngAnualizable="No")*(rngNormalizable="Sí")*(DATOS_[[#This Row],[Conc.Sal.01]:[C.Extra.11]]))*(1/DATOS_[[#This Row],[% normaliz]]) +SUMPRODUCT((RngTipo=$CS$7)*(rngAnualizable="No")*(rngNormalizable="No")*(DATOS_[[#This Row],[Conc.Sal.01]:[C.Extra.11]]))) *IF(DATOS_[[#This Row],[Check Equiparado]]="Sí",1,0) -> 0 | CT21: =+DATOS_[[#This Row],[SALARIO BASE Eq]]+DATOS_[[#This Row],[Tot COMPL.SAL Eq]] -> 0 | CU21: {=(SUMPRODUCT((RngTipo=$CU$7)*(rngAnualizable="Sí")*(rngNormalizable="Sí")*(DATOS_[[#This Row],[Conc.Sal.01]:[C.Extra.11]]))*(1/DATOS_[[#This Row],[% anualiz]])*(1/DATOS_[[#This Row],[% normaliz]]) +SUMPRODUCT((RngTipo=$CU$7)*(rngAnualizable="Sí")*(rngNormalizable="No")*(DATOS_[[#This Row],[Conc.Sal.01]:[C.Extra.11]]))*(1/DATOS_[[#This Row],[% anualiz]]) +SUMPRODUCT((RngTipo=$CU$7)*(rngAnualizable="No")*(rngNormalizable="Sí")*(DATOS_[[#This Row],[Conc.Sal.01]:[C.Extra.11]]))*(1/DATOS_[[#This Row],[% normaliz]]) +SUMPRODUCT((RngTipo=$CU$7)*(rngAnualizable="No")*(rngNormalizable="No")*(DATOS_[[#This Row],[Conc.Sal.01]:[C.Extra.11]]))) *IF(DATOS_[[#This Row],[Check Equiparado]]="Sí",1,0)} -> 0 | CV21: =+DATOS_[[#This Row],[TOTAL SALARIO Eq]]+DATOS_[[#This Row],[Tot Extrasalarial Eq]] -> 0 | CW21: =DATOS_[[#This Row],[S.BASE]] -> 0 | CX21: =+SUM(DATOS_[[#This Row],[Conc.Sal.01]:[Conc.Sal.30]]) -> 0 | CY21: =+DATOS_[[#This Row],[SALARIO BASE Ef]]+DATOS_[[#This Row],[Tot COMPL.SAL Ef]] -> 0 | CZ21: =+SUM(DATOS_[[#This Row],[C.Extra.01]:[C.Extra.11]]) -> 0 | DA21: =+DATOS_[[#This Row],[TOTAL SALARIO Ef]]+DATOS_[[#This Row],[Tot Extrasalarial Ef]] -> 0 | DB21: =MIN(IF(DATOS_[[#This Row],[Fecha Fin Contrato]]="",$D$4,DATOS_[[#This Row],[Fecha Fin Contrato]]),$D$4)-MAX(DATOS_[[#This Row],[Fecha de Contratación]],$D$3)+1 -> 366 | DC21: =IF(COUNTIFS(DATOS_[id/cod],DATOS_[[#This Row],[id/cod]])>1,DATOS_[[#This Row],[id/cod]],"") | DD21: =(Inicio!$G$10-DATOS_[[#This Row],[Fecha Nacimiento]])/365.25 -> 50.425736 | DE21: =(Inicio!$G$10-DATOS_[[#This Row],[Fecha de Antigüedad]])/365.25 -> 24.876112 | DF21: =+VLOOKUP(DATOS_[[#This Row],[Clave de Contrato]],TblTiposContrato13[],3,FALSE) -> #N/A | DG21: =+VLOOKUP(DATOS_[[#This Row],[Clave de Contrato]],TblTiposContrato13[],4,FALSE) -> #N/A | DH21: =VLOOKUP(DATOS_[[#This Row],[Edad]],CONTRATOS!TblRngEdad,2,TRUE) -> 50 a 55 | DI21: =VLOOKUP(DATOS_[[#This Row],[Antigüedad]],TblRngAntg14[],2,TRUE) -> más de 15
A22: MIGUEL ANGEL FERNANDEZ MUÑOZ | B22: 14 | C22: HOMBRE | D22: 28650 | E22: FPI | H22: 36743 | J22: 36743 | M22: 1 | Q22: CONDUCTORES | R22: CONDUCTORES | S22: CONDUCTOR/OPERARIO CREMATORIO | T22: CONTINUO | U22: SI | Y22: 14000425011981 | AA22: PERSONAL OPERARIO GENERAL | AC22: 8 | CH22: =+MAX($D$3,DATOS_[[#This Row],[Fecha Inicio Sit. Contract.]]) -> 45292 | CI22: =+MIN($D$4,DATOS_[[#This Row],[Fecha Fin Sit. Contract.]]) -> 45657 | CJ22: =+DATOS_[[#This Row],[% de jornada]]*IF(DATOS_[[#This Row],[% jornada reducida]]="",1,DATOS_[[#This Row],[% jornada reducida]]) -> 1 | CK22: =+(DATOS_[[#This Row],[F.fin.cal]]-DATOS_[[#This Row],[F.ini.cal]]+1)/($D$4-$D$3+1) -> 1 | CL22: =IF(OR(AND(DATOS_[[#This Row],[Fecha Fin Contrato]]<$D$3,DATOS_[[#This Row],[Fecha Fin Contrato]]<>""),DATOS_[[#This Row],[Fecha de Contratación]]>$D$4),"Fuera","Dentro") -> Dentro | CM22: {=IF(MAX(IF(DATOS_[id/cod]=DATOS_[[#This Row],[id/cod]],DATOS_[F.fin.cal]))=DATOS_[[#This Row],[F.fin.cal]],"Sí","NO")} -> Sí | CN22: =IF(AND(DATOS_[[#This Row],[% normaliz]]<>1,DATOS_[[#This Row],[% anualiz]]=1),"Sí","NO") -> NO | CO22: =IF(AND(DATOS_[[#This Row],[% normaliz]]=1,DATOS_[[#This Row],[% anualiz]]<>1),"Sí","NO") -> NO | CP22: =IF(AND(DATOS_[[#This Row],[% normaliz]]<>1,DATOS_[[#This Row],[% anualiz]]<>1),"Sí","NO") -> NO | CQ22: =+IF(DATOS_[[#This Row],[% normaliz]]*DATOS_[[#This Row],[% anualiz]]=1,"NO","Sí") -> NO | CR22: =(DATOS_[[#This Row],[S.BASE]]*(1/DATOS_[[#This Row],[% normaliz]])*(1/DATOS_[[#This Row],[% anualiz]]))*IF(DATOS_[[#This Row],[Check Equiparado]]="Sí",1,0) -> 0 | CS22: =(SUMPRODUCT((RngTipo=$CS$7)*(rngAnualizable="Sí")*(rngNormalizable="Sí")*(DATOS_[[#This Row],[Conc.Sal.01]:[C.Extra.11]]))*(1/DATOS_[[#This Row],[% anualiz]])*(1/DATOS_[[#This Row],[% normaliz]]) +SUMPRODUCT((RngTipo=$CS$7)*(rngAnualizable="Sí")*(rngNormalizable="No")*(DATOS_[[#This Row],[Conc.Sal.01]:[C.Extra.11]]))*(1/DATOS_[[#This Row],[% anualiz]]) +SUMPRODUCT((RngTipo=$CS$7)*(rngAnualizable="No")*(rngNormalizable="Sí")*(DATOS_[[#This Row],[Conc.Sal.01]:[C.Extra.11]]))*(1/DATOS_[[#This Row],[% normaliz]]) +SUMPRODUCT((RngTipo=$CS$7)*(rngAnualizable="No")*(rngNormalizable="No")*(DATOS_[[#This Row],[Conc.Sal.01]:[C.Extra.11]]))) *IF(DATOS_[[#This Row],[Check Equiparado]]="Sí",1,0) -> 0 | CT22: =+DATOS_[[#This Row],[SALARIO BASE Eq]]+DATOS_[[#This Row],[Tot COMPL.SAL Eq]] -> 0 | CU22: {=(SUMPRODUCT((RngTipo=$CU$7)*(rngAnualizable="Sí")*(rngNormalizable="Sí")*(DATOS_[[#This Row],[Conc.Sal.01]:[C.Extra.11]]))*(1/DATOS_[[#This Row],[% anualiz]])*(1/DATOS_[[#This Row],[% normaliz]]) +SUMPRODUCT((RngTipo=$CU$7)*(rngAnualizable="Sí")*(rngNormalizable="No")*(DATOS_[[#This Row],[Conc.Sal.01]:[C.Extra.11]]))*(1/DATOS_[[#This Row],[% anualiz]]) +SUMPRODUCT((RngTipo=$CU$7)*(rngAnualizable="No")*(rngNormalizable="Sí")*(DATOS_[[#This Row],[Conc.Sal.01]:[C.Extra.11]]))*(1/DATOS_[[#This Row],[% normaliz]]) +SUMPRODUCT((RngTipo=$CU$7)*(rngAnualizable="No")*(rngNormalizable="No")*(DATOS_[[#This Row],[Conc.Sal.01]:[C.Extra.11]]))) *IF(DATOS_[[#This Row],[Check Equiparado]]="Sí",1,0)} -> 0 | CV22: =+DATOS_[[#This Row],[TOTAL SALARIO Eq]]+DATOS_[[#This Row],[Tot Extrasalarial Eq]] -> 0 | CW22: =DATOS_[[#This Row],[S.BASE]] -> 0 | CX22: =+SUM(DATOS_[[#This Row],[Conc.Sal.01]:[Conc.Sal.30]]) -> 0 | CY22: =+DATOS_[[#This Row],[SALARIO BASE Ef]]+DATOS_[[#This Row],[Tot COMPL.SAL Ef]] -> 0 | CZ22: =+SUM(DATOS_[[#This Row],[C.Extra.01]:[C.Extra.11]]) -> 0 | DA22: =+DATOS_[[#This Row],[TOTAL SALARIO Ef]]+DATOS_[[#This Row],[Tot Extrasalarial Ef]] -> 0 | DB22: =MIN(IF(DATOS_[[#This Row],[Fecha Fin Contrato]]="",$D$4,DATOS_[[#This Row],[Fecha Fin Contrato]]),$D$4)-MAX(DATOS_[[#This Row],[Fecha de Contratación]],$D$3)+1 -> 366 | DC22: =IF(COUNTIFS(DATOS_[id/cod],DATOS_[[#This Row],[id/cod]])>1,DATOS_[[#This Row],[id/cod]],"") | DD22: =(Inicio!$G$10-DATOS_[[#This Row],[Fecha Nacimiento]])/365.25 -> 46.562628 | DE22: =(Inicio!$G$10-DATOS_[[#This Row],[Fecha de Antigüedad]])/365.25 -> 24.405202 | DF22: =+VLOOKUP(DATOS_[[#This Row],[Clave de Contrato]],TblTiposContrato13[],3,FALSE) -> #N/A | DG22: =+VLOOKUP(DATOS_[[#This Row],[Clave de Contrato]],TblTiposContrato13[],4,FALSE) -> #N/A | DH22: =VLOOKUP(DATOS_[[#This Row],[Edad]],CONTRATOS!TblRngEdad,2,TRUE) -> 45 a 50 | DI22: =VLOOKUP(DATOS_[[#This Row],[Antigüedad]],TblRngAntg14[],2,TRUE) -> más de 15
A23: FRANCISCO DANIEL GARCIA ARANDA | B23: 15 | C23: HOMBRE | D23: 36924 | E23: FPI | H23: 36924 | J23: 36924 | M23: 1 | Q23: CONDUCTORES | R23: CONDUCTORES | S23: CONDUCTOR | T23: CONTINUO | U23: SI | Y23: 14000425011981 | AA23: PERSONAL OPERARIO GENERAL | AC23: 8 | CH23: =+MAX($D$3,DATOS_[[#This Row],[Fecha Inicio Sit. Contract.]]) -> 45292 | CI23: =+MIN($D$4,DATOS_[[#This Row],[Fecha Fin Sit. Contract.]]) -> 45657 | CJ23: =+DATOS_[[#This Row],[% de jornada]]*IF(DATOS_[[#This Row],[% jornada reducida]]="",1,DATOS_[[#This Row],[% jornada reducida]]) -> 1 | CK23: =+(DATOS_[[#This Row],[F.fin.cal]]-DATOS_[[#This Row],[F.ini.cal]]+1)/($D$4-$D$3+1) -> 1 | CL23: =IF(OR(AND(DATOS_[[#This Row],[Fecha Fin Contrato]]<$D$3,DATOS_[[#This Row],[Fecha Fin Contrato]]<>""),DATOS_[[#This Row],[Fecha de Contratación]]>$D$4),"Fuera","Dentro") -> Dentro | CM23: {=IF(MAX(IF(DATOS_[id/cod]=DATOS_[[#This Row],[id/cod]],DATOS_[F.fin.cal]))=DATOS_[[#This Row],[F.fin.cal]],"Sí","NO")} -> Sí | CN23: =IF(AND(DATOS_[[#This Row],[% normaliz]]<>1,DATOS_[[#This Row],[% anualiz]]=1),"Sí","NO") -> NO | CO23: =IF(AND(DATOS_[[#This Row],[% normaliz]]=1,DATOS_[[#This Row],[% anualiz]]<>1),"Sí","NO") -> NO | CP23: =IF(AND(DATOS_[[#This Row],[% normaliz]]<>1,DATOS_[[#This Row],[% anualiz]]<>1),"Sí","NO") -> NO | CQ23: =+IF(DATOS_[[#This Row],[% normaliz]]*DATOS_[[#This Row],[% anualiz]]=1,"NO","Sí") -> NO | CR23: =(DATOS_[[#This Row],[S.BASE]]*(1/DATOS_[[#This Row],[% normaliz]])*(1/DATOS_[[#This Row],[% anualiz]]))*IF(DATOS_[[#This Row],[Check Equiparado]]="Sí",1,0) -> 0 | CS23: =(SUMPRODUCT((RngTipo=$CS$7)*(rngAnualizable="Sí")*(rngNormalizable="Sí")*(DATOS_[[#This Row],[Conc.Sal.01]:[C.Extra.11]]))*(1/DATOS_[[#This Row],[% anualiz]])*(1/DATOS_[[#This Row],[% normaliz]]) +SUMPRODUCT((RngTipo=$CS$7)*(rngAnualizable="Sí")*(rngNormalizable="No")*(DATOS_[[#This Row],[Conc.Sal.01]:[C.Extra.11]]))*(1/DATOS_[[#This Row],[% anualiz]]) +SUMPRODUCT((RngTipo=$CS$7)*(rngAnualizable="No")*(rngNormalizable="Sí")*(DATOS_[[#This Row],[Conc.Sal.01]:[C.Extra.11]]))*(1/DATOS_[[#This Row],[% normaliz]]) +SUMPRODUCT((RngTipo=$CS$7)*(rngAnualizable="No")*(rngNormalizable="No")*(DATOS_[[#This Row],[Conc.Sal.01]:[C.Extra.11]]))) *IF(DATOS_[[#This Row],[Check Equiparado]]="Sí",1,0) -> 0 | CT23: =+DATOS_[[#This Row],[SALARIO BASE Eq]]+DATOS_[[#This Row],[Tot COMPL.SAL Eq]] -> 0 | CU23: {=(SUMPRODUCT((RngTipo=$CU$7)*(rngAnualizable="Sí")*(rngNormalizable="Sí")*(DATOS_[[#This Row],[Conc.Sal.01]:[C.Extra.11]]))*(1/DATOS_[[#This Row],[% anualiz]])*(1/DATOS_[[#This Row],[% normaliz]]) +SUMPRODUCT((RngTipo=$CU$7)*(rngAnualizable="Sí")*(rngNormalizable="No")*(DATOS_[[#This Row],[Conc.Sal.01]:[C.Extra.11]]))*(1/DATOS_[[#This Row],[% anualiz]]) +SUMPRODUCT((RngTipo=$CU$7)*(rngAnualizable="No")*(rngNormalizable="Sí")*(DATOS_[[#This Row],[Conc.Sal.01]:[C.Extra.11]]))*(1/DATOS_[[#This Row],[% normaliz]]) +SUMPRODUCT((RngTipo=$CU$7)*(rngAnualizable="No")*(rngNormalizable="No")*(DATOS_[[#This Row],[Conc.Sal.01]:[C.Extra.11]]))) *IF(DATOS_[[#This Row],[Check Equiparado]]="Sí",1,0)} -> 0 | CV23: =+DATOS_[[#This Row],[TOTAL SALARIO Eq]]+DATOS_[[#This Row],[Tot Extrasalarial Eq]] -> 0 | CW23: =DATOS_[[#This Row],[S.BASE]] -> 0 | CX23: =+SUM(DATOS_[[#This Row],[Conc.Sal.01]:[Conc.Sal.30]]) -> 0 | CY23: =+DATOS_[[#This Row],[SALARIO BASE Ef]]+DATOS_[[#This Row],[Tot COMPL.SAL Ef]] -> 0 | CZ23: =+SUM(DATOS_[[#This Row],[C.Extra.01]:[C.Extra.11]]) -> 0 | DA23: =+DATOS_[[#This Row],[TOTAL SALARIO Ef]]+DATOS_[[#This Row],[Tot Extrasalarial Ef]] -> 0 | DB23: =MIN(IF(DATOS_[[#This Row],[Fecha Fin Contrato]]="",$D$4,DATOS_[[#This Row],[Fecha Fin Contrato]]),$D$4)-MAX(DATOS_[[#This Row],[Fecha de Contratación]],$D$3)+1 -> 366 | DC23: =IF(COUNTIFS(DATOS_[id/cod],DATOS_[[#This Row],[id/cod]])>1,DATOS_[[#This Row],[id/cod]],"") | DD23: =(Inicio!$G$10-DATOS_[[#This Row],[Fecha Nacimiento]])/365.25 -> 23.909651 | DE23: =(Inicio!$G$10-DATOS_[[#This Row],[Fecha de Antigüedad]])/365.25 -> 23.909651 | DF23: =+VLOOKUP(DATOS_[[#This Row],[Clave de Contrato]],TblTiposContrato13[],3,FALSE) -> #N/A | DG23: =+VLOOKUP(DATOS_[[#This Row],[Clave de Contrato]],TblTiposContrato13[],4,FALSE) -> #N/A | DH23: =VLOOKUP(DATOS_[[#This Row],[Edad]],CONTRATOS!TblRngEdad,2,TRUE) -> 20 a 25 | DI23: =VLOOKUP(DATOS_[[#This Row],[Antigüedad]],TblRngAntg14[],2,TRUE) -> más de 15
A24: JUAN DE DIOS SANCHEZ CORONA | B24: 16 | C24: HOMBRE | D24: 23620 | E24: FPI | H24: 37165 | J24: 37165 | M24: 1 | Q24: CONDUCTORES | R24: CONDUCTORES | S24: RECEPCIONISTA | T24: CONTINUO | U24: SI | Y24: 14000425011981 | AA24: PERSONAL OPERARIO GENERAL | AC24: 8 | CH24: =+MAX($D$3,DATOS_[[#This Row],[Fecha Inicio Sit. Contract.]]) -> 45292 | CI24: =+MIN($D$4,DATOS_[[#This Row],[Fecha Fin Sit. Contract.]]) -> 45657 | CJ24: =+DATOS_[[#This Row],[% de jornada]]*IF(DATOS_[[#This Row],[% jornada reducida]]="",1,DATOS_[[#This Row],[% jornada reducida]]) -> 1 | CK24: =+(DATOS_[[#This Row],[F.fin.cal]]-DATOS_[[#This Row],[F.ini.cal]]+1)/($D$4-$D$3+1) -> 1 | CL24: =IF(OR(AND(DATOS_[[#This Row],[Fecha Fin Contrato]]<$D$3,DATOS_[[#This Row],[Fecha Fin Contrato]]<>""),DATOS_[[#This Row],[Fecha de Contratación]]>$D$4),"Fuera","Dentro") -> Dentro | CM24: {=IF(MAX(IF(DATOS_[id/cod]=DATOS_[[#This Row],[id/cod]],DATOS_[F.fin.cal]))=DATOS_[[#This Row],[F.fin.cal]],"Sí","NO")} -> Sí | CN24: =IF(AND(DATOS_[[#This Row],[% normaliz]]<>1,DATOS_[[#This Row],[% anualiz]]=1),"Sí","NO") -> NO | CO24: =IF(AND(DATOS_[[#This Row],[% normaliz]]=1,DATOS_[[#This Row],[% anualiz]]<>1),"Sí","NO") -> NO | CP24: =IF(AND(DATOS_[[#This Row],[% normaliz]]<>1,DATOS_[[#This Row],[% anualiz]]<>1),"Sí","NO") -> NO | CQ24: =+IF(DATOS_[[#This Row],[% normaliz]]*DATOS_[[#This Row],[% anualiz]]=1,"NO","Sí") -> NO | CR24: =(DATOS_[[#This Row],[S.BASE]]*(1/DATOS_[[#This Row],[% normaliz]])*(1/DATOS_[[#This Row],[% anualiz]]))*IF(DATOS_[[#This Row],[Check Equiparado]]="Sí",1,0) -> 0 | CS24: =(SUMPRODUCT((RngTipo=$CS$7)*(rngAnualizable="Sí")*(rngNormalizable="Sí")*(DATOS_[[#This Row],[Conc.Sal.01]:[C.Extra.11]]))*(1/DATOS_[[#This Row],[% anualiz]])*(1/DATOS_[[#This Row],[% normaliz]]) +SUMPRODUCT((RngTipo=$CS$7)*(rngAnualizable="Sí")*(rngNormalizable="No")*(DATOS_[[#This Row],[Conc.Sal.01]:[C.Extra.11]]))*(1/DATOS_[[#This Row],[% anualiz]]) +SUMPRODUCT((RngTipo=$CS$7)*(rngAnualizable="No")*(rngNormalizable="Sí")*(DATOS_[[#This Row],[Conc.Sal.01]:[C.Extra.11]]))*(1/DATOS_[[#This Row],[% normaliz]]) +SUMPRODUCT((RngTipo=$CS$7)*(rngAnualizable="No")*(rngNormalizable="No")*(DATOS_[[#This Row],[Conc.Sal.01]:[C.Extra.11]]))) *IF(DATOS_[[#This Row],[Check Equiparado]]="Sí",1,0) -> 0 | CT24: =+DATOS_[[#This Row],[SALARIO BASE Eq]]+DATOS_[[#This Row],[Tot COMPL.SAL Eq]] -> 0 | CU24: {=(SUMPRODUCT((RngTipo=$CU$7)*(rngAnualizable="Sí")*(rngNormalizable="Sí")*(DATOS_[[#This Row],[Conc.Sal.01]:[C.Extra.11]]))*(1/DATOS_[[#This Row],[% anualiz]])*(1/DATOS_[[#This Row],[% normaliz]]) +SUMPRODUCT((RngTipo=$CU$7)*(rngAnualizable="Sí")*(rngNormalizable="No")*(DATOS_[[#This Row],[Conc.Sal.01]:[C.Extra.11]]))*(1/DATOS_[[#This Row],[% anualiz]]) +SUMPRODUCT((RngTipo=$CU$7)*(rngAnualizable="No")*(rngNormalizable="Sí")*(DATOS_[[#This Row],[Conc.Sal.01]:[C.Extra.11]]))*(1/DATOS_[[#This Row],[% normaliz]]) +SUMPRODUCT((RngTipo=$CU$7)*(rngAnualizable="No")*(rngNormalizable="No")*(DATOS_[[#This Row],[Conc.Sal.01]:[C.Extra.11]]))) *IF(DATOS_[[#This Row],[Check Equiparado]]="Sí",1,0)} -> 0 | CV24: =+DATOS_[[#This Row],[TOTAL SALARIO Eq]]+DATOS_[[#This Row],[Tot Extrasalarial Eq]] -> 0 | CW24: =DATOS_[[#This Row],[S.BASE]] -> 0 | CX24: =+SUM(DATOS_[[#This Row],[Conc.Sal.01]:[Conc.Sal.30]]) -> 0 | CY24: =+DATOS_[[#This Row],[SALARIO BASE Ef]]+DATOS_[[#This Row],[Tot COMPL.SAL Ef]] -> 0 | CZ24: =+SUM(DATOS_[[#This Row],[C.Extra.01]:[C.Extra.11]]) -> 0 | DA24: =+DATOS_[[#This Row],[TOTAL SALARIO Ef]]+DATOS_[[#This Row],[Tot Extrasalarial Ef]] -> 0 | DB24: =MIN(IF(DATOS_[[#This Row],[Fecha Fin Contrato]]="",$D$4,DATOS_[[#This Row],[Fecha Fin Contrato]]),$D$4)-MAX(DATOS_[[#This Row],[Fecha de Contratación]],$D$3)+1 -> 366 | DC24: =IF(COUNTIFS(DATOS_[id/cod],DATOS_[[#This Row],[id/cod]])>1,DATOS_[[#This Row],[id/cod]],"") | DD24: =(Inicio!$G$10-DATOS_[[#This Row],[Fecha Nacimiento]])/365.25 -> 60.334018 | DE24: =(Inicio!$G$10-DATOS_[[#This Row],[Fecha de Antigüedad]])/365.25 -> 23.249829 | DF24: =+VLOOKUP(DATOS_[[#This Row],[Clave de Contrato]],TblTiposContrato13[],3,FALSE) -> #N/A | DG24: =+VLOOKUP(DATOS_[[#This Row],[Clave de Contrato]],TblTiposContrato13[],4,FALSE) -> #N/A | DH24: =VLOOKUP(DATOS_[[#This Row],[Edad]],CONTRATOS!TblRngEdad,2,TRUE) -> 60 en adelante | DI24: =VLOOKUP(DATOS_[[#This Row],[Antigüedad]],TblRngAntg14[],2,TRUE) -> más de 15
A25: FRANCISCO JOSE LOPEZ GONZALEZ | B25: 17 | C25: HOMBRE | D25: 23031 | E25: GRADUADO ESCOLAR | H25: 37462 | J25: 37462 | M25: 1 | Q25: CONDUCTORES | R25: CONDUCTORES | S25: CONDUCTOR | T25: CONTINUO | U25: SI | Y25: 14000425011981 | AA25: PERSONAL OPERARIO GENERAL | AC25: 8 | CH25: =+MAX($D$3,DATOS_[[#This Row],[Fecha Inicio Sit. Contract.]]) -> 45292 | CI25: =+MIN($D$4,DATOS_[[#This Row],[Fecha Fin Sit. Contract.]]) -> 45657 | CJ25: =+DATOS_[[#This Row],[% de jornada]]*IF(DATOS_[[#This Row],[% jornada reducida]]="",1,DATOS_[[#This Row],[% jornada reducida]]) -> 1 | CK25: =+(DATOS_[[#This Row],[F.fin.cal]]-DATOS_[[#This Row],[F.ini.cal]]+1)/($D$4-$D$3+1) -> 1 | CL25: =IF(OR(AND(DATOS_[[#This Row],[Fecha Fin Contrato]]<$D$3,DATOS_[[#This Row],[Fecha Fin Contrato]]<>""),DATOS_[[#This Row],[Fecha de Contratación]]>$D$4),"Fuera","Dentro") -> Dentro | CM25: {=IF(MAX(IF(DATOS_[id/cod]=DATOS_[[#This Row],[id/cod]],DATOS_[F.fin.cal]))=DATOS_[[#This Row],[F.fin.cal]],"Sí","NO")} -> Sí | CN25: =IF(AND(DATOS_[[#This Row],[% normaliz]]<>1,DATOS_[[#This Row],[% anualiz]]=1),"Sí","NO") -> NO | CO25: =IF(AND(DATOS_[[#This Row],[% normaliz]]=1,DATOS_[[#This Row],[% anualiz]]<>1),"Sí","NO") -> NO | CP25: =IF(AND(DATOS_[[#This Row],[% normaliz]]<>1,DATOS_[[#This Row],[% anualiz]]<>1),"Sí","NO") -> NO | CQ25: =+IF(DATOS_[[#This Row],[% normaliz]]*DATOS_[[#This Row],[% anualiz]]=1,"NO","Sí") -> NO | CR25: =(DATOS_[[#This Row],[S.BASE]]*(1/DATOS_[[#This Row],[% normaliz]])*(1/DATOS_[[#This Row],[% anualiz]]))*IF(DATOS_[[#This Row],[Check Equiparado]]="Sí",1,0) -> 0 | CS25: =(SUMPRODUCT((RngTipo=$CS$7)*(rngAnualizable="Sí")*(rngNormalizable="Sí")*(DATOS_[[#This Row],[Conc.Sal.01]:[C.Extra.11]]))*(1/DATOS_[[#This Row],[% anualiz]])*(1/DATOS_[[#This Row],[% normaliz]]) +SUMPRODUCT((RngTipo=$CS$7)*(rngAnualizable="Sí")*(rngNormalizable="No")*(DATOS_[[#This Row],[Conc.Sal.01]:[C.Extra.11]]))*(1/DATOS_[[#This Row],[% anualiz]]) +SUMPRODUCT((RngTipo=$CS$7)*(rngAnualizable="No")*(rngNormalizable="Sí")*(DATOS_[[#This Row],[Conc.Sal.01]:[C.Extra.11]]))*(1/DATOS_[[#This Row],[% normaliz]]) +SUMPRODUCT((RngTipo=$CS$7)*(rngAnualizable="No")*(rngNormalizable="No")*(DATOS_[[#This Row],[Conc.Sal.01]:[C.Extra.11]]))) *IF(DATOS_[[#This Row],[Check Equiparado]]="Sí",1,0) -> 0 | CT25: =+DATOS_[[#This Row],[SALARIO BASE Eq]]+DATOS_[[#This Row],[Tot COMPL.SAL Eq]] -> 0 | CU25: {=(SUMPRODUCT((RngTipo=$CU$7)*(rngAnualizable="Sí")*(rngNormalizable="Sí")*(DATOS_[[#This Row],[Conc.Sal.01]:[C.Extra.11]]))*(1/DATOS_[[#This Row],[% anualiz]])*(1/DATOS_[[#This Row],[% normaliz]]) +SUMPRODUCT((RngTipo=$CU$7)*(rngAnualizable="Sí")*(rngNormalizable="No")*(DATOS_[[#This Row],[Conc.Sal.01]:[C.Extra.11]]))*(1/DATOS_[[#This Row],[% anualiz]]) +SUMPRODUCT((RngTipo=$CU$7)*(rngAnualizable="No")*(rngNormalizable="Sí")*(DATOS_[[#This Row],[Conc.Sal.01]:[C.Extra.11]]))*(1/DATOS_[[#This Row],[% normaliz]]) +SUMPRODUCT((RngTipo=$CU$7)*(rngAnualizable="No")*(rngNormalizable="No")*(DATOS_[[#This Row],[Conc.Sal.01]:[C.Extra.11]]))) *IF(DATOS_[[#This Row],[Check Equiparado]]="Sí",1,0)} -> 0 | CV25: =+DATOS_[[#This Row],[TOTAL SALARIO Eq]]+DATOS_[[#This Row],[Tot Extrasalarial Eq]] -> 0 | CW25: =DATOS_[[#This Row],[S.BASE]] -> 0 | CX25: =+SUM(DATOS_[[#This Row],[Conc.Sal.01]:[Conc.Sal.30]]) -> 0 | CY25: =+DATOS_[[#This Row],[SALARIO BASE Ef]]+DATOS_[[#This Row],[Tot COMPL.SAL Ef]] -> 0 | CZ25: =+SUM(DATOS_[[#This Row],[C.Extra.01]:[C.Extra.11]]) -> 0 | DA25: =+DATOS_[[#This Row],[TOTAL SALARIO Ef]]+DATOS_[[#This Row],[Tot Extrasalarial Ef]] -> 0 | DB25: =MIN(IF(DATOS_[[#This Row],[Fecha Fin Contrato]]="",$D$4,DATOS_[[#This Row],[Fecha Fin Contrato]]),$D$4)-MAX(DATOS_[[#This Row],[Fecha de Contratación]],$D$3)+1 -> 366 | DC25: =IF(COUNTIFS(DATOS_[id/cod],DATOS_[[#This Row],[id/cod]])>1,DATOS_[[#This Row],[id/cod]],"") | DD25: =(Inicio!$G$10-DATOS_[[#This Row],[Fecha Nacimiento]])/365.25 -> 61.946612 | DE25: =(Inicio!$G$10-DATOS_[[#This Row],[Fecha de Antigüedad]])/365.25 -> 22.436687 | DF25: =+VLOOKUP(DATOS_[[#This Row],[Clave de Contrato]],TblTiposContrato13[],3,FALSE) -> #N/A | DG25: =+VLOOKUP(DATOS_[[#This Row],[Clave de Contrato]],TblTiposContrato13[],4,FALSE) -> #N/A | DH25: =VLOOKUP(DATOS_[[#This Row],[Edad]],CONTRATOS!TblRngEdad,2,TRUE) -> 60 en adelante | DI25: =VLOOKUP(DATOS_[[#This Row],[Antigüedad]],TblRngAntg14[],2,TRUE) -> más de 15
A26: JUAN JOSE JURADO POLO | B26: 18 | C26: Hombre | D26: 29521 | E26: FPI | H26: 45644 | J26: 37573 | M26: 1 | P26: 100 | Q26: ADMINISTRACIÓN | R26: ADMINISTRACIÓN | S26: RELACIONES PUBLICAS | T26: CONTINUO | U26: NO | Y26: 14000425011981 | AA26: PERSONAL ADMINISTRATIVO | AC26: 5 | CH26: =+MAX($D$3,DATOS_[[#This Row],[Fecha Inicio Sit. Contract.]]) -> 45292 | CI26: =+MIN($D$4,DATOS_[[#This Row],[Fecha Fin Sit. Contract.]]) -> 45657 | CJ26: =+DATOS_[[#This Row],[% de jornada]]*IF(DATOS_[[#This Row],[% jornada reducida]]="",1,DATOS_[[#This Row],[% jornada reducida]]) -> 1 | CK26: =+(DATOS_[[#This Row],[F.fin.cal]]-DATOS_[[#This Row],[F.ini.cal]]+1)/($D$4-$D$3+1) -> 1 | CL26: =IF(OR(AND(DATOS_[[#This Row],[Fecha Fin Contrato]]<$D$3,DATOS_[[#This Row],[Fecha Fin Contrato]]<>""),DATOS_[[#This Row],[Fecha de Contratación]]>$D$4),"Fuera","Dentro") -> Dentro | CM26: {=IF(MAX(IF(DATOS_[id/cod]=DATOS_[[#This Row],[id/cod]],DATOS_[F.fin.cal]))=DATOS_[[#This Row],[F.fin.cal]],"Sí","NO")} -> Sí | CN26: =IF(AND(DATOS_[[#This Row],[% normaliz]]<>1,DATOS_[[#This Row],[% anualiz]]=1),"Sí","NO") -> NO | CO26: =IF(AND(DATOS_[[#This Row],[% normaliz]]=1,DATOS_[[#This Row],[% anualiz]]<>1),"Sí","NO") -> NO | CP26: =IF(AND(DATOS_[[#This Row],[% normaliz]]<>1,DATOS_[[#This Row],[% anualiz]]<>1),"Sí","NO") -> NO | CQ26: =+IF(DATOS_[[#This Row],[% normaliz]]*DATOS_[[#This Row],[% anualiz]]=1,"NO","Sí") -> NO | CR26: =(DATOS_[[#This Row],[S.BASE]]*(1/DATOS_[[#This Row],[% normaliz]])*(1/DATOS_[[#This Row],[% anualiz]]))*IF(DATOS_[[#This Row],[Check Equiparado]]="Sí",1,0) -> 0 | CS26: =(SUMPRODUCT((RngTipo=$CS$7)*(rngAnualizable="Sí")*(rngNormalizable="Sí")*(DATOS_[[#This Row],[Conc.Sal.01]:[C.Extra.11]]))*(1/DATOS_[[#This Row],[% anualiz]])*(1/DATOS_[[#This Row],[% normaliz]]) +SUMPRODUCT((RngTipo=$CS$7)*(rngAnualizable="Sí")*(rngNormalizable="No")*(DATOS_[[#This Row],[Conc.Sal.01]:[C.Extra.11]]))*(1/DATOS_[[#This Row],[% anualiz]]) +SUMPRODUCT((RngTipo=$CS$7)*(rngAnualizable="No")*(rngNormalizable="Sí")*(DATOS_[[#This Row],[Conc.Sal.01]:[C.Extra.11]]))*(1/DATOS_[[#This Row],[% normaliz]]) +SUMPRODUCT((RngTipo=$CS$7)*(rngAnualizable="No")*(rngNormalizable="No")*(DATOS_[[#This Row],[Conc.Sal.01]:[C.Extra.11]]))) *IF(DATOS_[[#This Row],[Check Equiparado]]="Sí",1,0) -> 0 | CT26: =+DATOS_[[#This Row],[SALARIO BASE Eq]]+DATOS_[[#This Row],[Tot COMPL.SAL Eq]] -> 0 | CU26: {=(SUMPRODUCT((RngTipo=$CU$7)*(rngAnualizable="Sí")*(rngNormalizable="Sí")*(DATOS_[[#This Row],[Conc.Sal.01]:[C.Extra.11]]))*(1/DATOS_[[#This Row],[% anualiz]])*(1/DATOS_[[#This Row],[% normaliz]]) +SUMPRODUCT((RngTipo=$CU$7)*(rngAnualizable="Sí")*(rngNormalizable="No")*(DATOS_[[#This Row],[Conc.Sal.01]:[C.Extra.11]]))*(1/DATOS_[[#This Row],[% anualiz]]) +SUMPRODUCT((RngTipo=$CU$7)*(rngAnualizable="No")*(rngNormalizable="Sí")*(DATOS_[[#This Row],[Conc.Sal.01]:[C.Extra.11]]))*(1/DATOS_[[#This Row],[% normaliz]]) +SUMPRODUCT((RngTipo=$CU$7)*(rngAnualizable="No")*(rngNormalizable="No")*(DATOS_[[#This Row],[Conc.Sal.01]:[C.Extra.11]]))) *IF(DATOS_[[#This Row],[Check Equiparado]]="Sí",1,0)} -> 0 | CV26: =+DATOS_[[#This Row],[TOTAL SALARIO Eq]]+DATOS_[[#This Row],[Tot Extrasalarial Eq]] -> 0 | CW26: =DATOS_[[#This Row],[S.BASE]] -> 0 | CX26: =+SUM(DATOS_[[#This Row],[Conc.Sal.01]:[Conc.Sal.30]]) -> 0 | CY26: =+DATOS_[[#This Row],[SALARIO BASE Ef]]+DATOS_[[#This Row],[Tot COMPL.SAL Ef]] -> 0 | CZ26: =+SUM(DATOS_[[#This Row],[C.Extra.01]:[C.Extra.11]]) -> 0 | DA26: =+DATOS_[[#This Row],[TOTAL SALARIO Ef]]+DATOS_[[#This Row],[Tot Extrasalarial Ef]] -> 0 | DB26: =MIN(IF(DATOS_[[#This Row],[Fecha Fin Contrato]]="",$D$4,DATOS_[[#This Row],[Fecha Fin Contrato]]),$D$4)-MAX(DATOS_[[#This Row],[Fecha de Contratación]],$D$3)+1 -> 14 | DC26: =IF(COUNTIFS(DATOS_[id/cod],DATOS_[[#This Row],[id/cod]])>1,DATOS_[[#This Row],[id/cod]],"") -> 18 | DD26: =(Inicio!$G$10-DATOS_[[#This Row],[Fecha Nacimiento]])/365.25 -> 44.17796 | DE26: =(Inicio!$G$10-DATOS_[[#This Row],[Fecha de Antigüedad]])/365.25 -> 22.132786 | DF26: =+VLOOKUP(DATOS_[[#This Row],[Clave de Contrato]],TblTiposContrato13[],3,FALSE) -> Completa | DG26: =+VLOOKUP(DATOS_[[#This Row],[Clave de Contrato]],TblTiposContrato13[],4,FALSE) -> Indefinido | DH26: =VLOOKUP(DATOS_[[#This Row],[Edad]],CONTRATOS!TblRngEdad,2,TRUE) -> 40 a 45 | DI26: =VLOOKUP(DATOS_[[#This Row],[Antigüedad]],TblRngAntg14[],2,TRUE) -> más de 15
A27: JUAN JOSE JURADO POLO | B27: 18 | C27: Hombre | D27: 29521 | E27: FPI | H27: 39203 | J27: 37573 | M27: 1 | P27: 100 | Q27: ADMINISTRACIÓN | R27: ADMINISTRACIÓN | S27: RELACIONES PUBLICAS | T27: CONTINUO | U27: NO | Y27: 14000425011981 | AA27: PERSONAL ADMINISTRATIVO | AC27: 5 | CH27: =+MAX($D$3,DATOS_[[#This Row],[Fecha Inicio Sit. Contract.]]) -> 45292 | CI27: =+MIN($D$4,DATOS_[[#This Row],[Fecha Fin Sit. Contract.]]) -> 45657 | CJ27: =+DATOS_[[#This Row],[% de jornada]]*IF(DATOS_[[#This Row],[% jornada reducida]]="",1,DATOS_[[#This Row],[% jornada reducida]]) -> 1 | CK27: =+(DATOS_[[#This Row],[F.fin.cal]]-DATOS_[[#This Row],[F.ini.cal]]+1)/($D$4-$D$3+1) -> 1 | CL27: =IF(OR(AND(DATOS_[[#This Row],[Fecha Fin Contrato]]<$D$3,DATOS_[[#This Row],[Fecha Fin Contrato]]<>""),DATOS_[[#This Row],[Fecha de Contratación]]>$D$4),"Fuera","Dentro") -> Dentro | CM27: {=IF(MAX(IF(DATOS_[id/cod]=DATOS_[[#This Row],[id/cod]],DATOS_[F.fin.cal]))=DATOS_[[#This Row],[F.fin.cal]],"Sí","NO")} -> Sí | CN27: =IF(AND(DATOS_[[#This Row],[% normaliz]]<>1,DATOS_[[#This Row],[% anualiz]]=1),"Sí","NO") -> NO | CO27: =IF(AND(DATOS_[[#This Row],[% normaliz]]=1,DATOS_[[#This Row],[% anualiz]]<>1),"Sí","NO") -> NO | CP27: =IF(AND(DATOS_[[#This Row],[% normaliz]]<>1,DATOS_[[#This Row],[% anualiz]]<>1),"Sí","NO") -> NO | CQ27: =+IF(DATOS_[[#This Row],[% normaliz]]*DATOS_[[#This Row],[% anualiz]]=1,"NO","Sí") -> NO | CR27: =(DATOS_[[#This Row],[S.BASE]]*(1/DATOS_[[#This Row],[% normaliz]])*(1/DATOS_[[#This Row],[% anualiz]]))*IF(DATOS_[[#This Row],[Check Equiparado]]="Sí",1,0) -> 0 | CS27: =(SUMPRODUCT((RngTipo=$CS$7)*(rngAnualizable="Sí")*(rngNormalizable="Sí")*(DATOS_[[#This Row],[Conc.Sal.01]:[C.Extra.11]]))*(1/DATOS_[[#This Row],[% anualiz]])*(1/DATOS_[[#This Row],[% normaliz]]) +SUMPRODUCT((RngTipo=$CS$7)*(rngAnualizable="Sí")*(rngNormalizable="No")*(DATOS_[[#This Row],[Conc.Sal.01]:[C.Extra.11]]))*(1/DATOS_[[#This Row],[% anualiz]]) +SUMPRODUCT((RngTipo=$CS$7)*(rngAnualizable="No")*(rngNormalizable="Sí")*(DATOS_[[#This Row],[Conc.Sal.01]:[C.Extra.11]]))*(1/DATOS_[[#This Row],[% normaliz]]) +SUMPRODUCT((RngTipo=$CS$7)*(rngAnualizable="No")*(rngNormalizable="No")*(DATOS_[[#This Row],[Conc.Sal.01]:[C.Extra.11]]))) *IF(DATOS_[[#This Row],[Check Equiparado]]="Sí",1,0) -> 0 | CT27: =+DATOS_[[#This Row],[SALARIO BASE Eq]]+DATOS_[[#This Row],[Tot COMPL.SAL Eq]] -> 0 | CU27: {=(SUMPRODUCT((RngTipo=$CU$7)*(rngAnualizable="Sí")*(rngNormalizable="Sí")*(DATOS_[[#This Row],[Conc.Sal.01]:[C.Extra.11]]))*(1/DATOS_[[#This Row],[% anualiz]])*(1/DATOS_[[#This Row],[% normaliz]]) +SUMPRODUCT((RngTipo=$CU$7)*(rngAnualizable="Sí")*(rngNormalizable="No")*(DATOS_[[#This Row],[Conc.Sal.01]:[C.Extra.11]]))*(1/DATOS_[[#This Row],[% anualiz]]) +SUMPRODUCT((RngTipo=$CU$7)*(rngAnualizable="No")*(rngNormalizable="Sí")*(DATOS_[[#This Row],[Conc.Sal.01]:[C.Extra.11]]))*(1/DATOS_[[#This Row],[% normaliz]]) +SUMPRODUCT((RngTipo=$CU$7)*(rngAnualizable="No")*(rngNormalizable="No")*(DATOS_[[#This Row],[Conc.Sal.01]:[C.Extra.11]]))) *IF(DATOS_[[#This Row],[Check Equiparado]]="Sí",1,0)} -> 0 | CV27: =+DATOS_[[#This Row],[TOTAL SALARIO Eq]]+DATOS_[[#This Row],[Tot Extrasalarial Eq]] -> 0 | CW27: =DATOS_[[#This Row],[S.BASE]] -> 0 | CX27: =+SUM(DATOS_[[#This Row],[Conc.Sal.01]:[Conc.Sal.30]]) -> 0 | CY27: =+DATOS_[[#This Row],[SALARIO BASE Ef]]+DATOS_[[#This Row],[Tot COMPL.SAL Ef]] -> 0 | CZ27: =+SUM(DATOS_[[#This Row],[C.Extra.01]:[C.Extra.11]]) -> 0 | DA27: =+DATOS_[[#This Row],[TOTAL SALARIO Ef]]+DATOS_[[#This Row],[Tot Extrasalarial Ef]] -> 0 | DB27: =MIN(IF(DATOS_[[#This Row],[Fecha Fin Contrato]]="",$D$4,DATOS_[[#This Row],[Fecha Fin Contrato]]),$D$4)-MAX(DATOS_[[#This Row],[Fecha de Contratación]],$D$3)+1 -> 366 | DC27: =IF(COUNTIFS(DATOS_[id/cod],DATOS_[[#This Row],[id/cod]])>1,DATOS_[[#This Row],[id/cod]],"") -> 18 | DD27: =(Inicio!$G$10-DATOS_[[#This Row],[Fecha Nacimiento]])/365.25 -> 44.17796 | DE27: =(Inicio!$G$10-DATOS_[[#This Row],[Fecha de Antigüedad]])/365.25 -> 22.132786 | DF27: =+VLOOKUP(DATOS_[[#This Row],[Clave de Contrato]],TblTiposContrato13[],3,FALSE) -> Completa | DG27: =+VLOOKUP(DATOS_[[#This Row],[Clave de Contrato]],TblTiposContrato13[],4,FALSE) -> Indefinido | DH27: =VLOOKUP(DATOS_[[#This Row],[Edad]],CONTRATOS!TblRngEdad,2,TRUE) -> 40 a 45 | DI27: =VLOOKUP(DATOS_[[#This Row],[Antigüedad]],TblRngAntg14[],2,TRUE) -> más de 15
A28: JUAN JOSE JURADO POLO | B28: 18 | C28: Hombre | D28: 29521 | E28: FPI | H28: 45587 | J28: 37573 | M28: 1 | P28: 100 | Q28: ADMINISTRACIÓN | R28: ADMINISTRACIÓN | S28: RELACIONES PUBLICAS | T28: CONTINUO | U28: NO | Y28: 14000425011981 | AA28: PERSONAL ADMINISTRATIVO | AC28: 5 | CH28: =+MAX($D$3,DATOS_[[#This Row],[Fecha Inicio Sit. Contract.]]) -> 45292 | CI28: =+MIN($D$4,DATOS_[[#This Row],[Fecha Fin Sit. Contract.]]) -> 45657 | CJ28: =+DATOS_[[#This Row],[% de jornada]]*IF(DATOS_[[#This Row],[% jornada reducida]]="",1,DATOS_[[#This Row],[% jornada reducida]]) -> 1 | CK28: =+(DATOS_[[#This Row],[F.fin.cal]]-DATOS_[[#This Row],[F.ini.cal]]+1)/($D$4-$D$3+1) -> 1 | CL28: =IF(OR(AND(DATOS_[[#This Row],[Fecha Fin Contrato]]<$D$3,DATOS_[[#This Row],[Fecha Fin Contrato]]<>""),DATOS_[[#This Row],[Fecha de Contratación]]>$D$4),"Fuera","Dentro") -> Dentro | CM28: {=IF(MAX(IF(DATOS_[id/cod]=DATOS_[[#This Row],[id/cod]],DATOS_[F.fin.cal]))=DATOS_[[#This Row],[F.fin.cal]],"Sí","NO")} -> Sí | CN28: =IF(AND(DATOS_[[#This Row],[% normaliz]]<>1,DATOS_[[#This Row],[% anualiz]]=1),"Sí","NO") -> NO | CO28: =IF(AND(DATOS_[[#This Row],[% normaliz]]=1,DATOS_[[#This Row],[% anualiz]]<>1),"Sí","NO") -> NO | CP28: =IF(AND(DATOS_[[#This Row],[% normaliz]]<>1,DATOS_[[#This Row],[% anualiz]]<>1),"Sí","NO") -> NO | CQ28: =+IF(DATOS_[[#This Row],[% normaliz]]*DATOS_[[#This Row],[% anualiz]]=1,"NO","Sí") -> NO | CR28: =(DATOS_[[#This Row],[S.BASE]]*(1/DATOS_[[#This Row],[% normaliz]])*(1/DATOS_[[#This Row],[% anualiz]]))*IF(DATOS_[[#This Row],[Check Equiparado]]="Sí",1,0) -> 0 | CS28: =(SUMPRODUCT((RngTipo=$CS$7)*(rngAnualizable="Sí")*(rngNormalizable="Sí")*(DATOS_[[#This Row],[Conc.Sal.01]:[C.Extra.11]]))*(1/DATOS_[[#This Row],[% anualiz]])*(1/DATOS_[[#This Row],[% normaliz]]) +SUMPRODUCT((RngTipo=$CS$7)*(rngAnualizable="Sí")*(rngNormalizable="No")*(DATOS_[[#This Row],[Conc.Sal.01]:[C.Extra.11]]))*(1/DATOS_[[#This Row],[% anualiz]]) +SUMPRODUCT((RngTipo=$CS$7)*(rngAnualizable="No")*(rngNormalizable="Sí")*(DATOS_[[#This Row],[Conc.Sal.01]:[C.Extra.11]]))*(1/DATOS_[[#This Row],[% normaliz]]) +SUMPRODUCT((RngTipo=$CS$7)*(rngAnualizable="No")*(rngNormalizable="No")*(DATOS_[[#This Row],[Conc.Sal.01]:[C.Extra.11]]))) *IF(DATOS_[[#This Row],[Check Equiparado]]="Sí",1,0) -> 0 | CT28: =+DATOS_[[#This Row],[SALARIO BASE Eq]]+DATOS_[[#This Row],[Tot COMPL.SAL Eq]] -> 0 | CU28: {=(SUMPRODUCT((RngTipo=$CU$7)*(rngAnualizable="Sí")*(rngNormalizable="Sí")*(DATOS_[[#This Row],[Conc.Sal.01]:[C.Extra.11]]))*(1/DATOS_[[#This Row],[% anualiz]])*(1/DATOS_[[#This Row],[% normaliz]]) +SUMPRODUCT((RngTipo=$CU$7)*(rngAnualizable="Sí")*(rngNormalizable="No")*(DATOS_[[#This Row],[Conc.Sal.01]:[C.Extra.11]]))*(1/DATOS_[[#This Row],[% anualiz]]) +SUMPRODUCT((RngTipo=$CU$7)*(rngAnualizable="No")*(rngNormalizable="Sí")*(DATOS_[[#This Row],[Conc.Sal.01]:[C.Extra.11]]))*(1/DATOS_[[#This Row],[% normaliz]]) +SUMPRODUCT((RngTipo=$CU$7)*(rngAnualizable="No")*(rngNormalizable="No")*(DATOS_[[#This Row],[Conc.Sal.01]:[C.Extra.11]]))) *IF(DATOS_[[#This Row],[Check Equiparado]]="Sí",1,0)} -> 0 | CV28: =+DATOS_[[#This Row],[TOTAL SALARIO Eq]]+DATOS_[[#This Row],[Tot Extrasalarial Eq]] -> 0 | CW28: =DATOS_[[#This Row],[S.BASE]] -> 0 | CX28: =+SUM(DATOS_[[#This Row],[Conc.Sal.01]:[Conc.Sal.30]]) -> 0 | CY28: =+DATOS_[[#This Row],[SALARIO BASE Ef]]+DATOS_[[#This Row],[Tot COMPL.SAL Ef]] -> 0 | CZ28: =+SUM(DATOS_[[#This Row],[C.Extra.01]:[C.Extra.11]]) -> 0 | DA28: =+DATOS_[[#This Row],[TOTAL SALARIO Ef]]+DATOS_[[#This Row],[Tot Extrasalarial Ef]] -> 0 | DB28: =MIN(IF(DATOS_[[#This Row],[Fecha Fin Contrato]]="",$D$4,DATOS_[[#This Row],[Fecha Fin Contrato]]),$D$4)-MAX(DATOS_[[#This Row],[Fecha de Contratación]],$D$3)+1 -> 71 | DC28: =IF(COUNTIFS(DATOS_[id/cod],DATOS_[[#This Row],[id/cod]])>1,DATOS_[[#This Row],[id/cod]],"") -> 18 | DD28: =(Inicio!$G$10-DATOS_[[#This Row],[Fecha Nacimiento]])/365.25 -> 44.17796 | DE28: =(Inicio!$G$10-DATOS_[[#This Row],[Fecha de Antigüedad]])/365.25 -> 22.132786 | DF28: =+VLOOKUP(DATOS_[[#This Row],[Clave de Contrato]],TblTiposContrato13[],3,FALSE) -> Completa | DG28: =+VLOOKUP(DATOS_[[#This Row],[Clave de Contrato]],TblTiposContrato13[],4,FALSE) -> Indefinido | DH28: =VLOOKUP(DATOS_[[#This Row],[Edad]],CONTRATOS!TblRngEdad,2,TRUE) -> 40 a 45 | DI28: =VLOOKUP(DATOS_[[#This Row],[Antigüedad]],TblRngAntg14[],2,TRUE) -> más de 15
A29: ROSARIO FERNANDEZ SANZ | B29: 19 | C29: HOMBRE | D29: 27489 | E29: BACHILLER | H29: 37679 | J29: 37679 | M29: 1 | P29: 189 | Q29: CONDUCTORES | R29: CONDUCTORES | S29: CONDUCTOR | T29: CONTINUO | U29: SI | W29: GRUPO 02 | Y29: 14000425011981 | Z29: Oficial administrativo/a 2da | AA29: PERSONAL OPERARIO GENERAL | AC29: 5 | AD29: 12879.24 | AE29: 2660 | AF29: 37.44 | AG29: 902.4 | AH29: 713.4 | AI29: 611.7 | AJ29: 720 | AK29: 543.24 | AL29: 843.12 | AM29: 1262.52 | AN29: 65 | AO29: 107.32 | AP29: 3603.65 | CH29: =+MAX($D$3,DATOS_[[#This Row],[Fecha Inicio Sit. Contract.]]) -> 45292 | CI29: =+MIN($D$4,DATOS_[[#This Row],[Fecha Fin Sit. Contract.]]) -> 45657 | CJ29: =+DATOS_[[#This Row],[% de jornada]]*IF(DATOS_[[#This Row],[% jornada reducida]]="",1,DATOS_[[#This Row],[% jornada reducida]]) -> 1 | CK29: =+(DATOS_[[#This Row],[F.fin.cal]]-DATOS_[[#This Row],[F.ini.cal]]+1)/($D$4-$D$3+1) -> 1 | CL29: =IF(OR(AND(DATOS_[[#This Row],[Fecha Fin Contrato]]<$D$3,DATOS_[[#This Row],[Fecha Fin Contrato]]<>""),DATOS_[[#This Row],[Fecha de Contratación]]>$D$4),"Fuera","Dentro") -> Dentro | CM29: {=IF(MAX(IF(DATOS_[id/cod]=DATOS_[[#This Row],[id/cod]],DATOS_[F.fin.cal]))=DATOS_[[#This Row],[F.fin.cal]],"Sí","NO")} -> Sí | CN29: =IF(AND(DATOS_[[#This Row],[% normaliz]]<>1,DATOS_[[#This Row],[% anualiz]]=1),"Sí","NO") -> NO | CO29: =IF(AND(DATOS_[[#This Row],[% normaliz]]=1,DATOS_[[#This Row],[% anualiz]]<>1),"Sí","NO") -> NO | CP29: =IF(AND(DATOS_[[#This Row],[% normaliz]]<>1,DATOS_[[#This Row],[% anualiz]]<>1),"Sí","NO") -> NO | CQ29: =+IF(DATOS_[[#This Row],[% normaliz]]*DATOS_[[#This Row],[% anualiz]]=1,"NO","Sí") -> NO | CR29: =(DATOS_[[#This Row],[S.BASE]]*(1/DATOS_[[#This Row],[% normaliz]])*(1/DATOS_[[#This Row],[% anualiz]]))*IF(DATOS_[[#This Row],[Check Equiparado]]="Sí",1,0) -> 12879.24 | CS29: =(SUMPRODUCT((RngTipo=$CS$7)*(rngAnualizable="Sí")*(rngNormalizable="Sí")*(DATOS_[[#This Row],[Conc.Sal.01]:[C.Extra.11]]))*(1/DATOS_[[#This Row],[% anualiz]])*(1/DATOS_[[#This Row],[% normaliz]]) +SUMPRODUCT((RngTipo=$CS$7)*(rngAnualizable="Sí")*(rngNormalizable="No")*(DATOS_[[#This Row],[Conc.Sal.01]:[C.Extra.11]]))*(1/DATOS_[[#This Row],[% anualiz]]) +SUMPRODUCT((RngTipo=$CS$7)*(rngAnualizable="No")*(rngNormalizable="Sí")*(DATOS_[[#This Row],[Conc.Sal.01]:[C.Extra.11]]))*(1/DATOS_[[#This Row],[% normaliz]]) +SUMPRODUCT((RngTipo=$CS$7)*(rngAnualizable="No")*(rngNormalizable="No")*(DATOS_[[#This Row],[Conc.Sal.01]:[C.Extra.11]]))) *IF(DATOS_[[#This Row],[Check Equiparado]]="Sí",1,0) -> 12069.79 | CT29: =+DATOS_[[#This Row],[SALARIO BASE Eq]]+DATOS_[[#This Row],[Tot COMPL.SAL Eq]] -> 24949.03 | CU29: {=(SUMPRODUCT((RngTipo=$CU$7)*(rngAnualizable="Sí")*(rngNormalizable="Sí")*(DATOS_[[#This Row],[Conc.Sal.01]:[C.Extra.11]]))*(1/DATOS_[[#This Row],[% anualiz]])*(1/DATOS_[[#This Row],[% normaliz]]) +SUMPRODUCT((RngTipo=$CU$7)*(rngAnualizable="Sí")*(rngNormalizable="No")*(DATOS_[[#This Row],[Conc.Sal.01]:[C.Extra.11]]))*(1/DATOS_[[#This Row],[% anualiz]]) +SUMPRODUCT((RngTipo=$CU$7)*(rngAnualizable="No")*(rngNormalizable="Sí")*(DATOS_[[#This Row],[Conc.Sal.01]:[C.Extra.11]]))*(1/DATOS_[[#This Row],[% normaliz]]) +SUMPRODUCT((RngTipo=$CU$7)*(rngAnualizable="No")*(rngNormalizable="No")*(DATOS_[[#This Row],[Conc.Sal.01]:[C.Extra.11]]))) *IF(DATOS_[[#This Row],[Check Equiparado]]="Sí",1,0)} -> 0 | CV29: =+DATOS_[[#This Row],[TOTAL SALARIO Eq]]+DATOS_[[#This Row],[Tot Extrasalarial Eq]] -> 24949.03 | CW29: =DATOS_[[#This Row],[S.BASE]] -> 12879.24 | CX29: =+SUM(DATOS_[[#This Row],[Conc.Sal.01]:[Conc.Sal.30]]) -> 12069.79 | CY29: =+DATOS_[[#This Row],[SALARIO BASE Ef]]+DATOS_[[#This Row],[Tot COMPL.SAL Ef]] -> 24949.03 | CZ29: =+SUM(DATOS_[[#This Row],[C.Extra.01]:[C.Extra.11]]) -> 0 | DA29: =+DATOS_[[#This Row],[TOTAL SALARIO Ef]]+DATOS_[[#This Row],[Tot Extrasalarial Ef]] -> 24949.03 | DB29: =MIN(IF(DATOS_[[#This Row],[Fecha Fin Contrato]]="",$D$4,DATOS_[[#This Row],[Fecha Fin Contrato]]),$D$4)-MAX(DATOS_[[#This Row],[Fecha de Contratación]],$D$3)+1 -> 366 | DC29: =IF(COUNTIFS(DATOS_[id/cod],DATOS_[[#This Row],[id/cod]])>1,DATOS_[[#This Row],[id/cod]],"") | DD29: =(Inicio!$G$10-DATOS_[[#This Row],[Fecha Nacimiento]])/365.25 -> 49.741273 | DE29: =(Inicio!$G$10-DATOS_[[#This Row],[Fecha de Antigüedad]])/365.25 -> 21.842574 | DF29: =+VLOOKUP(DATOS_[[#This Row],[Clave de Contrato]],TblTiposContrato13[],3,FALSE) -> Completa | DG29: =+VLOOKUP(DATOS_[[#This Row],[Clave de Contrato]],TblTiposContrato13[],4,FALSE) -> Indefinido | DH29: =VLOOKUP(DATOS_[[#This Row],[Edad]],CONTRATOS!TblRngEdad,2,TRUE) -> 45 a 50 | DI29: =VLOOKUP(DATOS_[[#This Row],[Antigüedad]],TblRngAntg14[],2,TRUE) -> más de 15
A30: JUAN JOSE CARTES MOYA | B30: 20 | C30: MUJER | D30: 28802 | E30: FPII | H30: 37776 | J30: 37776 | M30: 1 | Q30: ASESORES | R30: ASESORES | S30: ASESORA | T30: CONTINUO | U30: SI | Y30: 14000425011981 | AA30: PERSONAL ADMINISTRATIVO | AC30: 7 | CH30: =+MAX($D$3,DATOS_[[#This Row],[Fecha Inicio Sit. Contract.]]) -> 45292 | CI30: =+MIN($D$4,DATOS_[[#This Row],[Fecha Fin Sit. Contract.]]) -> 45657 | CJ30: =+DATOS_[[#This Row],[% de jornada]]*IF(DATOS_[[#This Row],[% jornada reducida]]="",1,DATOS_[[#This Row],[% jornada reducida]]) -> 1 | CK30: =+(DATOS_[[#This Row],[F.fin.cal]]-DATOS_[[#This Row],[F.ini.cal]]+1)/($D$4-$D$3+1) -> 1 | CL30: =IF(OR(AND(DATOS_[[#This Row],[Fecha Fin Contrato]]<$D$3,DATOS_[[#This Row],[Fecha Fin Contrato]]<>""),DATOS_[[#This Row],[Fecha de Contratación]]>$D$4),"Fuera","Dentro") -> Dentro | CM30: {=IF(MAX(IF(DATOS_[id/cod]=DATOS_[[#This Row],[id/cod]],DATOS_[F.fin.cal]))=DATOS_[[#This Row],[F.fin.cal]],"Sí","NO")} -> Sí | CN30: =IF(AND(DATOS_[[#This Row],[% normaliz]]<>1,DATOS_[[#This Row],[% anualiz]]=1),"Sí","NO") -> NO | CO30: =IF(AND(DATOS_[[#This Row],[% normaliz]]=1,DATOS_[[#This Row],[% anualiz]]<>1),"Sí","NO") -> NO | CP30: =IF(AND(DATOS_[[#This Row],[% normaliz]]<>1,DATOS_[[#This Row],[% anualiz]]<>1),"Sí","NO") -> NO | CQ30: =+IF(DATOS_[[#This Row],[% normaliz]]*DATOS_[[#This Row],[% anualiz]]=1,"NO","Sí") -> NO | CR30: =(DATOS_[[#This Row],[S.BASE]]*(1/DATOS_[[#This Row],[% normaliz]])*(1/DATOS_[[#This Row],[% anualiz]]))*IF(DATOS_[[#This Row],[Check Equiparado]]="Sí",1,0) -> 0 | CS30: =(SUMPRODUCT((RngTipo=$CS$7)*(rngAnualizable="Sí")*(rngNormalizable="Sí")*(DATOS_[[#This Row],[Conc.Sal.01]:[C.Extra.11]]))*(1/DATOS_[[#This Row],[% anualiz]])*(1/DATOS_[[#This Row],[% normaliz]]) +SUMPRODUCT((RngTipo=$CS$7)*(rngAnualizable="Sí")*(rngNormalizable="No")*(DATOS_[[#This Row],[Conc.Sal.01]:[C.Extra.11]]))*(1/DATOS_[[#This Row],[% anualiz]]) +SUMPRODUCT((RngTipo=$CS$7)*(rngAnualizable="No")*(rngNormalizable="Sí")*(DATOS_[[#This Row],[Conc.Sal.01]:[C.Extra.11]]))*(1/DATOS_[[#This Row],[% normaliz]]) +SUMPRODUCT((RngTipo=$CS$7)*(rngAnualizable="No")*(rngNormalizable="No")*(DATOS_[[#This Row],[Conc.Sal.01]:[C.Extra.11]]))) *IF(DATOS_[[#This Row],[Check Equiparado]]="Sí",1,0) -> 0 | CT30: =+DATOS_[[#This Row],[SALARIO BASE Eq]]+DATOS_[[#This Row],[Tot COMPL.SAL Eq]] -> 0 | CU30: {=(SUMPRODUCT((RngTipo=$CU$7)*(rngAnualizable="Sí")*(rngNormalizable="Sí")*(DATOS_[[#This Row],[Conc.Sal.01]:[C.Extra.11]]))*(1/DATOS_[[#This Row],[% anualiz]])*(1/DATOS_[[#This Row],[% normaliz]]) +SUMPRODUCT((RngTipo=$CU$7)*(rngAnualizable="Sí")*(rngNormalizable="No")*(DATOS_[[#This Row],[Conc.Sal.01]:[C.Extra.11]]))*(1/DATOS_[[#This Row],[% anualiz]]) +SUMPRODUCT((RngTipo=$CU$7)*(rngAnualizable="No")*(rngNormalizable="Sí")*(DATOS_[[#This Row],[Conc.Sal.01]:[C.Extra.11]]))*(1/DATOS_[[#This Row],[% normaliz]]) +SUMPRODUCT((RngTipo=$CU$7)*(rngAnualizable="No")*(rngNormalizable="No")*(DATOS_[[#This Row],[Conc.Sal.01]:[C.Extra.11]]))) *IF(DATOS_[[#This Row],[Check Equiparado]]="Sí",1,0)} -> 0 | CV30: =+DATOS_[[#This Row],[TOTAL SALARIO Eq]]+DATOS_[[#This Row],[Tot Extrasalarial Eq]] -> 0 | CW30: =DATOS_[[#This Row],[S.BASE]] -> 0 | CX30: =+SUM(DATOS_[[#This Row],[Conc.Sal.01]:[Conc.Sal.30]]) -> 0 | CY30: =+DATOS_[[#This Row],[SALARIO BASE Ef]]+DATOS_[[#This Row],[Tot COMPL.SAL Ef]] -> 0 | CZ30: =+SUM(DATOS_[[#This Row],[C.Extra.01]:[C.Extra.11]]) -> 0 | DA30: =+DATOS_[[#This Row],[TOTAL SALARIO Ef]]+DATOS_[[#This Row],[Tot Extrasalarial Ef]] -> 0 | DB30: =MIN(IF(DATOS_[[#This Row],[Fecha Fin Contrato]]="",$D$4,DATOS_[[#This Row],[Fecha Fin Contrato]]),$D$4)-MAX(DATOS_[[#This Row],[Fecha de Contratación]],$D$3)+1 -> 366 | DC30: =IF(COUNTIFS(DATOS_[id/cod],DATOS_[[#This Row],[id/cod]])>1,DATOS_[[#This Row],[id/cod]],"") | DD30: =(Inicio!$G$10-DATOS_[[#This Row],[Fecha Nacimiento]])/365.25 -> 46.146475 | DE30: =(Inicio!$G$10-DATOS_[[#This Row],[Fecha de Antigüedad]])/365.25 -> 21.577002 | DF30: =+VLOOKUP(DATOS_[[#This Row],[Clave de Contrato]],TblTiposContrato13[],3,FALSE) -> #N/A | DG30: =+VLOOKUP(DATOS_[[#This Row],[Clave de Contrato]],TblTiposContrato13[],4,FALSE) -> #N/A | DH30: =VLOOKUP(DATOS_[[#This Row],[Edad]],CONTRATOS!TblRngEdad,2,TRUE) -> 45 a 50 | DI30: =VLOOKUP(DATOS_[[#This Row],[Antigüedad]],TblRngAntg14[],2,TRUE) -> más de 15
A31: Mª CARMEN SANCHEZ GUZMAN | B31: 21 | C31: MUJER | D31: 28440 | E31: GRADUADO ESCOLAR | H31: 37823 | J31: 37823 | M31: 1 | Q31: RECEPCIONISTA | R31: RECEPCION | S31: RECEPCIONISTA | T31: CONTINUO | U31: SI | Y31: 14000425011981 | AA31: PERSONAL OPERARIO GENERAL | AC31: 7 | CH31: =+MAX($D$3,DATOS_[[#This Row],[Fecha Inicio Sit. Contract.]]) -> 45292 | CI31: =+MIN($D$4,DATOS_[[#This Row],[Fecha Fin Sit. Contract.]]) -> 45657 | CJ31: =+DATOS_[[#This Row],[% de jornada]]*IF(DATOS_[[#This Row],[% jornada reducida]]="",1,DATOS_[[#This Row],[% jornada reducida]]) -> 1 | CK31: =+(DATOS_[[#This Row],[F.fin.cal]]-DATOS_[[#This Row],[F.ini.cal]]+1)/($D$4-$D$3+1) -> 1 | CL31: =IF(OR(AND(DATOS_[[#This Row],[Fecha Fin Contrato]]<$D$3,DATOS_[[#This Row],[Fecha Fin Contrato]]<>""),DATOS_[[#This Row],[Fecha de Contratación]]>$D$4),"Fuera","Dentro") -> Dentro | CM31: {=IF(MAX(IF(DATOS_[id/cod]=DATOS_[[#This Row],[id/cod]],DATOS_[F.fin.cal]))=DATOS_[[#This Row],[F.fin.cal]],"Sí","NO")} -> Sí | CN31: =IF(AND(DATOS_[[#This Row],[% normaliz]]<>1,DATOS_[[#This Row],[% anualiz]]=1),"Sí","NO") -> NO | CO31: =IF(AND(DATOS_[[#This Row],[% normaliz]]=1,DATOS_[[#This Row],[% anualiz]]<>1),"Sí","NO") -> NO | CP31: =IF(AND(DATOS_[[#This Row],[% normaliz]]<>1,DATOS_[[#This Row],[% anualiz]]<>1),"Sí","NO") -> NO | CQ31: =+IF(DATOS_[[#This Row],[% normaliz]]*DATOS_[[#This Row],[% anualiz]]=1,"NO","Sí") -> NO | CR31: =(DATOS_[[#This Row],[S.BASE]]*(1/DATOS_[[#This Row],[% normaliz]])*(1/DATOS_[[#This Row],[% anualiz]]))*IF(DATOS_[[#This Row],[Check Equiparado]]="Sí",1,0) -> 0 | CS31: =(SUMPRODUCT((RngTipo=$CS$7)*(rngAnualizable="Sí")*(rngNormalizable="Sí")*(DATOS_[[#This Row],[Conc.Sal.01]:[C.Extra.11]]))*(1/DATOS_[[#This Row],[% anualiz]])*(1/DATOS_[[#This Row],[% normaliz]]) +SUMPRODUCT((RngTipo=$CS$7)*(rngAnualizable="Sí")*(rngNormalizable="No")*(DATOS_[[#This Row],[Conc.Sal.01]:[C.Extra.11]]))*(1/DATOS_[[#This Row],[% anualiz]]) +SUMPRODUCT((RngTipo=$CS$7)*(rngAnualizable="No")*(rngNormalizable="Sí")*(DATOS_[[#This Row],[Conc.Sal.01]:[C.Extra.11]]))*(1/DATOS_[[#This Row],[% normaliz]]) +SUMPRODUCT((RngTipo=$CS$7)*(rngAnualizable="No")*(rngNormalizable="No")*(DATOS_[[#This Row],[Conc.Sal.01]:[C.Extra.11]]))) *IF(DATOS_[[#This Row],[Check Equiparado]]="Sí",1,0) -> 0 | CT31: =+DATOS_[[#This Row],[SALARIO BASE Eq]]+DATOS_[[#This Row],[Tot COMPL.SAL Eq]] -> 0 | CU31: {=(SUMPRODUCT((RngTipo=$CU$7)*(rngAnualizable="Sí")*(rngNormalizable="Sí")*(DATOS_[[#This Row],[Conc.Sal.01]:[C.Extra.11]]))*(1/DATOS_[[#This Row],[% anualiz]])*(1/DATOS_[[#This Row],[% normaliz]]) +SUMPRODUCT((RngTipo=$CU$7)*(rngAnualizable="Sí")*(rngNormalizable="No")*(DATOS_[[#This Row],[Conc.Sal.01]:[C.Extra.11]]))*(1/DATOS_[[#This Row],[% anualiz]]) +SUMPRODUCT((RngTipo=$CU$7)*(rngAnualizable="No")*(rngNormalizable="Sí")*(DATOS_[[#This Row],[Conc.Sal.01]:[C.Extra.11]]))*(1/DATOS_[[#This Row],[% normaliz]]) +SUMPRODUCT((RngTipo=$CU$7)*(rngAnualizable="No")*(rngNormalizable="No")*(DATOS_[[#This Row],[Conc.Sal.01]:[C.Extra.11]]))) *IF(DATOS_[[#This Row],[Check Equiparado]]="Sí",1,0)} -> 0 | CV31: =+DATOS_[[#This Row],[TOTAL SALARIO Eq]]+DATOS_[[#This Row],[Tot Extrasalarial Eq]] -> 0 | CW31: =DATOS_[[#This Row],[S.BASE]] -> 0 | CX31: =+SUM(DATOS_[[#This Row],[Conc.Sal.01]:[Conc.Sal.30]]) -> 0 | CY31: =+DATOS_[[#This Row],[SALARIO BASE Ef]]+DATOS_[[#This Row],[Tot COMPL.SAL Ef]] -> 0 | CZ31: =+SUM(DATOS_[[#This Row],[C.Extra.01]:[C.Extra.11]]) -> 0 | DA31: =+DATOS_[[#This Row],[TOTAL SALARIO Ef]]+DATOS_[[#This Row],[Tot Extrasalarial Ef]] -> 0 | DB31: =MIN(IF(DATOS_[[#This Row],[Fecha Fin Contrato]]="",$D$4,DATOS_[[#This Row],[Fecha Fin Contrato]]),$D$4)-MAX(DATOS_[[#This Row],[Fecha de Contratación]],$D$3)+1 -> 366 | DC31: =IF(COUNTIFS(DATOS_[id/cod],DATOS_[[#This Row],[id/cod]])>1,DATOS_[[#This Row],[id/cod]],"") | DD31: =(Inicio!$G$10-DATOS_[[#This Row],[Fecha Nacimiento]])/365.25 -> 47.137577 | DE31: =(Inicio!$G$10-DATOS_[[#This Row],[Fecha de Antigüedad]])/365.25 -> 21.448323 | DF31: =+VLOOKUP(DATOS_[[#This Row],[Clave de Contrato]],TblTiposContrato13[],3,FALSE) -> #N/A | DG31: =+VLOOKUP(DATOS_[[#This Row],[Clave de Contrato]],TblTiposContrato13[],4,FALSE) -> #N/A | DH31: =VLOOKUP(DATOS_[[#This Row],[Edad]],CONTRATOS!TblRngEdad,2,TRUE) -> 45 a 50 | DI31: =VLOOKUP(DATOS_[[#This Row],[Antigüedad]],TblRngAntg14[],2,TRUE) -> más de 15
A32: Mª ANGELES AGUDO GOMEZ | B32: 22 | C32: MUJER | D32: 28836 | E32: FPI | H32: 37891 | J32: 37891 | M32: 1 | P32: 189 | Q32: PROTOCOLO | R32: PROTOCOLO | S32: MAESTRA DE CEREMONIAS | T32: CONTINUO | U32: SI | W32: GRUPO 04 | Y32: 14000425011981 | Z32: Recepcionista | AA32: PERSONAL OPERARIO GENERAL | AC32: 7 | AD32: 11549.76 | AE32: 160 | AF32: 37.44 | AG32: 1205.4 | AH32: 1673.4 | AI32: 215.7 | AJ32: 1925.36 | AK32: 131.5 | AL32: 348.84 | AM32: 231.22 | AN32: 818.1 | AO32: 843.12 | AP32: 1132.2 | AQ32: 0 | AR32: 0 | AS32: 0 | AT32: 3607.16 | AU32: 0 | AV32: 0 | AW32: 0 | AX32: 300 | AY32: 0 | AZ32: 0 | BA32: 65 | CH32: =+MAX($D$3,DATOS_[[#This Row],[Fecha Inicio Sit. Contract.]]) -> 45292 | CI32: =+MIN($D$4,DATOS_[[#This Row],[Fecha Fin Sit. Contract.]]) -> 45657 | CJ32: =+DATOS_[[#This Row],[% de jornada]]*IF(DATOS_[[#This Row],[% jornada reducida]]="",1,DATOS_[[#This Row],[% jornada reducida]]) -> 1 | CK32: =+(DATOS_[[#This Row],[F.fin.cal]]-DATOS_[[#This Row],[F.ini.cal]]+1)/($D$4-$D$3+1) -> 1 | CL32: =IF(OR(AND(DATOS_[[#This Row],[Fecha Fin Contrato]]<$D$3,DATOS_[[#This Row],[Fecha Fin Contrato]]<>""),DATOS_[[#This Row],[Fecha de Contratación]]>$D$4),"Fuera","Dentro") -> Dentro | CM32: {=IF(MAX(IF(DATOS_[id/cod]=DATOS_[[#This Row],[id/cod]],DATOS_[F.fin.cal]))=DATOS_[[#This Row],[F.fin.cal]],"Sí","NO")} -> Sí | CN32: =IF(AND(DATOS_[[#This Row],[% normaliz]]<>1,DATOS_[[#This Row],[% anualiz]]=1),"Sí","NO") -> NO | CO32: =IF(AND(DATOS_[[#This Row],[% normaliz]]=1,DATOS_[[#This Row],[% anualiz]]<>1),"Sí","NO") -> NO | CP32: =IF(AND(DATOS_[[#This Row],[% normaliz]]<>1,DATOS_[[#This Row],[% anualiz]]<>1),"Sí","NO") -> NO | CQ32: =+IF(DATOS_[[#This Row],[% normaliz]]*DATOS_[[#This Row],[% anualiz]]=1,"NO","Sí") -> NO | CR32: =(DATOS_[[#This Row],[S.BASE]]*(1/DATOS_[[#This Row],[% normaliz]])*(1/DATOS_[[#This Row],[% anualiz]]))*IF(DATOS_[[#This Row],[Check Equiparado]]="Sí",1,0) -> 11549.76 | CS32: =(SUMPRODUCT((RngTipo=$CS$7)*(rngAnualizable="Sí")*(rngNormalizable="Sí")*(DATOS_[[#This Row],[Conc.Sal.01]:[C.Extra.11]]))*(1/DATOS_[[#This Row],[% anualiz]])*(1/DATOS_[[#This Row],[% normaliz]]) +SUMPRODUCT((RngTipo=$CS$7)*(rngAnualizable="Sí")*(rngNormalizable="No")*(DATOS_[[#This Row],[Conc.Sal.01]:[C.Extra.11]]))*(1/DATOS_[[#This Row],[% anualiz]]) +SUMPRODUCT((RngTipo=$CS$7)*(rngAnualizable="No")*(rngNormalizable="Sí")*(DATOS_[[#This Row],[Conc.Sal.01]:[C.Extra.11]]))*(1/DATOS_[[#This Row],[% normaliz]]) +SUMPRODUCT((RngTipo=$CS$7)*(rngAnualizable="No")*(rngNormalizable="No")*(DATOS_[[#This Row],[Conc.Sal.01]:[C.Extra.11]]))) *IF(DATOS_[[#This Row],[Check Equiparado]]="Sí",1,0) -> 9022.28 | CT32: =+DATOS_[[#This Row],[SALARIO BASE Eq]]+DATOS_[[#This Row],[Tot COMPL.SAL Eq]] -> 20572.04 | CU32: {=(SUMPRODUCT((RngTipo=$CU$7)*(rngAnualizable="Sí")*(rngNormalizable="Sí")*(DATOS_[[#This Row],[Conc.Sal.01]:[C.Extra.11]]))*(1/DATOS_[[#This Row],[% anualiz]])*(1/DATOS_[[#This Row],[% normaliz]]) +SUMPRODUCT((RngTipo=$CU$7)*(rngAnualizable="Sí")*(rngNormalizable="No")*(DATOS_[[#This Row],[Conc.Sal.01]:[C.Extra.11]]))*(1/DATOS_[[#This Row],[% anualiz]]) +SUMPRODUCT((RngTipo=$CU$7)*(rngAnualizable="No")*(rngNormalizable="Sí")*(DATOS_[[#This Row],[Conc.Sal.01]:[C.Extra.11]]))*(1/DATOS_[[#This Row],[% normaliz]]) +SUMPRODUCT((RngTipo=$CU$7)*(rngAnualizable="No")*(rngNormalizable="No")*(DATOS_[[#This Row],[Conc.Sal.01]:[C.Extra.11]]))) *IF(DATOS_[[#This Row],[Check Equiparado]]="Sí",1,0)} -> 3607.16 | CV32: =+DATOS_[[#This Row],[TOTAL SALARIO Eq]]+DATOS_[[#This Row],[Tot Extrasalarial Eq]] -> 24179.2 | CW32: =DATOS_[[#This Row],[S.BASE]] -> 11549.76 | CX32: =+SUM(DATOS_[[#This Row],[Conc.Sal.01]:[Conc.Sal.30]]) -> 12694.44 | CY32: =+DATOS_[[#This Row],[SALARIO BASE Ef]]+DATOS_[[#This Row],[Tot COMPL.SAL Ef]] -> 24244.2 | CZ32: =+SUM(DATOS_[[#This Row],[C.Extra.01]:[C.Extra.11]]) -> 0 | DA32: =+DATOS_[[#This Row],[TOTAL SALARIO Ef]]+DATOS_[[#This Row],[Tot Extrasalarial Ef]] -> 24244.2 | DB32: =MIN(IF(DATOS_[[#This Row],[Fecha Fin Contrato]]="",$D$4,DATOS_[[#This Row],[Fecha Fin Contrato]]),$D$4)-MAX(DATOS_[[#This Row],[Fecha de Contratación]],$D$3)+1 -> 366 | DC32: =IF(COUNTIFS(DATOS_[id/cod],DATOS_[[#This Row],[id/cod]])>1,DATOS_[[#This Row],[id/cod]],"") | DD32: =(Inicio!$G$10-DATOS_[[#This Row],[Fecha Nacimiento]])/365.25 -> 46.053388 | DE32: =(Inicio!$G$10-DATOS_[[#This Row],[Fecha de Antigüedad]])/365.25 -> 21.262149 | DF32: =+VLOOKUP(DATOS_[[#This Row],[Clave de Contrato]],TblTiposContrato13[],3,FALSE) -> Completa | DG32: =+VLOOKUP(DATOS_[[#This Row],[Clave de Contrato]],TblTiposContrato13[],4,FALSE) -> Indefinido | DH32: =VLOOKUP(DATOS_[[#This Row],[Edad]],CONTRATOS!TblRngEdad,2,TRUE) -> 45 a 50 | DI32: =VLOOKUP(DATOS_[[#This Row],[Antigüedad]],TblRngAntg14[],2,TRUE) -> más de 15
A33: ANA ADAME ECHEVARRIA | B33: 23 | C33: MUJER | D33: 27060 | E33: FPI | H33: 38021 | J33: 38021 | M33: 1 | P33: 100 | Q33: PROTOCOLO | R33: PROTOCOLO | S33: MAESTRA DE CEREMONIAS | T33: CONTINUO | U33: SI | W33: GRUPO 04 | Y33: 14000425011981 | Z33: Aux. Admministrativo/a | AA33: PERSONAL OPERARIO GENERAL | AC33: 7 | AD33: 12771.91 | AE33: 719 | AF33: 37.15 | AG33: 894.88 | AH33: 1564.26 | AI33: 267.6 | AJ33: 1624.09 | AK33: 720 | AL33: 129.18 | AM33: 836.09 | AN33: 1252 | AO33: 0 | AP33: 0 | AQ33: 450 | AR33: 612 | AS33: 612 | AT33: 0 | AU33: 0 | AV33: 0 | AW33: 65 | AX33: 107.32 | AY33: 3813.1 | CH33: =+MAX($D$3,DATOS_[[#This Row],[Fecha Inicio Sit. Contract.]]) -> 45292 | CI33: =+MIN($D$4,DATOS_[[#This Row],[Fecha Fin Sit. Contract.]]) -> 45657 | CJ33: =+DATOS_[[#This Row],[% de jornada]]*IF(DATOS_[[#This Row],[% jornada reducida]]="",1,DATOS_[[#This Row],[% jornada reducida]]) -> 1 | CK33: =+(DATOS_[[#This Row],[F.fin.cal]]-DATOS_[[#This Row],[F.ini.cal]]+1)/($D$4-$D$3+1) -> 1 | CL33: =IF(OR(AND(DATOS_[[#This Row],[Fecha Fin Contrato]]<$D$3,DATOS_[[#This Row],[Fecha Fin Contrato]]<>""),DATOS_[[#This Row],[Fecha de Contratación]]>$D$4),"Fuera","Dentro") -> Dentro | CM33: {=IF(MAX(IF(DATOS_[id/cod]=DATOS_[[#This Row],[id/cod]],DATOS_[F.fin.cal]))=DATOS_[[#This Row],[F.fin.cal]],"Sí","NO")} -> Sí | CN33: =IF(AND(DATOS_[[#This Row],[% normaliz]]<>1,DATOS_[[#This Row],[% anualiz]]=1),"Sí","NO") -> NO | CO33: =IF(AND(DATOS_[[#This Row],[% normaliz]]=1,DATOS_[[#This Row],[% anualiz]]<>1),"Sí","NO") -> NO | CP33: =IF(AND(DATOS_[[#This Row],[% normaliz]]<>1,DATOS_[[#This Row],[% anualiz]]<>1),"Sí","NO") -> NO | CQ33: =+IF(DATOS_[[#This Row],[% normaliz]]*DATOS_[[#This Row],[% anualiz]]=1,"NO","Sí") -> NO | CR33: =(DATOS_[[#This Row],[S.BASE]]*(1/DATOS_[[#This Row],[% normaliz]])*(1/DATOS_[[#This Row],[% anualiz]]))*IF(DATOS_[[#This Row],[Check Equiparado]]="Sí",1,0) -> 12771.91 | CS33: =(SUMPRODUCT((RngTipo=$CS$7)*(rngAnualizable="Sí")*(rngNormalizable="Sí")*(DATOS_[[#This Row],[Conc.Sal.01]:[C.Extra.11]]))*(1/DATOS_[[#This Row],[% anualiz]])*(1/DATOS_[[#This Row],[% normaliz]]) +SUMPRODUCT((RngTipo=$CS$7)*(rngAnualizable="Sí")*(rngNormalizable="No")*(DATOS_[[#This Row],[Conc.Sal.01]:[C.Extra.11]]))*(1/DATOS_[[#This Row],[% anualiz]]) +SUMPRODUCT((RngTipo=$CS$7)*(rngAnualizable="No")*(rngNormalizable="Sí")*(DATOS_[[#This Row],[Conc.Sal.01]:[C.Extra.11]]))*(1/DATOS_[[#This Row],[% normaliz]]) +SUMPRODUCT((RngTipo=$CS$7)*(rngAnualizable="No")*(rngNormalizable="No")*(DATOS_[[#This Row],[Conc.Sal.01]:[C.Extra.11]]))) *IF(DATOS_[[#This Row],[Check Equiparado]]="Sí",1,0) -> 13091.67 | CT33: =+DATOS_[[#This Row],[SALARIO BASE Eq]]+DATOS_[[#This Row],[Tot COMPL.SAL Eq]] -> 25863.58 | CU33: {=(SUMPRODUCT((RngTipo=$CU$7)*(rngAnualizable="Sí")*(rngNormalizable="Sí")*(DATOS_[[#This Row],[Conc.Sal.01]:[C.Extra.11]]))*(1/DATOS_[[#This Row],[% anualiz]])*(1/DATOS_[[#This Row],[% normaliz]]) +SUMPRODUCT((RngTipo=$CU$7)*(rngAnualizable="Sí")*(rngNormalizable="No")*(DATOS_[[#This Row],[Conc.Sal.01]:[C.Extra.11]]))*(1/DATOS_[[#This Row],[% anualiz]]) +SUMPRODUCT((RngTipo=$CU$7)*(rngAnualizable="No")*(rngNormalizable="Sí")*(DATOS_[[#This Row],[Conc.Sal.01]:[C.Extra.11]]))*(1/DATOS_[[#This Row],[% normaliz]]) +SUMPRODUCT((RngTipo=$CU$7)*(rngAnualizable="No")*(rngNormalizable="No")*(DATOS_[[#This Row],[Conc.Sal.01]:[C.Extra.11]]))) *IF(DATOS_[[#This Row],[Check Equiparado]]="Sí",1,0)} -> 612 | CV33: =+DATOS_[[#This Row],[TOTAL SALARIO Eq]]+DATOS_[[#This Row],[Tot Extrasalarial Eq]] -> 26475.58 | CW33: =DATOS_[[#This Row],[S.BASE]] -> 12771.91 | CX33: =+SUM(DATOS_[[#This Row],[Conc.Sal.01]:[Conc.Sal.30]]) -> 13703.67 | CY33: =+DATOS_[[#This Row],[SALARIO BASE Ef]]+DATOS_[[#This Row],[Tot COMPL.SAL Ef]] -> 26475.58 | CZ33: =+SUM(DATOS_[[#This Row],[C.Extra.01]:[C.Extra.11]]) -> 0 | DA33: =+DATOS_[[#This Row],[TOTAL SALARIO Ef]]+DATOS_[[#This Row],[Tot Extrasalarial Ef]] -> 26475.58 | DB33: =MIN(IF(DATOS_[[#This Row],[Fecha Fin Contrato]]="",$D$4,DATOS_[[#This Row],[Fecha Fin Contrato]]),$D$4)-MAX(DATOS_[[#This Row],[Fecha de Contratación]],$D$3)+1 -> 366 | DC33: =IF(COUNTIFS(DATOS_[id/cod],DATOS_[[#This Row],[id/cod]])>1,DATOS_[[#This Row],[id/cod]],"") | DD33: =(Inicio!$G$10-DATOS_[[#This Row],[Fecha Nacimiento]])/365.25 -> 50.915811 | DE33: =(Inicio!$G$10-DATOS_[[#This Row],[Fecha de Antigüedad]])/365.25 -> 20.906229 | DF33: =+VLOOKUP(DATOS_[[#This Row],[Clave de Contrato]],TblTiposContrato13[],3,FALSE) -> Completa | DG33: =+VLOOKUP(DATOS_[[#This Row],[Clave de Contrato]],TblTiposContrato13[],4,FALSE) -> Indefinido | DH33: =VLOOKUP(DATOS_[[#This Row],[Edad]],CONTRATOS!TblRngEdad,2,TRUE) -> 50 a 55 | DI33: =VLOOKUP(DATOS_[[#This Row],[Antigüedad]],TblRngAntg14[],2,TRUE) -> más de 15
A34: ANA LUCIA PEREZ CAZALLA | B34: 24 | C34: HOMBRE | D34: 23609 | E34: E. G. B | H34: 38247 | J34: 38247 | M34: 1 | P34: 100 | Q34: CONDUCTORES | R34: CONDUCTOR | S34: CONDUCTOR | T34: CONTINUO | U34: SI | W34: GRUPO 04 | Y34: 14000425011981 | Z34: Aux. Admministrativo/a | AA34: PERSONAL OPERARIO GENERAL | AC34: 7 | AD34: 12879.24 | AE34: 658 | AF34: 37.44 | AG34: 902.4 | AH34: 1673.4 | AI34: 178.2 | AJ34: 1676.48 | AK34: 720 | AL34: 137.79 | AM34: 843.12 | AN34: 1132.2 | AO34: 131.5 | AP34: 194.4 | AQ34: 550 | AR34: 0 | AS34: 0 | AT34: 0 | AU34: 0 | AV34: 0 | AW34: 65 | AX34: 107.32 | AY34: 3863.78 | CH34: =+MAX($D$3,DATOS_[[#This Row],[Fecha Inicio Sit. Contract.]]) -> 45292 | CI34: =+MIN($D$4,DATOS_[[#This Row],[Fecha Fin Sit. Contract.]]) -> 45657 | CJ34: =+DATOS_[[#This Row],[% de jornada]]*IF(DATOS_[[#This Row],[% jornada reducida]]="",1,DATOS_[[#This Row],[% jornada reducida]]) -> 1 | CK34: =+(DATOS_[[#This Row],[F.fin.cal]]-DATOS_[[#This Row],[F.ini.cal]]+1)/($D$4-$D$3+1) -> 1 | CL34: =IF(OR(AND(DATOS_[[#This Row],[Fecha Fin Contrato]]<$D$3,DATOS_[[#This Row],[Fecha Fin Contrato]]<>""),DATOS_[[#This Row],[Fecha de Contratación]]>$D$4),"Fuera","Dentro") -> Dentro | CM34: {=IF(MAX(IF(DATOS_[id/cod]=DATOS_[[#This Row],[id/cod]],DATOS_[F.fin.cal]))=DATOS_[[#This Row],[F.fin.cal]],"Sí","NO")} -> Sí | CN34: =IF(AND(DATOS_[[#This Row],[% normaliz]]<>1,DATOS_[[#This Row],[% anualiz]]=1),"Sí","NO") -> NO | CO34: =IF(AND(DATOS_[[#This Row],[% normaliz]]=1,DATOS_[[#This Row],[% anualiz]]<>1),"Sí","NO") -> NO | CP34: =IF(AND(DATOS_[[#This Row],[% normaliz]]<>1,DATOS_[[#This Row],[% anualiz]]<>1),"Sí","NO") -> NO | CQ34: =+IF(DATOS_[[#This Row],[% normaliz]]*DATOS_[[#This Row],[% anualiz]]=1,"NO","Sí") -> NO | CR34: =(DATOS_[[#This Row],[S.BASE]]*(1/DATOS_[[#This Row],[% normaliz]])*(1/DATOS_[[#This Row],[% anualiz]]))*IF(DATOS_[[#This Row],[Check Equiparado]]="Sí",1,0) -> 12879.24 | CS34: =(SUMPRODUCT((RngTipo=$CS$7)*(rngAnualizable="Sí")*(rngNormalizable="Sí")*(DATOS_[[#This Row],[Conc.Sal.01]:[C.Extra.11]]))*(1/DATOS_[[#This Row],[% anualiz]])*(1/DATOS_[[#This Row],[% normaliz]]) +SUMPRODUCT((RngTipo=$CS$7)*(rngAnualizable="Sí")*(rngNormalizable="No")*(DATOS_[[#This Row],[Conc.Sal.01]:[C.Extra.11]]))*(1/DATOS_[[#This Row],[% anualiz]]) +SUMPRODUCT((RngTipo=$CS$7)*(rngAnualizable="No")*(rngNormalizable="Sí")*(DATOS_[[#This Row],[Conc.Sal.01]:[C.Extra.11]]))*(1/DATOS_[[#This Row],[% normaliz]]) +SUMPRODUCT((RngTipo=$CS$7)*(rngAnualizable="No")*(rngNormalizable="No")*(DATOS_[[#This Row],[Conc.Sal.01]:[C.Extra.11]]))) *IF(DATOS_[[#This Row],[Check Equiparado]]="Sí",1,0) -> 12871.03 | CT34: =+DATOS_[[#This Row],[SALARIO BASE Eq]]+DATOS_[[#This Row],[Tot COMPL.SAL Eq]] -> 25750.27 | CU34: {=(SUMPRODUCT((RngTipo=$CU$7)*(rngAnualizable="Sí")*(rngNormalizable="Sí")*(DATOS_[[#This Row],[Conc.Sal.01]:[C.Extra.11]]))*(1/DATOS_[[#This Row],[% anualiz]])*(1/DATOS_[[#This Row],[% normaliz]]) +SUMPRODUCT((RngTipo=$CU$7)*(rngAnualizable="Sí")*(rngNormalizable="No")*(DATOS_[[#This Row],[Conc.Sal.01]:[C.Extra.11]]))*(1/DATOS_[[#This Row],[% anualiz]]) +SUMPRODUCT((RngTipo=$CU$7)*(rngAnualizable="No")*(rngNormalizable="Sí")*(DATOS_[[#This Row],[Conc.Sal.01]:[C.Extra.11]]))*(1/DATOS_[[#This Row],[% normaliz]]) +SUMPRODUCT((RngTipo=$CU$7)*(rngAnualizable="No")*(rngNormalizable="No")*(DATOS_[[#This Row],[Conc.Sal.01]:[C.Extra.11]]))) *IF(DATOS_[[#This Row],[Check Equiparado]]="Sí",1,0)} -> 0 | CV34: =+DATOS_[[#This Row],[TOTAL SALARIO Eq]]+DATOS_[[#This Row],[Tot Extrasalarial Eq]] -> 25750.27 | CW34: =DATOS_[[#This Row],[S.BASE]] -> 12879.24 | CX34: =+SUM(DATOS_[[#This Row],[Conc.Sal.01]:[Conc.Sal.30]]) -> 12871.03 | CY34: =+DATOS_[[#This Row],[SALARIO BASE Ef]]+DATOS_[[#This Row],[Tot COMPL.SAL Ef]] -> 25750.27 | CZ34: =+SUM(DATOS_[[#This Row],[C.Extra.01]:[C.Extra.11]]) -> 0 | DA34: =+DATOS_[[#This Row],[TOTAL SALARIO Ef]]+DATOS_[[#This Row],[Tot Extrasalarial Ef]] -> 25750.27 | DB34: =MIN(IF(DATOS_[[#This Row],[Fecha Fin Contrato]]="",$D$4,DATOS_[[#This Row],[Fecha Fin Contrato]]),$D$4)-MAX(DATOS_[[#This Row],[Fecha de Contratación]],$D$3)+1 -> 366 | DC34: =IF(COUNTIFS(DATOS_[id/cod],DATOS_[[#This Row],[id/cod]])>1,DATOS_[[#This Row],[id/cod]],"") | DD34: =(Inicio!$G$10-DATOS_[[#This Row],[Fecha Nacimiento]])/365.25 -> 60.364134 | DE34: =(Inicio!$G$10-DATOS_[[#This Row],[Fecha de Antigüedad]])/365.25 -> 20.287474 | DF34: =+VLOOKUP(DATOS_[[#This Row],[Clave de Contrato]],TblTiposContrato13[],3,FALSE) -> Completa | DG34: =+VLOOKUP(DATOS_[[#This Row],[Clave de Contrato]],TblTiposContrato13[],4,FALSE) -> Indefinido | DH34: =VLOOKUP(DATOS_[[#This Row],[Edad]],CONTRATOS!TblRngEdad,2,TRUE) -> 60 en adelante | DI34: =VLOOKUP(DATOS_[[#This Row],[Antigüedad]],TblRngAntg14[],2,TRUE) -> más de 15
A35: ANTONIO FERNANDEZ ARROYO | B35: 25 | C35: HOMBRE | D35: 23271 | E35: GRADUADO ESCOLAR | H35: 38672 | J35: 38672 | M35: 1 | P35: 100 | Q35: CONDUCTORES | R35: CONDUCTOR | S35: CONDUCTOR | T35: CONTINUO | U35: SI | Y35: 14000425011981 | AA35: PERSONAL OPERARIO GENERAL | AC35: 7 | CH35: =+MAX($D$3,DATOS_[[#This Row],[Fecha Inicio Sit. Contract.]]) -> 45292 | CI35: =+MIN($D$4,DATOS_[[#This Row],[Fecha Fin Sit. Contract.]]) -> 45657 | CJ35: =+DATOS_[[#This Row],[% de jornada]]*IF(DATOS_[[#This Row],[% jornada reducida]]="",1,DATOS_[[#This Row],[% jornada reducida]]) -> 1 | CK35: =+(DATOS_[[#This Row],[F.fin.cal]]-DATOS_[[#This Row],[F.ini.cal]]+1)/($D$4-$D$3+1) -> 1 | CL35: =IF(OR(AND(DATOS_[[#This Row],[Fecha Fin Contrato]]<$D$3,DATOS_[[#This Row],[Fecha Fin Contrato]]<>""),DATOS_[[#This Row],[Fecha de Contratación]]>$D$4),"Fuera","Dentro") -> Dentro | CM35: {=IF(MAX(IF(DATOS_[id/cod]=DATOS_[[#This Row],[id/cod]],DATOS_[F.fin.cal]))=DATOS_[[#This Row],[F.fin.cal]],"Sí","NO")} -> Sí | CN35: =IF(AND(DATOS_[[#This Row],[% normaliz]]<>1,DATOS_[[#This Row],[% anualiz]]=1),"Sí","NO") -> NO | CO35: =IF(AND(DATOS_[[#This Row],[% normaliz]]=1,DATOS_[[#This Row],[% anualiz]]<>1),"Sí","NO") -> NO | CP35: =IF(AND(DATOS_[[#This Row],[% normaliz]]<>1,DATOS_[[#This Row],[% anualiz]]<>1),"Sí","NO") -> NO | CQ35: =+IF(DATOS_[[#This Row],[% normaliz]]*DATOS_[[#This Row],[% anualiz]]=1,"NO","Sí") -> NO | CR35: =(DATOS_[[#This Row],[S.BASE]]*(1/DATOS_[[#This Row],[% normaliz]])*(1/DATOS_[[#This Row],[% anualiz]]))*IF(DATOS_[[#This Row],[Check Equiparado]]="Sí",1,0) -> 0 | CS35: =(SUMPRODUCT((RngTipo=$CS$7)*(rngAnualizable="Sí")*(rngNormalizable="Sí")*(DATOS_[[#This Row],[Conc.Sal.01]:[C.Extra.11]]))*(1/DATOS_[[#This Row],[% anualiz]])*(1/DATOS_[[#This Row],[% normaliz]]) +SUMPRODUCT((RngTipo=$CS$7)*(rngAnualizable="Sí")*(rngNormalizable="No")*(DATOS_[[#This Row],[Conc.Sal.01]:[C.Extra.11]]))*(1/DATOS_[[#This Row],[% anualiz]]) +SUMPRODUCT((RngTipo=$CS$7)*(rngAnualizable="No")*(rngNormalizable="Sí")*(DATOS_[[#This Row],[Conc.Sal.01]:[C.Extra.11]]))*(1/DATOS_[[#This Row],[% normaliz]]) +SUMPRODUCT((RngTipo=$CS$7)*(rngAnualizable="No")*(rngNormalizable="No")*(DATOS_[[#This Row],[Conc.Sal.01]:[C.Extra.11]]))) *IF(DATOS_[[#This Row],[Check Equiparado]]="Sí",1,0) -> 0 | CT35: =+DATOS_[[#This Row],[SALARIO BASE Eq]]+DATOS_[[#This Row],[Tot COMPL.SAL Eq]] -> 0 | CU35: {=(SUMPRODUCT((RngTipo=$CU$7)*(rngAnualizable="Sí")*(rngNormalizable="Sí")*(DATOS_[[#This Row],[Conc.Sal.01]:[C.Extra.11]]))*(1/DATOS_[[#This Row],[% anualiz]])*(1/DATOS_[[#This Row],[% normaliz]]) +SUMPRODUCT((RngTipo=$CU$7)*(rngAnualizable="Sí")*(rngNormalizable="No")*(DATOS_[[#This Row],[Conc.Sal.01]:[C.Extra.11]]))*(1/DATOS_[[#This Row],[% anualiz]]) +SUMPRODUCT((RngTipo=$CU$7)*(rngAnualizable="No")*(rngNormalizable="Sí")*(DATOS_[[#This Row],[Conc.Sal.01]:[C.Extra.11]]))*(1/DATOS_[[#This Row],[% normaliz]]) +SUMPRODUCT((RngTipo=$CU$7)*(rngAnualizable="No")*(rngNormalizable="No")*(DATOS_[[#This Row],[Conc.Sal.01]:[C.Extra.11]]))) *IF(DATOS_[[#This Row],[Check Equiparado]]="Sí",1,0)} -> 0 | CV35: =+DATOS_[[#This Row],[TOTAL SALARIO Eq]]+DATOS_[[#This Row],[Tot Extrasalarial Eq]] -> 0 | CW35: =DATOS_[[#This Row],[S.BASE]] -> 0 | CX35: =+SUM(DATOS_[[#This Row],[Conc.Sal.01]:[Conc.Sal.30]]) -> 0 | CY35: =+DATOS_[[#This Row],[SALARIO BASE Ef]]+DATOS_[[#This Row],[Tot COMPL.SAL Ef]] -> 0 | CZ35: =+SUM(DATOS_[[#This Row],[C.Extra.01]:[C.Extra.11]]) -> 0 | DA35: =+DATOS_[[#This Row],[TOTAL SALARIO Ef]]+DATOS_[[#This Row],[Tot Extrasalarial Ef]] -> 0 | DB35: =MIN(IF(DATOS_[[#This Row],[Fecha Fin Contrato]]="",$D$4,DATOS_[[#This Row],[Fecha Fin Contrato]]),$D$4)-MAX(DATOS_[[#This Row],[Fecha de Contratación]],$D$3)+1 -> 366 | DC35: =IF(COUNTIFS(DATOS_[id/cod],DATOS_[[#This Row],[id/cod]])>1,DATOS_[[#This Row],[id/cod]],"") | DD35: =(Inicio!$G$10-DATOS_[[#This Row],[Fecha Nacimiento]])/365.25 -> 61.289528 | DE35: =(Inicio!$G$10-DATOS_[[#This Row],[Fecha de Antigüedad]])/365.25 -> 19.123888 | DF35: =+VLOOKUP(DATOS_[[#This Row],[Clave de Contrato]],TblTiposContrato13[],3,FALSE) -> Completa | DG35: =+VLOOKUP(DATOS_[[#This Row],[Clave de Contrato]],TblTiposContrato13[],4,FALSE) -> Indefinido | DH35: =VLOOKUP(DATOS_[[#This Row],[Edad]],CONTRATOS!TblRngEdad,2,TRUE) -> 60 en adelante | DI35: =VLOOKUP(DATOS_[[#This Row],[Antigüedad]],TblRngAntg14[],2,TRUE) -> más de 15
A36: JOSE RODRIGUEZ GONZALEZ | B36: 26 | C36: HOMBRE | D36: 22511 | E36: GRADUADO ESCOLAR | H36: 39428 | J36: 39428 | M36: 1 | P36: 100 | Q36: CONDUCTORES | R36: CONDUCTOR | S36: CONDUCTOR | T36: CONTINUO | U36: SI | Y36: 14000425011981 | AA36: PERSONAL OPERARIO GENERAL | AC36: 7 | CH36: =+MAX($D$3,DATOS_[[#This Row],[Fecha Inicio Sit. Contract.]]) -> 45292 | CI36: =+MIN($D$4,DATOS_[[#This Row],[Fecha Fin Sit. Contract.]]) -> 45657 | CJ36: =+DATOS_[[#This Row],[% de jornada]]*IF(DATOS_[[#This Row],[% jornada reducida]]="",1,DATOS_[[#This Row],[% jornada reducida]]) -> 1 | CK36: =+(DATOS_[[#This Row],[F.fin.cal]]-DATOS_[[#This Row],[F.ini.cal]]+1)/($D$4-$D$3+1) -> 1 | CL36: =IF(OR(AND(DATOS_[[#This Row],[Fecha Fin Contrato]]<$D$3,DATOS_[[#This Row],[Fecha Fin Contrato]]<>""),DATOS_[[#This Row],[Fecha de Contratación]]>$D$4),"Fuera","Dentro") -> Dentro | CM36: {=IF(MAX(IF(DATOS_[id/cod]=DATOS_[[#This Row],[id/cod]],DATOS_[F.fin.cal]))=DATOS_[[#This Row],[F.fin.cal]],"Sí","NO")} -> Sí | CN36: =IF(AND(DATOS_[[#This Row],[% normaliz]]<>1,DATOS_[[#This Row],[% anualiz]]=1),"Sí","NO") -> NO | CO36: =IF(AND(DATOS_[[#This Row],[% normaliz]]=1,DATOS_[[#This Row],[% anualiz]]<>1),"Sí","NO") -> NO | CP36: =IF(AND(DATOS_[[#This Row],[% normaliz]]<>1,DATOS_[[#This Row],[% anualiz]]<>1),"Sí","NO") -> NO | CQ36: =+IF(DATOS_[[#This Row],[% normaliz]]*DATOS_[[#This Row],[% anualiz]]=1,"NO","Sí") -> NO | CR36: =(DATOS_[[#This Row],[S.BASE]]*(1/DATOS_[[#This Row],[% normaliz]])*(1/DATOS_[[#This Row],[% anualiz]]))*IF(DATOS_[[#This Row],[Check Equiparado]]="Sí",1,0) -> 0 | CS36: =(SUMPRODUCT((RngTipo=$CS$7)*(rngAnualizable="Sí")*(rngNormalizable="Sí")*(DATOS_[[#This Row],[Conc.Sal.01]:[C.Extra.11]]))*(1/DATOS_[[#This Row],[% anualiz]])*(1/DATOS_[[#This Row],[% normaliz]]) +SUMPRODUCT((RngTipo=$CS$7)*(rngAnualizable="Sí")*(rngNormalizable="No")*(DATOS_[[#This Row],[Conc.Sal.01]:[C.Extra.11]]))*(1/DATOS_[[#This Row],[% anualiz]]) +SUMPRODUCT((RngTipo=$CS$7)*(rngAnualizable="No")*(rngNormalizable="Sí")*(DATOS_[[#This Row],[Conc.Sal.01]:[C.Extra.11]]))*(1/DATOS_[[#This Row],[% normaliz]]) +SUMPRODUCT((RngTipo=$CS$7)*(rngAnualizable="No")*(rngNormalizable="No")*(DATOS_[[#This Row],[Conc.Sal.01]:[C.Extra.11]]))) *IF(DATOS_[[#This Row],[Check Equiparado]]="Sí",1,0) -> 0 | CT36: =+DATOS_[[#This Row],[SALARIO BASE Eq]]+DATOS_[[#This Row],[Tot COMPL.SAL Eq]] -> 0 | CU36: {=(SUMPRODUCT((RngTipo=$CU$7)*(rngAnualizable="Sí")*(rngNormalizable="Sí")*(DATOS_[[#This Row],[Conc.Sal.01]:[C.Extra.11]]))*(1/DATOS_[[#This Row],[% anualiz]])*(1/DATOS_[[#This Row],[% normaliz]]) +SUMPRODUCT((RngTipo=$CU$7)*(rngAnualizable="Sí")*(rngNormalizable="No")*(DATOS_[[#This Row],[Conc.Sal.01]:[C.Extra.11]]))*(1/DATOS_[[#This Row],[% anualiz]]) +SUMPRODUCT((RngTipo=$CU$7)*(rngAnualizable="No")*(rngNormalizable="Sí")*(DATOS_[[#This Row],[Conc.Sal.01]:[C.Extra.11]]))*(1/DATOS_[[#This Row],[% normaliz]]) +SUMPRODUCT((RngTipo=$CU$7)*(rngAnualizable="No")*(rngNormalizable="No")*(DATOS_[[#This Row],[Conc.Sal.01]:[C.Extra.11]]))) *IF(DATOS_[[#This Row],[Check Equiparado]]="Sí",1,0)} -> 0 | CV36: =+DATOS_[[#This Row],[TOTAL SALARIO Eq]]+DATOS_[[#This Row],[Tot Extrasalarial Eq]] -> 0 | CW36: =DATOS_[[#This Row],[S.BASE]] -> 0 | CX36: =+SUM(DATOS_[[#This Row],[Conc.Sal.01]:[Conc.Sal.30]]) -> 0 | CY36: =+DATOS_[[#This Row],[SALARIO BASE Ef]]+DATOS_[[#This Row],[Tot COMPL.SAL Ef]] -> 0 | CZ36: =+SUM(DATOS_[[#This Row],[C.Extra.01]:[C.Extra.11]]) -> 0 | DA36: =+DATOS_[[#This Row],[TOTAL SALARIO Ef]]+DATOS_[[#This Row],[Tot Extrasalarial Ef]] -> 0 | DB36: =MIN(IF(DATOS_[[#This Row],[Fecha Fin Contrato]]="",$D$4,DATOS_[[#This Row],[Fecha Fin Contrato]]),$D$4)-MAX(DATOS_[[#This Row],[Fecha de Contratación]],$D$3)+1 -> 366 | DC36: =IF(COUNTIFS(DATOS_[id/cod],DATOS_[[#This Row],[id/cod]])>1,DATOS_[[#This Row],[id/cod]],"") | DD36: =(Inicio!$G$10-DATOS_[[#This Row],[Fecha Nacimiento]])/365.25 -> 63.370294 | DE36: =(Inicio!$G$10-DATOS_[[#This Row],[Fecha de Antigüedad]])/365.25 -> 17.054073 | DF36: =+VLOOKUP(DATOS_[[#This Row],[Clave de Contrato]],TblTiposContrato13[],3,FALSE) -> Completa | DG36: =+VLOOKUP(DATOS_[[#This Row],[Clave de Contrato]],TblTiposContrato13[],4,FALSE) -> Indefinido | DH36: =VLOOKUP(DATOS_[[#This Row],[Edad]],CONTRATOS!TblRngEdad,2,TRUE) -> 60 en adelante | DI36: =VLOOKUP(DATOS_[[#This Row],[Antigüedad]],TblRngAntg14[],2,TRUE) -> más de 15
A37: ORESTES MUÑOZ OTS | B37: 27 | C37: HOMBRE | D37: 30237 | E37: FPII | H37: 39496 | J37: 39496 | M37: 1 | P37: 100 | Q37: ASESORES | R37: ASESORES | S37: ASESOR | T37: CONTINUO | U37: SI | Y37: 14000425011981 | AA37: PERSONAL OPERARIO GENERAL | AC37: 7 | CH37: =+MAX($D$3,DATOS_[[#This Row],[Fecha Inicio Sit. Contract.]]) -> 45292 | CI37: =+MIN($D$4,DATOS_[[#This Row],[Fecha Fin Sit. Contract.]]) -> 45657 | CJ37: =+DATOS_[[#This Row],[% de jornada]]*IF(DATOS_[[#This Row],[% jornada reducida]]="",1,DATOS_[[#This Row],[% jornada reducida]]) -> 1 | CK37: =+(DATOS_[[#This Row],[F.fin.cal]]-DATOS_[[#This Row],[F.ini.cal]]+1)/($D$4-$D$3+1) -> 1 | CL37: =IF(OR(AND(DATOS_[[#This Row],[Fecha Fin Contrato]]<$D$3,DATOS_[[#This Row],[Fecha Fin Contrato]]<>""),DATOS_[[#This Row],[Fecha de Contratación]]>$D$4),"Fuera","Dentro") -> Dentro | CM37: {=IF(MAX(IF(DATOS_[id/cod]=DATOS_[[#This Row],[id/cod]],DATOS_[F.fin.cal]))=DATOS_[[#This Row],[F.fin.cal]],"Sí","NO")} -> Sí | CN37: =IF(AND(DATOS_[[#This Row],[% normaliz]]<>1,DATOS_[[#This Row],[% anualiz]]=1),"Sí","NO") -> NO | CO37: =IF(AND(DATOS_[[#This Row],[% normaliz]]=1,DATOS_[[#This Row],[% anualiz]]<>1),"Sí","NO") -> NO | CP37: =IF(AND(DATOS_[[#This Row],[% normaliz]]<>1,DATOS_[[#This Row],[% anualiz]]<>1),"Sí","NO") -> NO | CQ37: =+IF(DATOS_[[#This Row],[% normaliz]]*DATOS_[[#This Row],[% anualiz]]=1,"NO","Sí") -> NO | CR37: =(DATOS_[[#This Row],[S.BASE]]*(1/DATOS_[[#This Row],[% normaliz]])*(1/DATOS_[[#This Row],[% anualiz]]))*IF(DATOS_[[#This Row],[Check Equiparado]]="Sí",1,0) -> 0 | CS37: =(SUMPRODUCT((RngTipo=$CS$7)*(rngAnualizable="Sí")*(rngNormalizable="Sí")*(DATOS_[[#This Row],[Conc.Sal.01]:[C.Extra.11]]))*(1/DATOS_[[#This Row],[% anualiz]])*(1/DATOS_[[#This Row],[% normaliz]]) +SUMPRODUCT((RngTipo=$CS$7)*(rngAnualizable="Sí")*(rngNormalizable="No")*(DATOS_[[#This Row],[Conc.Sal.01]:[C.Extra.11]]))*(1/DATOS_[[#This Row],[% anualiz]]) +SUMPRODUCT((RngTipo=$CS$7)*(rngAnualizable="No")*(rngNormalizable="Sí")*(DATOS_[[#This Row],[Conc.Sal.01]:[C.Extra.11]]))*(1/DATOS_[[#This Row],[% normaliz]]) +SUMPRODUCT((RngTipo=$CS$7)*(rngAnualizable="No")*(rngNormalizable="No")*(DATOS_[[#This Row],[Conc.Sal.01]:[C.Extra.11]]))) *IF(DATOS_[[#This Row],[Check Equiparado]]="Sí",1,0) -> 0 | CT37: =+DATOS_[[#This Row],[SALARIO BASE Eq]]+DATOS_[[#This Row],[Tot COMPL.SAL Eq]] -> 0 | CU37: {=(SUMPRODUCT((RngTipo=$CU$7)*(rngAnualizable="Sí")*(rngNormalizable="Sí")*(DATOS_[[#This Row],[Conc.Sal.01]:[C.Extra.11]]))*(1/DATOS_[[#This Row],[% anualiz]])*(1/DATOS_[[#This Row],[% normaliz]]) +SUMPRODUCT((RngTipo=$CU$7)*(rngAnualizable="Sí")*(rngNormalizable="No")*(DATOS_[[#This Row],[Conc.Sal.01]:[C.Extra.11]]))*(1/DATOS_[[#This Row],[% anualiz]]) +SUMPRODUCT((RngTipo=$CU$7)*(rngAnualizable="No")*(rngNormalizable="Sí")*(DATOS_[[#This Row],[Conc.Sal.01]:[C.Extra.11]]))*(1/DATOS_[[#This Row],[% normaliz]]) +SUMPRODUCT((RngTipo=$CU$7)*(rngAnualizable="No")*(rngNormalizable="No")*(DATOS_[[#This Row],[Conc.Sal.01]:[C.Extra.11]]))) *IF(DATOS_[[#This Row],[Check Equiparado]]="Sí",1,0)} -> 0 | CV37: =+DATOS_[[#This Row],[TOTAL SALARIO Eq]]+DATOS_[[#This Row],[Tot Extrasalarial Eq]] -> 0 | CW37: =DATOS_[[#This Row],[S.BASE]] -> 0 | CX37: =+SUM(DATOS_[[#This Row],[Conc.Sal.01]:[Conc.Sal.30]]) -> 0 | CY37: =+DATOS_[[#This Row],[SALARIO BASE Ef]]+DATOS_[[#This Row],[Tot COMPL.SAL Ef]] -> 0 | CZ37: =+SUM(DATOS_[[#This Row],[C.Extra.01]:[C.Extra.11]]) -> 0 | DA37: =+DATOS_[[#This Row],[TOTAL SALARIO Ef]]+DATOS_[[#This Row],[Tot Extrasalarial Ef]] -> 0 | DB37: =MIN(IF(DATOS_[[#This Row],[Fecha Fin Contrato]]="",$D$4,DATOS_[[#This Row],[Fecha Fin Contrato]]),$D$4)-MAX(DATOS_[[#This Row],[Fecha de Contratación]],$D$3)+1 -> 366 | DC37: =IF(COUNTIFS(DATOS_[id/cod],DATOS_[[#This Row],[id/cod]])>1,DATOS_[[#This Row],[id/cod]],"") | DD37: =(Inicio!$G$10-DATOS_[[#This Row],[Fecha Nacimiento]])/365.25 -> 42.217659 | DE37: =(Inicio!$G$10-DATOS_[[#This Row],[Fecha de Antigüedad]])/365.25 -> 16.867899 | DF37: =+VLOOKUP(DATOS_[[#This Row],[Clave de Contrato]],TblTiposContrato13[],3,FALSE) -> Completa | DG37: =+VLOOKUP(DATOS_[[#This Row],[Clave de Contrato]],TblTiposContrato13[],4,FALSE) -> Indefinido | DH37: =VLOOKUP(DATOS_[[#This Row],[Edad]],CONTRATOS!TblRngEdad,2,TRUE) -> 40 a 45 | DI37: =VLOOKUP(DATOS_[[#This Row],[Antigüedad]],TblRngAntg14[],2,TRUE) -> más de 15
A38: JOSE Mª GARCIA MANZANO | B38: 28 | C38: MUJER | D38: 32442 | E38: GRADO | H38: 39651 | J38: 39651 | M38: 1 | P38: 100 | Q38: ADMINISTRACIÓN | R38: DIRECCIÓN | S38: GERENTE | T38: CONTINUO | U38: NO | Y38: 14000425011981 | AA38: PERSONAL OPERARIO GENERAL | AC38: 7 | CH38: =+MAX($D$3,DATOS_[[#This Row],[Fecha Inicio Sit. Contract.]]) -> 45292 | CI38: =+MIN($D$4,DATOS_[[#This Row],[Fecha Fin Sit. Contract.]]) -> 45657 | CJ38: =+DATOS_[[#This Row],[% de jornada]]*IF(DATOS_[[#This Row],[% jornada reducida]]="",1,DATOS_[[#This Row],[% jornada reducida]]) -> 1 | CK38: =+(DATOS_[[#This Row],[F.fin.cal]]-DATOS_[[#This Row],[F.ini.cal]]+1)/($D$4-$D$3+1) -> 1 | CL38: =IF(OR(AND(DATOS_[[#This Row],[Fecha Fin Contrato]]<$D$3,DATOS_[[#This Row],[Fecha Fin Contrato]]<>""),DATOS_[[#This Row],[Fecha de Contratación]]>$D$4),"Fuera","Dentro") -> Dentro | CM38: {=IF(MAX(IF(DATOS_[id/cod]=DATOS_[[#This Row],[id/cod]],DATOS_[F.fin.cal]))=DATOS_[[#This Row],[F.fin.cal]],"Sí","NO")} -> Sí | CN38: =IF(AND(DATOS_[[#This Row],[% normaliz]]<>1,DATOS_[[#This Row],[% anualiz]]=1),"Sí","NO") -> NO | CO38: =IF(AND(DATOS_[[#This Row],[% normaliz]]=1,DATOS_[[#This Row],[% anualiz]]<>1),"Sí","NO") -> NO | CP38: =IF(AND(DATOS_[[#This Row],[% normaliz]]<>1,DATOS_[[#This Row],[% anualiz]]<>1),"Sí","NO") -> NO | CQ38: =+IF(DATOS_[[#This Row],[% normaliz]]*DATOS_[[#This Row],[% anualiz]]=1,"NO","Sí") -> NO | CR38: =(DATOS_[[#This Row],[S.BASE]]*(1/DATOS_[[#This Row],[% normaliz]])*(1/DATOS_[[#This Row],[% anualiz]]))*IF(DATOS_[[#This Row],[Check Equiparado]]="Sí",1,0) -> 0 | CS38: =(SUMPRODUCT((RngTipo=$CS$7)*(rngAnualizable="Sí")*(rngNormalizable="Sí")*(DATOS_[[#This Row],[Conc.Sal.01]:[C.Extra.11]]))*(1/DATOS_[[#This Row],[% anualiz]])*(1/DATOS_[[#This Row],[% normaliz]]) +SUMPRODUCT((RngTipo=$CS$7)*(rngAnualizable="Sí")*(rngNormalizable="No")*(DATOS_[[#This Row],[Conc.Sal.01]:[C.Extra.11]]))*(1/DATOS_[[#This Row],[% anualiz]]) +SUMPRODUCT((RngTipo=$CS$7)*(rngAnualizable="No")*(rngNormalizable="Sí")*(DATOS_[[#This Row],[Conc.Sal.01]:[C.Extra.11]]))*(1/DATOS_[[#This Row],[% normaliz]]) +SUMPRODUCT((RngTipo=$CS$7)*(rngAnualizable="No")*(rngNormalizable="No")*(DATOS_[[#This Row],[Conc.Sal.01]:[C.Extra.11]]))) *IF(DATOS_[[#This Row],[Check Equiparado]]="Sí",1,0) -> 0 | CT38: =+DATOS_[[#This Row],[SALARIO BASE Eq]]+DATOS_[[#This Row],[Tot COMPL.SAL Eq]] -> 0 | CU38: {=(SUMPRODUCT((RngTipo=$CU$7)*(rngAnualizable="Sí")*(rngNormalizable="Sí")*(DATOS_[[#This Row],[Conc.Sal.01]:[C.Extra.11]]))*(1/DATOS_[[#This Row],[% anualiz]])*(1/DATOS_[[#This Row],[% normaliz]]) +SUMPRODUCT((RngTipo=$CU$7)*(rngAnualizable="Sí")*(rngNormalizable="No")*(DATOS_[[#This Row],[Conc.Sal.01]:[C.Extra.11]]))*(1/DATOS_[[#This Row],[% anualiz]]) +SUMPRODUCT((RngTipo=$CU$7)*(rngAnualizable="No")*(rngNormalizable="Sí")*(DATOS_[[#This Row],[Conc.Sal.01]:[C.Extra.11]]))*(1/DATOS_[[#This Row],[% normaliz]]) +SUMPRODUCT((RngTipo=$CU$7)*(rngAnualizable="No")*(rngNormalizable="No")*(DATOS_[[#This Row],[Conc.Sal.01]:[C.Extra.11]]))) *IF(DATOS_[[#This Row],[Check Equiparado]]="Sí",1,0)} -> 0 | CV38: =+DATOS_[[#This Row],[TOTAL SALARIO Eq]]+DATOS_[[#This Row],[Tot Extrasalarial Eq]] -> 0 | CW38: =DATOS_[[#This Row],[S.BASE]] -> 0 | CX38: =+SUM(DATOS_[[#This Row],[Conc.Sal.01]:[Conc.Sal.30]]) -> 0 | CY38: =+DATOS_[[#This Row],[SALARIO BASE Ef]]+DATOS_[[#This Row],[Tot COMPL.SAL Ef]] -> 0 | CZ38: =+SUM(DATOS_[[#This Row],[C.Extra.01]:[C.Extra.11]]) -> 0 | DA38: =+DATOS_[[#This Row],[TOTAL SALARIO Ef]]+DATOS_[[#This Row],[Tot Extrasalarial Ef]] -> 0 | DB38: =MIN(IF(DATOS_[[#This Row],[Fecha Fin Contrato]]="",$D$4,DATOS_[[#This Row],[Fecha Fin Contrato]]),$D$4)-MAX(DATOS_[[#This Row],[Fecha de Contratación]],$D$3)+1 -> 366 | DC38: =IF(COUNTIFS(DATOS_[id/cod],DATOS_[[#This Row],[id/cod]])>1,DATOS_[[#This Row],[id/cod]],"") | DD38: =(Inicio!$G$10-DATOS_[[#This Row],[Fecha Nacimiento]])/365.25 -> 36.180698 | DE38: =(Inicio!$G$10-DATOS_[[#This Row],[Fecha de Antigüedad]])/365.25 -> 16.443532 | DF38: =+VLOOKUP(DATOS_[[#This Row],[Clave de Contrato]],TblTiposContrato13[],3,FALSE) -> Completa | DG38: =+VLOOKUP(DATOS_[[#This Row],[Clave de Contrato]],TblTiposContrato13[],4,FALSE) -> Indefinido | DH38: =VLOOKUP(DATOS_[[#This Row],[Edad]],CONTRATOS!TblRngEdad,2,TRUE) -> 35 a 40 | DI38: =VLOOKUP(DATOS_[[#This Row],[Antigüedad]],TblRngAntg14[],2,TRUE) -> más de 15
A39: INMACULADA ESCUDERO MOLINA | B39: 29 | C39: HOMBRE | D39: 39762 | E39: BACHILLER | H39: 39762 | J39: 39762 | M39: 1 | P39: 100 | Q39: ASESORES | R39: ASESORES | S39: ASESOR | T39: CONTINUO | U39: SI | Y39: 14000425011981 | AA39: PERSONAL OPERARIO GENERAL | AC39: 7 | CH39: =+MAX($D$3,DATOS_[[#This Row],[Fecha Inicio Sit. Contract.]]) -> 45292 | CI39: =+MIN($D$4,DATOS_[[#This Row],[Fecha Fin Sit. Contract.]]) -> 45657 | CJ39: =+DATOS_[[#This Row],[% de jornada]]*IF(DATOS_[[#This Row],[% jornada reducida]]="",1,DATOS_[[#This Row],[% jornada reducida]]) -> 1 | CK39: =+(DATOS_[[#This Row],[F.fin.cal]]-DATOS_[[#This Row],[F.ini.cal]]+1)/($D$4-$D$3+1) -> 1 | CL39: =IF(OR(AND(DATOS_[[#This Row],[Fecha Fin Contrato]]<$D$3,DATOS_[[#This Row],[Fecha Fin Contrato]]<>""),DATOS_[[#This Row],[Fecha de Contratación]]>$D$4),"Fuera","Dentro") -> Dentro | CM39: {=IF(MAX(IF(DATOS_[id/cod]=DATOS_[[#This Row],[id/cod]],DATOS_[F.fin.cal]))=DATOS_[[#This Row],[F.fin.cal]],"Sí","NO")} -> Sí | CN39: =IF(AND(DATOS_[[#This Row],[% normaliz]]<>1,DATOS_[[#This Row],[% anualiz]]=1),"Sí","NO") -> NO | CO39: =IF(AND(DATOS_[[#This Row],[% normaliz]]=1,DATOS_[[#This Row],[% anualiz]]<>1),"Sí","NO") -> NO | CP39: =IF(AND(DATOS_[[#This Row],[% normaliz]]<>1,DATOS_[[#This Row],[% anualiz]]<>1),"Sí","NO") -> NO | CQ39: =+IF(DATOS_[[#This Row],[% normaliz]]*DATOS_[[#This Row],[% anualiz]]=1,"NO","Sí") -> NO | CR39: =(DATOS_[[#This Row],[S.BASE]]*(1/DATOS_[[#This Row],[% normaliz]])*(1/DATOS_[[#This Row],[% anualiz]]))*IF(DATOS_[[#This Row],[Check Equiparado]]="Sí",1,0) -> 0 | CS39: =(SUMPRODUCT((RngTipo=$CS$7)*(rngAnualizable="Sí")*(rngNormalizable="Sí")*(DATOS_[[#This Row],[Conc.Sal.01]:[C.Extra.11]]))*(1/DATOS_[[#This Row],[% anualiz]])*(1/DATOS_[[#This Row],[% normaliz]]) +SUMPRODUCT((RngTipo=$CS$7)*(rngAnualizable="Sí")*(rngNormalizable="No")*(DATOS_[[#This Row],[Conc.Sal.01]:[C.Extra.11]]))*(1/DATOS_[[#This Row],[% anualiz]]) +SUMPRODUCT((RngTipo=$CS$7)*(rngAnualizable="No")*(rngNormalizable="Sí")*(DATOS_[[#This Row],[Conc.Sal.01]:[C.Extra.11]]))*(1/DATOS_[[#This Row],[% normaliz]]) +SUMPRODUCT((RngTipo=$CS$7)*(rngAnualizable="No")*(rngNormalizable="No")*(DATOS_[[#This Row],[Conc.Sal.01]:[C.Extra.11]]))) *IF(DATOS_[[#This Row],[Check Equiparado]]="Sí",1,0) -> 0 | CT39: =+DATOS_[[#This Row],[SALARIO BASE Eq]]+DATOS_[[#This Row],[Tot COMPL.SAL Eq]] -> 0 | CU39: {=(SUMPRODUCT((RngTipo=$CU$7)*(rngAnualizable="Sí")*(rngNormalizable="Sí")*(DATOS_[[#This Row],[Conc.Sal.01]:[C.Extra.11]]))*(1/DATOS_[[#This Row],[% anualiz]])*(1/DATOS_[[#This Row],[% normaliz]]) +SUMPRODUCT((RngTipo=$CU$7)*(rngAnualizable="Sí")*(rngNormalizable="No")*(DATOS_[[#This Row],[Conc.Sal.01]:[C.Extra.11]]))*(1/DATOS_[[#This Row],[% anualiz]]) +SUMPRODUCT((RngTipo=$CU$7)*(rngAnualizable="No")*(rngNormalizable="Sí")*(DATOS_[[#This Row],[Conc.Sal.01]:[C.Extra.11]]))*(1/DATOS_[[#This Row],[% normaliz]]) +SUMPRODUCT((RngTipo=$CU$7)*(rngAnualizable="No")*(rngNormalizable="No")*(DATOS_[[#This Row],[Conc.Sal.01]:[C.Extra.11]]))) *IF(DATOS_[[#This Row],[Check Equiparado]]="Sí",1,0)} -> 0 | CV39: =+DATOS_[[#This Row],[TOTAL SALARIO Eq]]+DATOS_[[#This Row],[Tot Extrasalarial Eq]] -> 0 | CW39: =DATOS_[[#This Row],[S.BASE]] -> 0 | CX39: =+SUM(DATOS_[[#This Row],[Conc.Sal.01]:[Conc.Sal.30]]) -> 0 | CY39: =+DATOS_[[#This Row],[SALARIO BASE Ef]]+DATOS_[[#This Row],[Tot COMPL.SAL Ef]] -> 0 | CZ39: =+SUM(DATOS_[[#This Row],[C.Extra.01]:[C.Extra.11]]) -> 0 | DA39: =+DATOS_[[#This Row],[TOTAL SALARIO Ef]]+DATOS_[[#This Row],[Tot Extrasalarial Ef]] -> 0 | DB39: =MIN(IF(DATOS_[[#This Row],[Fecha Fin Contrato]]="",$D$4,DATOS_[[#This Row],[Fecha Fin Contrato]]),$D$4)-MAX(DATOS_[[#This Row],[Fecha de Contratación]],$D$3)+1 -> 366 | DC39: =IF(COUNTIFS(DATOS_[id/cod],DATOS_[[#This Row],[id/cod]])>1,DATOS_[[#This Row],[id/cod]],"") | DD39: =(Inicio!$G$10-DATOS_[[#This Row],[Fecha Nacimiento]])/365.25 -> 16.13963 | DE39: =(Inicio!$G$10-DATOS_[[#This Row],[Fecha de Antigüedad]])/365.25 -> 16.13963 | DF39: =+VLOOKUP(DATOS_[[#This Row],[Clave de Contrato]],TblTiposContrato13[],3,FALSE) -> Completa | DG39: =+VLOOKUP(DATOS_[[#This Row],[Clave de Contrato]],TblTiposContrato13[],4,FALSE) -> Indefinido | DH39: =VLOOKUP(DATOS_[[#This Row],[Edad]],CONTRATOS!TblRngEdad,2,TRUE) -> 20 o menos | DI39: =VLOOKUP(DATOS_[[#This Row],[Antigüedad]],TblRngAntg14[],2,TRUE) -> más de 15
A40: ANGEL BOHOLLO HIDALGO | B40: 30 | C40: HOMBRE | D40: 31299 | E40: FPII | H40: 39762 | J40: 39762 | M40: 1 | P40: 100 | Q40: ASESORES | R40: ASESORES | S40: ASESOR | T40: CONTINUO | U40: SI | Y40: 14000425011981 | AA40: PERSONAL OPERARIO GENERAL | AC40: 7 | CH40: =+MAX($D$3,DATOS_[[#This Row],[Fecha Inicio Sit. Contract.]]) -> 45292 | CI40: =+MIN($D$4,DATOS_[[#This Row],[Fecha Fin Sit. Contract.]]) -> 45657 | CJ40: =+DATOS_[[#This Row],[% de jornada]]*IF(DATOS_[[#This Row],[% jornada reducida]]="",1,DATOS_[[#This Row],[% jornada reducida]]) -> 1 | CK40: =+(DATOS_[[#This Row],[F.fin.cal]]-DATOS_[[#This Row],[F.ini.cal]]+1)/($D$4-$D$3+1) -> 1 | CL40: =IF(OR(AND(DATOS_[[#This Row],[Fecha Fin Contrato]]<$D$3,DATOS_[[#This Row],[Fecha Fin Contrato]]<>""),DATOS_[[#This Row],[Fecha de Contratación]]>$D$4),"Fuera","Dentro") -> Dentro | CM40: {=IF(MAX(IF(DATOS_[id/cod]=DATOS_[[#This Row],[id/cod]],DATOS_[F.fin.cal]))=DATOS_[[#This Row],[F.fin.cal]],"Sí","NO")} -> Sí | CN40: =IF(AND(DATOS_[[#This Row],[% normaliz]]<>1,DATOS_[[#This Row],[% anualiz]]=1),"Sí","NO") -> NO | CO40: =IF(AND(DATOS_[[#This Row],[% normaliz]]=1,DATOS_[[#This Row],[% anualiz]]<>1),"Sí","NO") -> NO | CP40: =IF(AND(DATOS_[[#This Row],[% normaliz]]<>1,DATOS_[[#This Row],[% anualiz]]<>1),"Sí","NO") -> NO | CQ40: =+IF(DATOS_[[#This Row],[% normaliz]]*DATOS_[[#This Row],[% anualiz]]=1,"NO","Sí") -> NO | CR40: =(DATOS_[[#This Row],[S.BASE]]*(1/DATOS_[[#This Row],[% normaliz]])*(1/DATOS_[[#This Row],[% anualiz]]))*IF(DATOS_[[#This Row],[Check Equiparado]]="Sí",1,0) -> 0 | CS40: =(SUMPRODUCT((RngTipo=$CS$7)*(rngAnualizable="Sí")*(rngNormalizable="Sí")*(DATOS_[[#This Row],[Conc.Sal.01]:[C.Extra.11]]))*(1/DATOS_[[#This Row],[% anualiz]])*(1/DATOS_[[#This Row],[% normaliz]]) +SUMPRODUCT((RngTipo=$CS$7)*(rngAnualizable="Sí")*(rngNormalizable="No")*(DATOS_[[#This Row],[Conc.Sal.01]:[C.Extra.11]]))*(1/DATOS_[[#This Row],[% anualiz]]) +SUMPRODUCT((RngTipo=$CS$7)*(rngAnualizable="No")*(rngNormalizable="Sí")*(DATOS_[[#This Row],[Conc.Sal.01]:[C.Extra.11]]))*(1/DATOS_[[#This Row],[% normaliz]]) +SUMPRODUCT((RngTipo=$CS$7)*(rngAnualizable="No")*(rngNormalizable="No")*(DATOS_[[#This Row],[Conc.Sal.01]:[C.Extra.11]]))) *IF(DATOS_[[#This Row],[Check Equiparado]]="Sí",1,0) -> 0 | CT40: =+DATOS_[[#This Row],[SALARIO BASE Eq]]+DATOS_[[#This Row],[Tot COMPL.SAL Eq]] -> 0 | CU40: {=(SUMPRODUCT((RngTipo=$CU$7)*(rngAnualizable="Sí")*(rngNormalizable="Sí")*(DATOS_[[#This Row],[Conc.Sal.01]:[C.Extra.11]]))*(1/DATOS_[[#This Row],[% anualiz]])*(1/DATOS_[[#This Row],[% normaliz]]) +SUMPRODUCT((RngTipo=$CU$7)*(rngAnualizable="Sí")*(rngNormalizable="No")*(DATOS_[[#This Row],[Conc.Sal.01]:[C.Extra.11]]))*(1/DATOS_[[#This Row],[% anualiz]]) +SUMPRODUCT((RngTipo=$CU$7)*(rngAnualizable="No")*(rngNormalizable="Sí")*(DATOS_[[#This Row],[Conc.Sal.01]:[C.Extra.11]]))*(1/DATOS_[[#This Row],[% normaliz]]) +SUMPRODUCT((RngTipo=$CU$7)*(rngAnualizable="No")*(rngNormalizable="No")*(DATOS_[[#This Row],[Conc.Sal.01]:[C.Extra.11]]))) *IF(DATOS_[[#This Row],[Check Equiparado]]="Sí",1,0)} -> 0 | CV40: =+DATOS_[[#This Row],[TOTAL SALARIO Eq]]+DATOS_[[#This Row],[Tot Extrasalarial Eq]] -> 0 | CW40: =DATOS_[[#This Row],[S.BASE]] -> 0 | CX40: =+SUM(DATOS_[[#This Row],[Conc.Sal.01]:[Conc.Sal.30]]) -> 0 | CY40: =+DATOS_[[#This Row],[SALARIO BASE Ef]]+DATOS_[[#This Row],[Tot COMPL.SAL Ef]] -> 0 | CZ40: =+SUM(DATOS_[[#This Row],[C.Extra.01]:[C.Extra.11]]) -> 0 | DA40: =+DATOS_[[#This Row],[TOTAL SALARIO Ef]]+DATOS_[[#This Row],[Tot Extrasalarial Ef]] -> 0 | DB40: =MIN(IF(DATOS_[[#This Row],[Fecha Fin Contrato]]="",$D$4,DATOS_[[#This Row],[Fecha Fin Contrato]]),$D$4)-MAX(DATOS_[[#This Row],[Fecha de Contratación]],$D$3)+1 -> 366 | DC40: =IF(COUNTIFS(DATOS_[id/cod],DATOS_[[#This Row],[id/cod]])>1,DATOS_[[#This Row],[id/cod]],"") | DD40: =(Inicio!$G$10-DATOS_[[#This Row],[Fecha Nacimiento]])/365.25 -> 39.310062 | DE40: =(Inicio!$G$10-DATOS_[[#This Row],[Fecha de Antigüedad]])/365.25 -> 16.13963 | DF40: =+VLOOKUP(DATOS_[[#This Row],[Clave de Contrato]],TblTiposContrato13[],3,FALSE) -> Completa | DG40: =+VLOOKUP(DATOS_[[#This Row],[Clave de Contrato]],TblTiposContrato13[],4,FALSE) -> Indefinido | DH40: =VLOOKUP(DATOS_[[#This Row],[Edad]],CONTRATOS!TblRngEdad,2,TRUE) -> 35 a 40 | DI40: =VLOOKUP(DATOS_[[#This Row],[Antigüedad]],TblRngAntg14[],2,TRUE) -> más de 15
A41: ALBERTO MARTOS MOLINA | B41: 31 | C41: HOMBRE | D41: 28145 | E41: FPII | H41: 39979 | J41: 39979 | M41: 1 | P41: 100 | Q41: CONDUCTORES | R41: CONDUCTORES | S41: CONDUCTOR | T41: CONTINUO | U41: SI | Y41: 14000425011981 | AA41: PERSONAL OPERARIO GENERAL | AC41: 7 | CH41: =+MAX($D$3,DATOS_[[#This Row],[Fecha Inicio Sit. Contract.]]) -> 45292 | CI41: =+MIN($D$4,DATOS_[[#This Row],[Fecha Fin Sit. Contract.]]) -> 45657 | CJ41: =+DATOS_[[#This Row],[% de jornada]]*IF(DATOS_[[#This Row],[% jornada reducida]]="",1,DATOS_[[#This Row],[% jornada reducida]]) -> 1 | CK41: =+(DATOS_[[#This Row],[F.fin.cal]]-DATOS_[[#This Row],[F.ini.cal]]+1)/($D$4-$D$3+1) -> 1 | CL41: =IF(OR(AND(DATOS_[[#This Row],[Fecha Fin Contrato]]<$D$3,DATOS_[[#This Row],[Fecha Fin Contrato]]<>""),DATOS_[[#This Row],[Fecha de Contratación]]>$D$4),"Fuera","Dentro") -> Dentro | CM41: {=IF(MAX(IF(DATOS_[id/cod]=DATOS_[[#This Row],[id/cod]],DATOS_[F.fin.cal]))=DATOS_[[#This Row],[F.fin.cal]],"Sí","NO")} -> Sí | CN41: =IF(AND(DATOS_[[#This Row],[% normaliz]]<>1,DATOS_[[#This Row],[% anualiz]]=1),"Sí","NO") -> NO | CO41: =IF(AND(DATOS_[[#This Row],[% normaliz]]=1,DATOS_[[#This Row],[% anualiz]]<>1),"Sí","NO") -> NO | CP41: =IF(AND(DATOS_[[#This Row],[% normaliz]]<>1,DATOS_[[#This Row],[% anualiz]]<>1),"Sí","NO") -> NO | CQ41: =+IF(DATOS_[[#This Row],[% normaliz]]*DATOS_[[#This Row],[% anualiz]]=1,"NO","Sí") -> NO | CR41: =(DATOS_[[#This Row],[S.BASE]]*(1/DATOS_[[#This Row],[% normaliz]])*(1/DATOS_[[#This Row],[% anualiz]]))*IF(DATOS_[[#This Row],[Check Equiparado]]="Sí",1,0) -> 0 | CS41: =(SUMPRODUCT((RngTipo=$CS$7)*(rngAnualizable="Sí")*(rngNormalizable="Sí")*(DATOS_[[#This Row],[Conc.Sal.01]:[C.Extra.11]]))*(1/DATOS_[[#This Row],[% anualiz]])*(1/DATOS_[[#This Row],[% normaliz]]) +SUMPRODUCT((RngTipo=$CS$7)*(rngAnualizable="Sí")*(rngNormalizable="No")*(DATOS_[[#This Row],[Conc.Sal.01]:[C.Extra.11]]))*(1/DATOS_[[#This Row],[% anualiz]]) +SUMPRODUCT((RngTipo=$CS$7)*(rngAnualizable="No")*(rngNormalizable="Sí")*(DATOS_[[#This Row],[Conc.Sal.01]:[C.Extra.11]]))*(1/DATOS_[[#This Row],[% normaliz]]) +SUMPRODUCT((RngTipo=$CS$7)*(rngAnualizable="No")*(rngNormalizable="No")*(DATOS_[[#This Row],[Conc.Sal.01]:[C.Extra.11]]))) *IF(DATOS_[[#This Row],[Check Equiparado]]="Sí",1,0) -> 0 | CT41: =+DATOS_[[#This Row],[SALARIO BASE Eq]]+DATOS_[[#This Row],[Tot COMPL.SAL Eq]] -> 0 | CU41: {=(SUMPRODUCT((RngTipo=$CU$7)*(rngAnualizable="Sí")*(rngNormalizable="Sí")*(DATOS_[[#This Row],[Conc.Sal.01]:[C.Extra.11]]))*(1/DATOS_[[#This Row],[% anualiz]])*(1/DATOS_[[#This Row],[% normaliz]]) +SUMPRODUCT((RngTipo=$CU$7)*(rngAnualizable="Sí")*(rngNormalizable="No")*(DATOS_[[#This Row],[Conc.Sal.01]:[C.Extra.11]]))*(1/DATOS_[[#This Row],[% anualiz]]) +SUMPRODUCT((RngTipo=$CU$7)*(rngAnualizable="No")*(rngNormalizable="Sí")*(DATOS_[[#This Row],[Conc.Sal.01]:[C.Extra.11]]))*(1/DATOS_[[#This Row],[% normaliz]]) +SUMPRODUCT((RngTipo=$CU$7)*(rngAnualizable="No")*(rngNormalizable="No")*(DATOS_[[#This Row],[Conc.Sal.01]:[C.Extra.11]]))) *IF(DATOS_[[#This Row],[Check Equiparado]]="Sí",1,0)} -> 0 | CV41: =+DATOS_[[#This Row],[TOTAL SALARIO Eq]]+DATOS_[[#This Row],[Tot Extrasalarial Eq]] -> 0 | CW41: =DATOS_[[#This Row],[S.BASE]] -> 0 | CX41: =+SUM(DATOS_[[#This Row],[Conc.Sal.01]:[Conc.Sal.30]]) -> 0 | CY41: =+DATOS_[[#This Row],[SALARIO BASE Ef]]+DATOS_[[#This Row],[Tot COMPL.SAL Ef]] -> 0 | CZ41: =+SUM(DATOS_[[#This Row],[C.Extra.01]:[C.Extra.11]]) -> 0 | DA41: =+DATOS_[[#This Row],[TOTAL SALARIO Ef]]+DATOS_[[#This Row],[Tot Extrasalarial Ef]] -> 0 | DB41: =MIN(IF(DATOS_[[#This Row],[Fecha Fin Contrato]]="",$D$4,DATOS_[[#This Row],[Fecha Fin Contrato]]),$D$4)-MAX(DATOS_[[#This Row],[Fecha de Contratación]],$D$3)+1 -> 366 | DC41: =IF(COUNTIFS(DATOS_[id/cod],DATOS_[[#This Row],[id/cod]])>1,DATOS_[[#This Row],[id/cod]],"") | DD41: =(Inicio!$G$10-DATOS_[[#This Row],[Fecha Nacimiento]])/365.25 -> 47.945243 | DE41: =(Inicio!$G$10-DATOS_[[#This Row],[Fecha de Antigüedad]])/365.25 -> 15.545517 | DF41: =+VLOOKUP(DATOS_[[#This Row],[Clave de Contrato]],TblTiposContrato13[],3,FALSE) -> Completa | DG41: =+VLOOKUP(DATOS_[[#This Row],[Clave de Contrato]],TblTiposContrato13[],4,FALSE) -> Indefinido | DH41: =VLOOKUP(DATOS_[[#This Row],[Edad]],CONTRATOS!TblRngEdad,2,TRUE) -> 45 a 50 | DI41: =VLOOKUP(DATOS_[[#This Row],[Antigüedad]],TblRngAntg14[],2,TRUE) -> más de 15
A42: FRANCISCO MERINO LUNA | B42: 32 | C42: MUJER | D42: 22280 | E42: E.G.B. | H42: 40305 | J42: 40305 | M42: 0.75 | P42: 100 | Q42: LIMPIEZA | R42: LIMPIEZA | S42: LIMPIEZA | T42: PARTIDO | U42: SI | Y42: 14000425011981 | AA42: PERSONAL OPERARIO GENERAL | CH42: =+MAX($D$3,DATOS_[[#This Row],[Fecha Inicio Sit. Contract.]]) -> 45292 | CI42: =+MIN($D$4,DATOS_[[#This Row],[Fecha Fin Sit. Contract.]]) -> 45657 | CJ42: =+DATOS_[[#This Row],[% de jornada]]*IF(DATOS_[[#This Row],[% jornada reducida]]="",1,DATOS_[[#This Row],[% jornada reducida]]) -> 0.75 | CK42: =+(DATOS_[[#This Row],[F.fin.cal]]-DATOS_[[#This Row],[F.ini.cal]]+1)/($D$4-$D$3+1) -> 1 | CL42: =IF(OR(AND(DATOS_[[#This Row],[Fecha Fin Contrato]]<$D$3,DATOS_[[#This Row],[Fecha Fin Contrato]]<>""),DATOS_[[#This Row],[Fecha de Contratación]]>$D$4),"Fuera","Dentro") -> Dentro | CM42: {=IF(MAX(IF(DATOS_[id/cod]=DATOS_[[#This Row],[id/cod]],DATOS_[F.fin.cal]))=DATOS_[[#This Row],[F.fin.cal]],"Sí","NO")} -> Sí | CN42: =IF(AND(DATOS_[[#This Row],[% normaliz]]<>1,DATOS_[[#This Row],[% anualiz]]=1),"Sí","NO") -> Sí | CO42: =IF(AND(DATOS_[[#This Row],[% normaliz]]=1,DATOS_[[#This Row],[% anualiz]]<>1),"Sí","NO") -> NO | CP42: =IF(AND(DATOS_[[#This Row],[% normaliz]]<>1,DATOS_[[#This Row],[% anualiz]]<>1),"Sí","NO") -> NO | CQ42: =+IF(DATOS_[[#This Row],[% normaliz]]*DATOS_[[#This Row],[% anualiz]]=1,"NO","Sí") -> Sí | CR42: =(DATOS_[[#This Row],[S.BASE]]*(1/DATOS_[[#This Row],[% normaliz]])*(1/DATOS_[[#This Row],[% anualiz]]))*IF(DATOS_[[#This Row],[Check Equiparado]]="Sí",1,0) -> 0 | CS42: =(SUMPRODUCT((RngTipo=$CS$7)*(rngAnualizable="Sí")*(rngNormalizable="Sí")*(DATOS_[[#This Row],[Conc.Sal.01]:[C.Extra.11]]))*(1/DATOS_[[#This Row],[% anualiz]])*(1/DATOS_[[#This Row],[% normaliz]]) +SUMPRODUCT((RngTipo=$CS$7)*(rngAnualizable="Sí")*(rngNormalizable="No")*(DATOS_[[#This Row],[Conc.Sal.01]:[C.Extra.11]]))*(1/DATOS_[[#This Row],[% anualiz]]) +SUMPRODUCT((RngTipo=$CS$7)*(rngAnualizable="No")*(rngNormalizable="Sí")*(DATOS_[[#This Row],[Conc.Sal.01]:[C.Extra.11]]))*(1/DATOS_[[#This Row],[% normaliz]]) +SUMPRODUCT((RngTipo=$CS$7)*(rngAnualizable="No")*(rngNormalizable="No")*(DATOS_[[#This Row],[Conc.Sal.01]:[C.Extra.11]]))) *IF(DATOS_[[#This Row],[Check Equiparado]]="Sí",1,0) -> 0 | CT42: =+DATOS_[[#This Row],[SALARIO BASE Eq]]+DATOS_[[#This Row],[Tot COMPL.SAL Eq]] -> 0 | CU42: {=(SUMPRODUCT((RngTipo=$CU$7)*(rngAnualizable="Sí")*(rngNormalizable="Sí")*(DATOS_[[#This Row],[Conc.Sal.01]:[C.Extra.11]]))*(1/DATOS_[[#This Row],[% anualiz]])*(1/DATOS_[[#This Row],[% normaliz]]) +SUMPRODUCT((RngTipo=$CU$7)*(rngAnualizable="Sí")*(rngNormalizable="No")*(DATOS_[[#This Row],[Conc.Sal.01]:[C.Extra.11]]))*(1/DATOS_[[#This Row],[% anualiz]]) +SUMPRODUCT((RngTipo=$CU$7)*(rngAnualizable="No")*(rngNormalizable="Sí")*(DATOS_[[#This Row],[Conc.Sal.01]:[C.Extra.11]]))*(1/DATOS_[[#This Row],[% normaliz]]) +SUMPRODUCT((RngTipo=$CU$7)*(rngAnualizable="No")*(rngNormalizable="No")*(DATOS_[[#This Row],[Conc.Sal.01]:[C.Extra.11]]))) *IF(DATOS_[[#This Row],[Check Equiparado]]="Sí",1,0)} -> 0 | CV42: =+DATOS_[[#This Row],[TOTAL SALARIO Eq]]+DATOS_[[#This Row],[Tot Extrasalarial Eq]] -> 0 | CW42: =DATOS_[[#This Row],[S.BASE]] -> 0 | CX42: =+SUM(DATOS_[[#This Row],[Conc.Sal.01]:[Conc.Sal.30]]) -> 0 | CY42: =+DATOS_[[#This Row],[SALARIO BASE Ef]]+DATOS_[[#This Row],[Tot COMPL.SAL Ef]] -> 0 | CZ42: =+SUM(DATOS_[[#This Row],[C.Extra.01]:[C.Extra.11]]) -> 0 | DA42: =+DATOS_[[#This Row],[TOTAL SALARIO Ef]]+DATOS_[[#This Row],[Tot Extrasalarial Ef]] -> 0 | DB42: =MIN(IF(DATOS_[[#This Row],[Fecha Fin Contrato]]="",$D$4,DATOS_[[#This Row],[Fecha Fin Contrato]]),$D$4)-MAX(DATOS_[[#This Row],[Fecha de Contratación]],$D$3)+1 -> 366 | DC42: =IF(COUNTIFS(DATOS_[id/cod],DATOS_[[#This Row],[id/cod]])>1,DATOS_[[#This Row],[id/cod]],"") | DD42: =(Inicio!$G$10-DATOS_[[#This Row],[Fecha Nacimiento]])/365.25 -> 64.002738 | DE42: =(Inicio!$G$10-DATOS_[[#This Row],[Fecha de Antigüedad]])/365.25 -> 14.652977 | DF42: =+VLOOKUP(DATOS_[[#This Row],[Clave de Contrato]],TblTiposContrato13[],3,FALSE) -> Completa | DG42: =+VLOOKUP(DATOS_[[#This Row],[Clave de Contrato]],TblTiposContrato13[],4,FALSE) -> Indefinido | DH42: =VLOOKUP(DATOS_[[#This Row],[Edad]],CONTRATOS!TblRngEdad,2,TRUE) -> 60 en adelante | DI42: =VLOOKUP(DATOS_[[#This Row],[Antigüedad]],TblRngAntg14[],2,TRUE) -> de 10 a 15 años
A43: ENCARNACION ARENAS MOINA | B43: 33 | C43: HOMBRE | D43: 31301 | E43: FPII | H43: 40324 | J43: 40324 | M43: 1 | P43: 100 | Q43: ASESORES | R43: ASESORES | S43: ASESOR | T43: CONTINUO | U43: SI | W43: GRUPO 05 | Y43: 14000425011981 | Z43: limpiador/a | AA43: PERSONAL OPERARIO GENERAL | AC43: 10 | AD43: 6437.12 | AE43: 37.44 | AF43: 654.06 | AG43: 457.29 | AH43: 1005.52 | AI43: 82.64 | AJ43: 639.37 | AK43: 0 | AL43: 0 | AM43: 0 | AN43: 0 | AO43: 522.65 | AP43: 300 | AQ43: 0 | AR43: 61 | AS43: 0 | AT43: 2122.63 | AU43: 279 | AV43: 2150.45 | AW43: 0 | AX43: 0 | AY43: 65 | CH43: =+MAX($D$3,DATOS_[[#This Row],[Fecha Inicio Sit. Contract.]]) -> 45292 | CI43: =+MIN($D$4,DATOS_[[#This Row],[Fecha Fin Sit. Contract.]]) -> 45657 | CJ43: =+DATOS_[[#This Row],[% de jornada]]*IF(DATOS_[[#This Row],[% jornada reducida]]="",1,DATOS_[[#This Row],[% jornada reducida]]) -> 1 | CK43: =+(DATOS_[[#This Row],[F.fin.cal]]-DATOS_[[#This Row],[F.ini.cal]]+1)/($D$4-$D$3+1) -> 1 | CL43: =IF(OR(AND(DATOS_[[#This Row],[Fecha Fin Contrato]]<$D$3,DATOS_[[#This Row],[Fecha Fin Contrato]]<>""),DATOS_[[#This Row],[Fecha de Contratación]]>$D$4),"Fuera","Dentro") -> Dentro | CM43: {=IF(MAX(IF(DATOS_[id/cod]=DATOS_[[#This Row],[id/cod]],DATOS_[F.fin.cal]))=DATOS_[[#This Row],[F.fin.cal]],"Sí","NO")} -> Sí | CN43: =IF(AND(DATOS_[[#This Row],[% normaliz]]<>1,DATOS_[[#This Row],[% anualiz]]=1),"Sí","NO") -> NO | CO43: =IF(AND(DATOS_[[#This Row],[% normaliz]]=1,DATOS_[[#This Row],[% anualiz]]<>1),"Sí","NO") -> NO | CP43: =IF(AND(DATOS_[[#This Row],[% normaliz]]<>1,DATOS_[[#This Row],[% anualiz]]<>1),"Sí","NO") -> NO | CQ43: =+IF(DATOS_[[#This Row],[% normaliz]]*DATOS_[[#This Row],[% anualiz]]=1,"NO","Sí") -> NO | CR43: =(DATOS_[[#This Row],[S.BASE]]*(1/DATOS_[[#This Row],[% normaliz]])*(1/DATOS_[[#This Row],[% anualiz]]))*IF(DATOS_[[#This Row],[Check Equiparado]]="Sí",1,0) -> 6437.12 | CS43: =(SUMPRODUCT((RngTipo=$CS$7)*(rngAnualizable="Sí")*(rngNormalizable="Sí")*(DATOS_[[#This Row],[Conc.Sal.01]:[C.Extra.11]]))*(1/DATOS_[[#This Row],[% anualiz]])*(1/DATOS_[[#This Row],[% normaliz]]) +SUMPRODUCT((RngTipo=$CS$7)*(rngAnualizable="Sí")*(rngNormalizable="No")*(DATOS_[[#This Row],[Conc.Sal.01]:[C.Extra.11]]))*(1/DATOS_[[#This Row],[% anualiz]]) +SUMPRODUCT((RngTipo=$CS$7)*(rngAnualizable="No")*(rngNormalizable="Sí")*(DATOS_[[#This Row],[Conc.Sal.01]:[C.Extra.11]]))*(1/DATOS_[[#This Row],[% normaliz]]) +SUMPRODUCT((RngTipo=$CS$7)*(rngAnualizable="No")*(rngNormalizable="No")*(DATOS_[[#This Row],[Conc.Sal.01]:[C.Extra.11]]))) *IF(DATOS_[[#This Row],[Check Equiparado]]="Sí",1,0) -> 4103.97 | CT43: =+DATOS_[[#This Row],[SALARIO BASE Eq]]+DATOS_[[#This Row],[Tot COMPL.SAL Eq]] -> 10541.09 | CU43: {=(SUMPRODUCT((RngTipo=$CU$7)*(rngAnualizable="Sí")*(rngNormalizable="Sí")*(DATOS_[[#This Row],[Conc.Sal.01]:[C.Extra.11]]))*(1/DATOS_[[#This Row],[% anualiz]])*(1/DATOS_[[#This Row],[% normaliz]]) +SUMPRODUCT((RngTipo=$CU$7)*(rngAnualizable="Sí")*(rngNormalizable="No")*(DATOS_[[#This Row],[Conc.Sal.01]:[C.Extra.11]]))*(1/DATOS_[[#This Row],[% anualiz]]) +SUMPRODUCT((RngTipo=$CU$7)*(rngAnualizable="No")*(rngNormalizable="Sí")*(DATOS_[[#This Row],[Conc.Sal.01]:[C.Extra.11]]))*(1/DATOS_[[#This Row],[% normaliz]]) +SUMPRODUCT((RngTipo=$CU$7)*(rngAnualizable="No")*(rngNormalizable="No")*(DATOS_[[#This Row],[Conc.Sal.01]:[C.Extra.11]]))) *IF(DATOS_[[#This Row],[Check Equiparado]]="Sí",1,0)} -> 4273.08 | CV43: =+DATOS_[[#This Row],[TOTAL SALARIO Eq]]+DATOS_[[#This Row],[Tot Extrasalarial Eq]] -> 14814.17 | CW43: =DATOS_[[#This Row],[S.BASE]] -> 6437.12 | CX43: =+SUM(DATOS_[[#This Row],[Conc.Sal.01]:[Conc.Sal.30]]) -> 8377.05 | CY43: =+DATOS_[[#This Row],[SALARIO BASE Ef]]+DATOS_[[#This Row],[Tot COMPL.SAL Ef]] -> 14814.17 | CZ43: =+SUM(DATOS_[[#This Row],[C.Extra.01]:[C.Extra.11]]) -> 0 | DA43: =+DATOS_[[#This Row],[TOTAL SALARIO Ef]]+DATOS_[[#This Row],[Tot Extrasalarial Ef]] -> 14814.17 | DB43: =MIN(IF(DATOS_[[#This Row],[Fecha Fin Contrato]]="",$D$4,DATOS_[[#This Row],[Fecha Fin Contrato]]),$D$4)-MAX(DATOS_[[#This Row],[Fecha de Contratación]],$D$3)+1 -> 366 | DC43: =IF(COUNTIFS(DATOS_[id/cod],DATOS_[[#This Row],[id/cod]])>1,DATOS_[[#This Row],[id/cod]],"") | DD43: =(Inicio!$G$10-DATOS_[[#This Row],[Fecha Nacimiento]])/365.25 -> 39.304586 | DE43: =(Inicio!$G$10-DATOS_[[#This Row],[Fecha de Antigüedad]])/365.25 -> 14.600958 | DF43: =+VLOOKUP(DATOS_[[#This Row],[Clave de Contrato]],TblTiposContrato13[],3,FALSE) -> Completa | DG43: =+VLOOKUP(DATOS_[[#This Row],[Clave de Contrato]],TblTiposContrato13[],4,FALSE) -> Indefinido | DH43: =VLOOKUP(DATOS_[[#This Row],[Edad]],CONTRATOS!TblRngEdad,2,TRUE) -> 35 a 40 | DI43: =VLOOKUP(DATOS_[[#This Row],[Antigüedad]],TblRngAntg14[],2,TRUE) -> de 10 a 15 años
A44: JAIME NAVARRO GALLEGO | B44: 34 | C44: MUJER | D44: 25554 | E44: E.G.B. | H44: 40391 | J44: 40391 | M44: 1 | P44: 100 | Q44: LIMPIEZA | R44: LIMPIEZA | S44: LIMPIADORA | T44: CONTINUO | U44: SI | Y44: 14000425011981 | AA44: PERSONAL OPERARIO GENERAL | CH44: =+MAX($D$3,DATOS_[[#This Row],[Fecha Inicio Sit. Contract.]]) -> 45292 | CI44: =+MIN($D$4,DATOS_[[#This Row],[Fecha Fin Sit. Contract.]]) -> 45657 | CJ44: =+DATOS_[[#This Row],[% de jornada]]*IF(DATOS_[[#This Row],[% jornada reducida]]="",1,DATOS_[[#This Row],[% jornada reducida]]) -> 1 | CK44: =+(DATOS_[[#This Row],[F.fin.cal]]-DATOS_[[#This Row],[F.ini.cal]]+1)/($D$4-$D$3+1) -> 1 | CL44: =IF(OR(AND(DATOS_[[#This Row],[Fecha Fin Contrato]]<$D$3,DATOS_[[#This Row],[Fecha Fin Contrato]]<>""),DATOS_[[#This Row],[Fecha de Contratación]]>$D$4),"Fuera","Dentro") -> Dentro | CM44: {=IF(MAX(IF(DATOS_[id/cod]=DATOS_[[#This Row],[id/cod]],DATOS_[F.fin.cal]))=DATOS_[[#This Row],[F.fin.cal]],"Sí","NO")} -> Sí | CN44: =IF(AND(DATOS_[[#This Row],[% normaliz]]<>1,DATOS_[[#This Row],[% anualiz]]=1),"Sí","NO") -> NO | CO44: =IF(AND(DATOS_[[#This Row],[% normaliz]]=1,DATOS_[[#This Row],[% anualiz]]<>1),"Sí","NO") -> NO | CP44: =IF(AND(DATOS_[[#This Row],[% normaliz]]<>1,DATOS_[[#This Row],[% anualiz]]<>1),"Sí","NO") -> NO | CQ44: =+IF(DATOS_[[#This Row],[% normaliz]]*DATOS_[[#This Row],[% anualiz]]=1,"NO","Sí") -> NO | CR44: =(DATOS_[[#This Row],[S.BASE]]*(1/DATOS_[[#This Row],[% normaliz]])*(1/DATOS_[[#This Row],[% anualiz]]))*IF(DATOS_[[#This Row],[Check Equiparado]]="Sí",1,0) -> 0 | CS44: =(SUMPRODUCT((RngTipo=$CS$7)*(rngAnualizable="Sí")*(rngNormalizable="Sí")*(DATOS_[[#This Row],[Conc.Sal.01]:[C.Extra.11]]))*(1/DATOS_[[#This Row],[% anualiz]])*(1/DATOS_[[#This Row],[% normaliz]]) +SUMPRODUCT((RngTipo=$CS$7)*(rngAnualizable="Sí")*(rngNormalizable="No")*(DATOS_[[#This Row],[Conc.Sal.01]:[C.Extra.11]]))*(1/DATOS_[[#This Row],[% anualiz]]) +SUMPRODUCT((RngTipo=$CS$7)*(rngAnualizable="No")*(rngNormalizable="Sí")*(DATOS_[[#This Row],[Conc.Sal.01]:[C.Extra.11]]))*(1/DATOS_[[#This Row],[% normaliz]]) +SUMPRODUCT((RngTipo=$CS$7)*(rngAnualizable="No")*(rngNormalizable="No")*(DATOS_[[#This Row],[Conc.Sal.01]:[C.Extra.11]]))) *IF(DATOS_[[#This Row],[Check Equiparado]]="Sí",1,0) -> 0 | CT44: =+DATOS_[[#This Row],[SALARIO BASE Eq]]+DATOS_[[#This Row],[Tot COMPL.SAL Eq]] -> 0 | CU44: {=(SUMPRODUCT((RngTipo=$CU$7)*(rngAnualizable="Sí")*(rngNormalizable="Sí")*(DATOS_[[#This Row],[Conc.Sal.01]:[C.Extra.11]]))*(1/DATOS_[[#This Row],[% anualiz]])*(1/DATOS_[[#This Row],[% normaliz]]) +SUMPRODUCT((RngTipo=$CU$7)*(rngAnualizable="Sí")*(rngNormalizable="No")*(DATOS_[[#This Row],[Conc.Sal.01]:[C.Extra.11]]))*(1/DATOS_[[#This Row],[% anualiz]]) +SUMPRODUCT((RngTipo=$CU$7)*(rngAnualizable="No")*(rngNormalizable="Sí")*(DATOS_[[#This Row],[Conc.Sal.01]:[C.Extra.11]]))*(1/DATOS_[[#This Row],[% normaliz]]) +SUMPRODUCT((RngTipo=$CU$7)*(rngAnualizable="No")*(rngNormalizable="No")*(DATOS_[[#This Row],[Conc.Sal.01]:[C.Extra.11]]))) *IF(DATOS_[[#This Row],[Check Equiparado]]="Sí",1,0)} -> 0 | CV44: =+DATOS_[[#This Row],[TOTAL SALARIO Eq]]+DATOS_[[#This Row],[Tot Extrasalarial Eq]] -> 0 | CW44: =DATOS_[[#This Row],[S.BASE]] -> 0 | CX44: =+SUM(DATOS_[[#This Row],[Conc.Sal.01]:[Conc.Sal.30]]) -> 0 | CY44: =+DATOS_[[#This Row],[SALARIO BASE Ef]]+DATOS_[[#This Row],[Tot COMPL.SAL Ef]] -> 0 | CZ44: =+SUM(DATOS_[[#This Row],[C.Extra.01]:[C.Extra.11]]) -> 0 | DA44: =+DATOS_[[#This Row],[TOTAL SALARIO Ef]]+DATOS_[[#This Row],[Tot Extrasalarial Ef]] -> 0 | DB44: =MIN(IF(DATOS_[[#This Row],[Fecha Fin Contrato]]="",$D$4,DATOS_[[#This Row],[Fecha Fin Contrato]]),$D$4)-MAX(DATOS_[[#This Row],[Fecha de Contratación]],$D$3)+1 -> 366 | DC44: =IF(COUNTIFS(DATOS_[id/cod],DATOS_[[#This Row],[id/cod]])>1,DATOS_[[#This Row],[id/cod]],"") | DD44: =(Inicio!$G$10-DATOS_[[#This Row],[Fecha Nacimiento]])/365.25 -> 55.039014 | DE44: =(Inicio!$G$10-DATOS_[[#This Row],[Fecha de Antigüedad]])/365.25 -> 14.417522 | DF44: =+VLOOKUP(DATOS_[[#This Row],[Clave de Contrato]],TblTiposContrato13[],3,FALSE) -> Completa | DG44: =+VLOOKUP(DATOS_[[#This Row],[Clave de Contrato]],TblTiposContrato13[],4,FALSE) -> Indefinido | DH44: =VLOOKUP(DATOS_[[#This Row],[Edad]],CONTRATOS!TblRngEdad,2,TRUE) -> 55 a 60 | DI44: =VLOOKUP(DATOS_[[#This Row],[Antigüedad]],TblRngAntg14[],2,TRUE) -> de 10 a 15 años
A45: ELENA CASTON CRUZ | B45: 35 | C45: MUJER | D45: 40391 | E45: E.G.B. | H45: 40391 | J45: 40391 | M45: 0.75 | P45: 100 | Q45: LIMPIEZA | R45: LIMPIEZA | S45: LIMPIADORA | T45: PARCIAL | U45: SI | W45: GRUPO 05 | Y45: 14000425011981 | Z45: limpiador/a | AA45: PERSONAL OPERARIO GENERAL | AC45: 10 | AD45: 4086.91 | AE45: 13.26 | AF45: 381.01 | AG45: 265.54 | AH45: 849.11 | AI45: 125.62 | AJ45: 313.83 | AK45: 0 | AL45: 0 | AM45: 72.36 | AN45: 0 | AO45: 1654.35 | AP45: 0 | AQ45: 0 | AR45: 200 | AS45: 0 | AT45: 2170.26 | AU45: 393 | AV45: 8802.09 | AW45: 0 | AX45: 0 | AY45: 65 | CH45: =+MAX($D$3,DATOS_[[#This Row],[Fecha Inicio Sit. Contract.]]) -> 45292 | CI45: =+MIN($D$4,DATOS_[[#This Row],[Fecha Fin Sit. Contract.]]) -> 45657 | CJ45: =+DATOS_[[#This Row],[% de jornada]]*IF(DATOS_[[#This Row],[% jornada reducida]]="",1,DATOS_[[#This Row],[% jornada reducida]]) -> 0.75 | CK45: =+(DATOS_[[#This Row],[F.fin.cal]]-DATOS_[[#This Row],[F.ini.cal]]+1)/($D$4-$D$3+1) -> 1 | CL45: =IF(OR(AND(DATOS_[[#This Row],[Fecha Fin Contrato]]<$D$3,DATOS_[[#This Row],[Fecha Fin Contrato]]<>""),DATOS_[[#This Row],[Fecha de Contratación]]>$D$4),"Fuera","Dentro") -> Dentro | CM45: {=IF(MAX(IF(DATOS_[id/cod]=DATOS_[[#This Row],[id/cod]],DATOS_[F.fin.cal]))=DATOS_[[#This Row],[F.fin.cal]],"Sí","NO")} -> Sí | CN45: =IF(AND(DATOS_[[#This Row],[% normaliz]]<>1,DATOS_[[#This Row],[% anualiz]]=1),"Sí","NO") -> Sí | CO45: =IF(AND(DATOS_[[#This Row],[% normaliz]]=1,DATOS_[[#This Row],[% anualiz]]<>1),"Sí","NO") -> NO | CP45: =IF(AND(DATOS_[[#This Row],[% normaliz]]<>1,DATOS_[[#This Row],[% anualiz]]<>1),"Sí","NO") -> NO | CQ45: =+IF(DATOS_[[#This Row],[% normaliz]]*DATOS_[[#This Row],[% anualiz]]=1,"NO","Sí") -> Sí | CR45: =(DATOS_[[#This Row],[S.BASE]]*(1/DATOS_[[#This Row],[% normaliz]])*(1/DATOS_[[#This Row],[% anualiz]]))*IF(DATOS_[[#This Row],[Check Equiparado]]="Sí",1,0) -> 5449.2133 | CS45: =(SUMPRODUCT((RngTipo=$CS$7)*(rngAnualizable="Sí")*(rngNormalizable="Sí")*(DATOS_[[#This Row],[Conc.Sal.01]:[C.Extra.11]]))*(1/DATOS_[[#This Row],[% anualiz]])*(1/DATOS_[[#This Row],[% normaliz]]) +SUMPRODUCT((RngTipo=$CS$7)*(rngAnualizable="Sí")*(rngNormalizable="No")*(DATOS_[[#This Row],[Conc.Sal.01]:[C.Extra.11]]))*(1/DATOS_[[#This Row],[% anualiz]]) +SUMPRODUCT((RngTipo=$CS$7)*(rngAnualizable="No")*(rngNormalizable="Sí")*(DATOS_[[#This Row],[Conc.Sal.01]:[C.Extra.11]]))*(1/DATOS_[[#This Row],[% normaliz]]) +SUMPRODUCT((RngTipo=$CS$7)*(rngAnualizable="No")*(rngNormalizable="No")*(DATOS_[[#This Row],[Conc.Sal.01]:[C.Extra.11]]))) *IF(DATOS_[[#This Row],[Check Equiparado]]="Sí",1,0) -> 5777.44 | CT45: =+DATOS_[[#This Row],[SALARIO BASE Eq]]+DATOS_[[#This Row],[Tot COMPL.SAL Eq]] -> 11226.653 | CU45: {=(SUMPRODUCT((RngTipo=$CU$7)*(rngAnualizable="Sí")*(rngNormalizable="Sí")*(DATOS_[[#This Row],[Conc.Sal.01]:[C.Extra.11]]))*(1/DATOS_[[#This Row],[% anualiz]])*(1/DATOS_[[#This Row],[% normaliz]]) +SUMPRODUCT((RngTipo=$CU$7)*(rngAnualizable="Sí")*(rngNormalizable="No")*(DATOS_[[#This Row],[Conc.Sal.01]:[C.Extra.11]]))*(1/DATOS_[[#This Row],[% anualiz]]) +SUMPRODUCT((RngTipo=$CU$7)*(rngAnualizable="No")*(rngNormalizable="Sí")*(DATOS_[[#This Row],[Conc.Sal.01]:[C.Extra.11]]))*(1/DATOS_[[#This Row],[% normaliz]]) +SUMPRODUCT((RngTipo=$CU$7)*(rngAnualizable="No")*(rngNormalizable="No")*(DATOS_[[#This Row],[Conc.Sal.01]:[C.Extra.11]]))) *IF(DATOS_[[#This Row],[Check Equiparado]]="Sí",1,0)} -> 14629.8 | CV45: =+DATOS_[[#This Row],[TOTAL SALARIO Eq]]+DATOS_[[#This Row],[Tot Extrasalarial Eq]] -> 25856.453 | CW45: =DATOS_[[#This Row],[S.BASE]] -> 4086.91 | CX45: =+SUM(DATOS_[[#This Row],[Conc.Sal.01]:[Conc.Sal.30]]) -> 15305.43 | CY45: =+DATOS_[[#This Row],[SALARIO BASE Ef]]+DATOS_[[#This Row],[Tot COMPL.SAL Ef]] -> 19392.34 | CZ45: =+SUM(DATOS_[[#This Row],[C.Extra.01]:[C.Extra.11]]) -> 0 | DA45: =+DATOS_[[#This Row],[TOTAL SALARIO Ef]]+DATOS_[[#This Row],[Tot Extrasalarial Ef]] -> 19392.34 | DB45: =MIN(IF(DATOS_[[#This Row],[Fecha Fin Contrato]]="",$D$4,DATOS_[[#This Row],[Fecha Fin Contrato]]),$D$4)-MAX(DATOS_[[#This Row],[Fecha de Contratación]],$D$3)+1 -> 366 | DC45: =IF(COUNTIFS(DATOS_[id/cod],DATOS_[[#This Row],[id/cod]])>1,DATOS_[[#This Row],[id/cod]],"") | DD45: =(Inicio!$G$10-DATOS_[[#This Row],[Fecha Nacimiento]])/365.25 -> 14.417522 | DE45: =(Inicio!$G$10-DATOS_[[#This Row],[Fecha de Antigüedad]])/365.25 -> 14.417522 | DF45: =+VLOOKUP(DATOS_[[#This Row],[Clave de Contrato]],TblTiposContrato13[],3,FALSE) -> Completa | DG45: =+VLOOKUP(DATOS_[[#This Row],[Clave de Contrato]],TblTiposContrato13[],4,FALSE) -> Indefinido | DH45: =VLOOKUP(DATOS_[[#This Row],[Edad]],CONTRATOS!TblRngEdad,2,TRUE) -> 20 o menos | DI45: =VLOOKUP(DATOS_[[#This Row],[Antigüedad]],TblRngAntg14[],2,TRUE) -> de 10 a 15 años
A46: Mª CARMEN AGUAYO HUERTAS | B46: 36 | C46: MUJER | D46: 22830 | E46: CERTIFICADO ESCOLARIDAD | H46: 40399 | J46: 40399 | M46: 1 | P46: 100 | Q46: LIMPIEZA | R46: LIMPIEZA | S46: LIMPIADORA | T46: CONTINUO | U46: SI | W46: GRUPO 05 | Y46: 14000425011981 | Z46: limpiador/a | AA46: PERSONAL OPERARIO GENERAL | AC46: 10 | AD46: 10735.77 | AE46: 36.66 | AF46: 1000.85 | AG46: 697.55 | AH46: 1698.22 | AI46: 143.25 | AJ46: 824.38 | AK46: 0 | AL46: 0 | AM46: 0 | AN46: 308.84 | AO46: 85.81 | AP46: 300 | AQ46: 0 | AR46: 685 | AS46: 0 | AT46: 3107.26 | AU46: 0 | AV46: 0 | AW46: 0 | AX46: 0 | AY46: 65 | CH46: =+MAX($D$3,DATOS_[[#This Row],[Fecha Inicio Sit. Contract.]]) -> 45292 | CI46: =+MIN($D$4,DATOS_[[#This Row],[Fecha Fin Sit. Contract.]]) -> 45657 | CJ46: =+DATOS_[[#This Row],[% de jornada]]*IF(DATOS_[[#This Row],[% jornada reducida]]="",1,DATOS_[[#This Row],[% jornada reducida]]) -> 1 | CK46: =+(DATOS_[[#This Row],[F.fin.cal]]-DATOS_[[#This Row],[F.ini.cal]]+1)/($D$4-$D$3+1) -> 1 | CL46: =IF(OR(AND(DATOS_[[#This Row],[Fecha Fin Contrato]]<$D$3,DATOS_[[#This Row],[Fecha Fin Contrato]]<>""),DATOS_[[#This Row],[Fecha de Contratación]]>$D$4),"Fuera","Dentro") -> Dentro | CM46: {=IF(MAX(IF(DATOS_[id/cod]=DATOS_[[#This Row],[id/cod]],DATOS_[F.fin.cal]))=DATOS_[[#This Row],[F.fin.cal]],"Sí","NO")} -> Sí | CN46: =IF(AND(DATOS_[[#This Row],[% normaliz]]<>1,DATOS_[[#This Row],[% anualiz]]=1),"Sí","NO") -> NO | CO46: =IF(AND(DATOS_[[#This Row],[% normaliz]]=1,DATOS_[[#This Row],[% anualiz]]<>1),"Sí","NO") -> NO | CP46: =IF(AND(DATOS_[[#This Row],[% normaliz]]<>1,DATOS_[[#This Row],[% anualiz]]<>1),"Sí","NO") -> NO | CQ46: =+IF(DATOS_[[#This Row],[% normaliz]]*DATOS_[[#This Row],[% anualiz]]=1,"NO","Sí") -> NO | CR46: =(DATOS_[[#This Row],[S.BASE]]*(1/DATOS_[[#This Row],[% normaliz]])*(1/DATOS_[[#This Row],[% anualiz]]))*IF(DATOS_[[#This Row],[Check Equiparado]]="Sí",1,0) -> 10735.77 | CS46: =(SUMPRODUCT((RngTipo=$CS$7)*(rngAnualizable="Sí")*(rngNormalizable="Sí")*(DATOS_[[#This Row],[Conc.Sal.01]:[C.Extra.11]]))*(1/DATOS_[[#This Row],[% anualiz]])*(1/DATOS_[[#This Row],[% normaliz]]) +SUMPRODUCT((RngTipo=$CS$7)*(rngAnualizable="Sí")*(rngNormalizable="No")*(DATOS_[[#This Row],[Conc.Sal.01]:[C.Extra.11]]))*(1/DATOS_[[#This Row],[% anualiz]]) +SUMPRODUCT((RngTipo=$CS$7)*(rngAnualizable="No")*(rngNormalizable="Sí")*(DATOS_[[#This Row],[Conc.Sal.01]:[C.Extra.11]]))*(1/DATOS_[[#This Row],[% normaliz]]) +SUMPRODUCT((RngTipo=$CS$7)*(rngAnualizable="No")*(rngNormalizable="No")*(DATOS_[[#This Row],[Conc.Sal.01]:[C.Extra.11]]))) *IF(DATOS_[[#This Row],[Check Equiparado]]="Sí",1,0) -> 5845.56 | CT46: =+DATOS_[[#This Row],[SALARIO BASE Eq]]+DATOS_[[#This Row],[Tot COMPL.SAL Eq]] -> 16581.33 | CU46: {=(SUMPRODUCT((RngTipo=$CU$7)*(rngAnualizable="Sí")*(rngNormalizable="Sí")*(DATOS_[[#This Row],[Conc.Sal.01]:[C.Extra.11]]))*(1/DATOS_[[#This Row],[% anualiz]])*(1/DATOS_[[#This Row],[% normaliz]]) +SUMPRODUCT((RngTipo=$CU$7)*(rngAnualizable="Sí")*(rngNormalizable="No")*(DATOS_[[#This Row],[Conc.Sal.01]:[C.Extra.11]]))*(1/DATOS_[[#This Row],[% anualiz]]) +SUMPRODUCT((RngTipo=$CU$7)*(rngAnualizable="No")*(rngNormalizable="Sí")*(DATOS_[[#This Row],[Conc.Sal.01]:[C.Extra.11]]))*(1/DATOS_[[#This Row],[% normaliz]]) +SUMPRODUCT((RngTipo=$CU$7)*(rngAnualizable="No")*(rngNormalizable="No")*(DATOS_[[#This Row],[Conc.Sal.01]:[C.Extra.11]]))) *IF(DATOS_[[#This Row],[Check Equiparado]]="Sí",1,0)} -> 3107.26 | CV46: =+DATOS_[[#This Row],[TOTAL SALARIO Eq]]+DATOS_[[#This Row],[Tot Extrasalarial Eq]] -> 19688.59 | CW46: =DATOS_[[#This Row],[S.BASE]] -> 10735.77 | CX46: =+SUM(DATOS_[[#This Row],[Conc.Sal.01]:[Conc.Sal.30]]) -> 8952.82 | CY46: =+DATOS_[[#This Row],[SALARIO BASE Ef]]+DATOS_[[#This Row],[Tot COMPL.SAL Ef]] -> 19688.59 | CZ46: =+SUM(DATOS_[[#This Row],[C.Extra.01]:[C.Extra.11]]) -> 0 | DA46: =+DATOS_[[#This Row],[TOTAL SALARIO Ef]]+DATOS_[[#This Row],[Tot Extrasalarial Ef]] -> 19688.59 | DB46: =MIN(IF(DATOS_[[#This Row],[Fecha Fin Contrato]]="",$D$4,DATOS_[[#This Row],[Fecha Fin Contrato]]),$D$4)-MAX(DATOS_[[#This Row],[Fecha de Contratación]],$D$3)+1 -> 366 | DC46: =IF(COUNTIFS(DATOS_[id/cod],DATOS_[[#This Row],[id/cod]])>1,DATOS_[[#This Row],[id/cod]],"") | DD46: =(Inicio!$G$10-DATOS_[[#This Row],[Fecha Nacimiento]])/365.25 -> 62.49692 | DE46: =(Inicio!$G$10-DATOS_[[#This Row],[Fecha de Antigüedad]])/365.25 -> 14.395619 | DF46: =+VLOOKUP(DATOS_[[#This Row],[Clave de Contrato]],TblTiposContrato13[],3,FALSE) -> Completa | DG46: =+VLOOKUP(DATOS_[[#This Row],[Clave de Contrato]],TblTiposContrato13[],4,FALSE) -> Indefinido | DH46: =VLOOKUP(DATOS_[[#This Row],[Edad]],CONTRATOS!TblRngEdad,2,TRUE) -> 60 en adelante | DI46: =VLOOKUP(DATOS_[[#This Row],[Antigüedad]],TblRngAntg14[],2,TRUE) -> de 10 a 15 años
